{"id": "36335859", "title": "Lenovo ThinkPad T570 Intel® Core™ i5 i5-7200U Laptop 39.6 cm (15.6\") Full HD 8 GB DDR4-SDRAM 512 GB SSD NVIDIA® GeForce® 940MX Wi-Fi 5 (802.11ac) Windows 10 Pro Black", "brand": "Lenovo", "description": "Lenovo ThinkPad T570 Intel® Core™ i5 i5-7200U Laptop 39.6 cm (15.6\") Full HD 8 GB DDR4-SDRAM 512 GB SSD NVIDIA® GeForce® 940MX Wi-Fi 5 (802.11ac) Windows 10 Pro Black\n\n\nPerformance You Can Count With the responsiveness and efficiency of 7th generation Intel® Core™ processors, the Lenovo ThinkPad T570 lets you switch effortlessly between your favorite apps—increasing your productivity, creativity, or entertainment levels along the way. Super Fast SSD Storage Unlike a regular mechanical hard drive, a Solid-State Drive (SSD) has no moving parts and performs faster—including booting up (nearly 3X quicker), opening files (as much as 30% faster), and transferring files (around 200 MB/s, compared to 50-120 MB/s). As well as being quieter, it’s also more reliable, more rugged, and more secure. Tested for Battle, Built for Success Every ThinkPad laptop undergoes 12 stringent military tests and over 200 quality checks. So, you can rest easy knowing that your T570 is more than capable of surviving the bumps and bruises of everyday life. User-Friendly, Business-Friendly Easy to set up and roll out, the T570 is also quick to service, upgrade, and secure. From an everyday user to an IT technician, this business laptop is designed to make life (and work) easier for everyone. Less Really is More The T570 is available with Microsoft Windows 10 Pro Signature Edition. Now, you can say goodbye to unwanted trial ware, apps, or distractions. And hello to a faster laptop, from startup to shut down and everything in between. Forgot Your Password? Just Smile With Windows Hello’s advanced facial recognition and fingerprint technology, there’s no need to worry about remembering your password. Simply smile at the infrared camera or touch the fingerprint scanner to log in, quickly and securely. Make Light Work of Long Days With its two batteries and Power Bridge technology, the T570 gives you greater flexibility and up to 16 hours of power on a single charge—reducing the need to cart around a power cord or find a wall socket everywhere you go. For On-the-Go Productivity and Entertainment Weighing around 2 kg and just 22 mm thin, the T570 gives you portability, without sacrificing performance. Its 15.6\" FHD display delivers sharp, vibrant visuals—perfect for working on the go or kicking back to enjoy a movie. Stay Connected, Even When You’re Not With super-fast LTE-A (4G) connectivity, the T570 gives you prompt access to all your cloud data and apps—even if you are out of WiFi range. Look Sharp, Sound Sharper Conference calls are a breeze with the T570. As well as an HD webcam as standard, it has dual array microphones that cut down background noise—perfect for when you're dialing in from a busy office or your favorite diner. Intel® vPro Technology Delivering new productivity experiences for mobile business users, this leading-edge security technology makes enterprise-level manageability even more convenient and cost-effective. Now, you can better manage, protect, repair, or locate your deployed laptops from anywhere in the world. Extra Peace of Mind The T570 comes with a worldwide warranty as standard, enabling you to seek expert assistance and help in 160 countries across the globe. Enhanced TrackPad and TrackPoint By constantly listening to our customers, we have been able to refine the T570’s TrackPad and TrackPoint. With an improved design that lessens jumps or gaps when scrolling, these pointing devices offer a smoother, cleaner, and more accurate experience. Together with the award-winning ergonomic ThinkPad keyboard, the T570 will soon help you make light work of hard work.\n\n\nKey Specifications:\n- **Other features**: Maximum internal memory (64-bit): 32 GB\n- **Weight & dimensions**: Weight: 1.97 kg; Width: 365.8 mm; Depth: 252.8 mm; Height (front): 2 cm; Height (rear): 2.02 cm\n- **Sustainability**: Sustainability certificates: ENERGY STAR\n- **Certificates**: Compliance certificates: RoHS\n- **Security**: Password protection type: HDD, Power on, Supervisor\n- **Power**: AC adapter power: 65 W; AC adapter frequency: 50 - 60 Hz; AC adapter input voltage: 100 - 240 V\n- **Battery**: Number of battery cells: 3+4; Battery life (max): 13.8 h\n- **Processor special features**: Intel® Turbo Boost Technology: 2.0; Processor package size: 42 x 24 mm; Supported instruction sets: AVX 2.0, SSE4.1, SSE4.2; Processor code: SR2ZU; CPU configuration (max): 1; Graphics & IMC lithography: 14 nm; Intel Identity Protection Technology version: 1.00; Intel Smart Response Technology version: 1.00; Intel Stable Image Platform Program (SIPP) version: 0.00; Intel Secure Key Technology version: 1.00; Intel TSX-NI version: 0.00; Processor ARK ID: 95443\n- **Software**: Operating system installed: Windows 10 Pro; Operating system architecture: 64-bit\n- **Keyboard**: Pointing device: ThinkPad UltraNav\n- **Performance**: Motherboard chipset: Intel SoC\n- **Ports & interfaces**: USB 2.0 ports quantity: 0; USB 3.2 Gen 1 (3.1 Gen 1) Type-A ports quantity: 3; USB 3.2 Gen 1 (3.1 Gen 1) Type-C ports quantity: 0; HDMI ports quantity: 1; USB 3.2 Gen 2 (3.1 Gen 2) Type-A ports quantity: 0; USB 3.2 Gen 2 (3.1 Gen 2) Type-C ports quantity: 1; Ethernet LAN (RJ-45) ports: 1; HDMI version: 1.4b; DisplayPorts quantity: 0; Mini DisplayPorts quantity: 1; VGA (D-Sub) ports quantity: 0; Thunderbolt ports quantity: 0; Thunderbolt 3 ports quantity: 0; USB Sleep-and-Charge ports: 1\n- **Network**: Top Wi-Fi standard: Wi-Fi 5 (802.11ac); Mobile network generation: 4G; 4G standard: LTE; Wi-Fi standards: 802.11a, Wi-Fi 5 (802.11ac), 802.11b, 802.11g, Wi-Fi 4 (802.11n); Ethernet LAN data rates: 10,100,1000 Mbit/s; Bluetooth version: 4.1\n- **Camera**: Front camera resolution: 1280 x 720 pixels; Front camera signal format: 720p\n- **Audio**: Audio chip: Realtek ALC3268; Number of built-in speakers: 2; Speaker power: 2 W\n- **Graphics**: Discrete graphics card model: NVIDIA® GeForce® 940MX; On-board graphics card model: Intel® HD Graphics 620; Discrete graphics card memory: 2 GB; On-board graphics card base frequency: 300 MHz; On-board graphics card dynamic frequency (max): 1000 MHz; Maximum on-board graphics card memory: 32 GB; On-board graphics card DirectX version: 12.0; On-board graphics card OpenGL version: 4.4; On-board graphics card ID: 0x5916\n- **Storage**: Total storage capacity: 512 GB; Storage media: SSD; Number of SSDs installed: 1; SSD capacity: 512 GB; SSD form factor: M.2; Compatible memory cards: MMC, SD, SDHC, SDXC\n- **Memory**: Internal memory: 8 GB; Maximum internal memory: 32 GB; Internal memory type: DDR4-SDRAM; Memory clock speed: 2133 MHz; Memory form factor: SO-DIMM; Memory layout (slots x size): 1 x 8 GB; Memory slots: 2x SO-DIMM\n- **Processor**: Processor family: Intel® Core™ i5; Processor manufacturer: Intel; Processor model: i5-7200U; Processor frequency: 2.5 GHz; Processor generation: 7th gen Intel® Core™ i5; Processor cores: 2; Processor threads: 4; Processor boost frequency: 3.1 GHz; System bus rate: 4 GT/s; Processor cache: 3 MB; Processor cache type: Smart Cache; Processor socket: BGA 1356; Processor lithography: 14 nm; Processor operating modes: 64-bit; Processor codename: Kaby Lake; Bus type: OPI; Stepping: H0; Thermal Design Power (TDP): 15 W; Configurable TDP-up frequency: 2.7 GHz; Configurable TDP-up: 25 W; Configurable TDP-down: 7.5 W; Configurable TDP-down frequency: 0.8 GHz; Tjunction: 100 °C; Maximum number of PCI Express lanes: 12; PCI Express slots version: 3.0; PCI Express configurations: 1x2+2x1, 1x4, 2x2, 4x1\n- **Display**: Display diagonal: 39.6 cm (15.6\"); Display resolution: 1920 x 1080 pixels; HD type: Full HD; Native aspect ratio: 16:9; Display surface: Matt; Screen shape: Flat\n- **Design**: Product type: Laptop; Product colour: Black; Form factor: Clamshell; Housing material: Glass fibre; Market positioning: Business", "image_url": "https://images.icecat.biz/img/gallery_mediums/35993028_2896341224.jpg", "price": 1358.84, "currency": "EUR", "categories": ["Laptops"], "attrs": {"Product type": "Laptop", "Product colour": "Black", "Form factor": "Clamshell", "Housing material": "Glass fibre", "Market positioning": "Business", "Display diagonal": "39.6 cm (15.6\")", "Display resolution": "1920 x 1080 pixels", "HD type": "Full HD", "Native aspect ratio": "16:9", "Display surface": "Matt", "Screen shape": "Flat", "Processor family": "Intel® Core™ i5", "Processor manufacturer": "Intel", "Processor model": "i5-7200U", "Processor frequency": "2.5 GHz", "Processor generation": "7th gen Intel® Core™ i5", "Processor cores": "2", "Processor threads": "4", "Processor boost frequency": "3.1 GHz", "System bus rate": "4 GT/s", "Processor cache": "3 MB", "Processor cache type": "Smart Cache", "Processor socket": "BGA 1356", "Processor lithography": "14 nm", "Processor operating modes": "64-bit", "Processor codename": "Kaby Lake", "Bus type": "OPI", "Stepping": "H0", "Thermal Design Power (TDP)": "15 W", "Configurable TDP-up frequency": "2.7 GHz", "Configurable TDP-up": "25 W", "Configurable TDP-down": "7.5 W", "Configurable TDP-down frequency": "0.8 GHz", "Tjunction": "100 °C", "Maximum number of PCI Express lanes": "12", "PCI Express slots version": "3.0", "PCI Express configurations": "1x2+2x1, 1x4, 2x2, 4x1", "Internal memory": "8 GB", "Maximum internal memory": "32 GB", "Internal memory type": "DDR4-SDRAM", "Memory clock speed": "2133 MHz", "Memory form factor": "SO-DIMM", "Memory layout (slots x size)": "1 x 8 GB", "Memory slots": "2x SO-DIMM", "Total storage capacity": "512 GB", "Storage media": "SSD", "Number of SSDs installed": "1", "SSD capacity": "512 GB", "SSD form factor": "M.2", "Compatible memory cards": "MMC, SD, SDHC, SDXC", "Discrete graphics card model": "NVIDIA® GeForce® 940MX", "On-board graphics card model": "Intel® HD Graphics 620", "Discrete graphics card memory": "2 GB", "On-board graphics card base frequency": "300 MHz", "On-board graphics card dynamic frequency (max)": "1000 MHz", "Maximum on-board graphics card memory": "32 GB", "On-board graphics card DirectX version": "12.0", "On-board graphics card OpenGL version": "4.4", "On-board graphics card ID": "0x5916", "Audio chip": "Realtek ALC3268", "Number of built-in speakers": "2", "Speaker power": "2 W", "Front camera resolution": "1280 x 720 pixels", "Front camera signal format": "720p", "Top Wi-Fi standard": "Wi-Fi 5 (802.11ac)", "Mobile network generation": "4G", "4G standard": "LTE", "Wi-Fi standards": "802.11a, Wi-Fi 5 (802.11ac), 802.11b, 802.11g, Wi-Fi 4 (802.11n)", "Ethernet LAN data rates": "10,100,1000 Mbit/s", "Bluetooth version": "4.1", "USB 20 ports quantity": "0", "USB 32 Gen 1 (31 Gen 1) Type-A ports quantity": "3", "USB 32 Gen 1 (31 Gen 1) Type-C ports quantity": "0", "HDMI ports quantity": "1", "USB 32 Gen 2 (31 Gen 2) Type-A ports quantity": "0", "USB 32 Gen 2 (31 Gen 2) Type-C ports quantity": "1", "Ethernet LAN (RJ-45) ports": "1", "HDMI version": "1.4b", "DisplayPorts quantity": "0", "Mini DisplayPorts quantity": "1", "VGA (D-Sub) ports quantity": "0", "Thunderbolt ports quantity": "0", "Thunderbolt 3 ports quantity": "0", "USB Sleep-and-Charge ports": "1", "Motherboard chipset": "Intel SoC", "Pointing device": "ThinkPad UltraNav", "Operating system installed": "Windows 10 Pro", "Operating system architecture": "64-bit", "Intel® Turbo Boost Technology": "2.0", "Processor package size": "42 x 24 mm", "Supported instruction sets": "AVX 2.0, SSE4.1, SSE4.2", "Processor code": "SR2ZU", "CPU configuration (max)": "1", "Graphics & IMC lithography": "14 nm", "Intel Identity Protection Technology version": "1.00", "Intel Smart Response Technology version": "1.00", "Intel Stable Image Platform Program (SIPP) version": "0.00", "Intel Secure Key Technology version": "1.00", "Intel TSX-NI version": "0.00", "Processor ARK ID": "95443", "Number of battery cells": "3+4", "Battery life (max)": "13.8 h", "AC adapter power": "65 W", "AC adapter frequency": "50 - 60 Hz", "AC adapter input voltage": "100 - 240 V", "Password protection type": "HDD, Power on, Supervisor", "Compliance certificates": "RoHS", "Sustainability certificates": "ENERGY STAR", "Weight": "1.97 kg", "Width": "365.8 mm", "Depth": "252.8 mm", "Height (front)": "2 cm", "Height (rear)": "2.02 cm", "Maximum internal memory (64-bit)": "32 GB"}, "attr_keys": ["4G standard", "AC adapter frequency", "AC adapter input voltage", "AC adapter power", "Audio chip", "Battery life (max)", "Bluetooth version", "Bus type", "CPU configuration (max)", "Compatible memory cards", "Compliance certificates", "Configurable TDP-down", "Configurable TDP-down frequency", "Configurable TDP-up", "Configurable TDP-up frequency", "Depth", "Discrete graphics card memory", "Discrete graphics card model", "Display diagonal", "Display resolution", "Display surface", "DisplayPorts quantity", "Ethernet LAN (RJ-45) ports", "Ethernet LAN data rates", "Form factor", "Front camera resolution", "Front camera signal format", "Graphics & IMC lithography", "HD type", "HDMI ports quantity", "HDMI version", "Height (front)", "Height (rear)", "Housing material", "Intel Identity Protection Technology version", "Intel Secure Key Technology version", "Intel Smart Response Technology version", "Intel Stable Image Platform Program (SIPP) version", "Intel TSX-NI version", "Intel® Turbo Boost Technology", "Internal memory", "Internal memory type", "Market positioning", "Maximum internal memory", "Maximum internal memory (64-bit)", "Maximum number of PCI Express lanes", "Maximum on-board graphics card memory", "Memory clock speed", "Memory form factor", "Memory layout (slots x size)", "Memory slots", "Mini DisplayPorts quantity", "Mobile network generation", "Motherboard chipset", "Native aspect ratio", "Number of SSDs installed", "Number of battery cells", "Number of built-in speakers", "On-board graphics card DirectX version", "On-board graphics card ID", "On-board graphics card OpenGL version", "On-board graphics card base frequency", "On-board graphics card dynamic frequency (max)", "On-board graphics card model", "Operating system architecture", "Operating system installed", "PCI Express configurations", "PCI Express slots version", "Password protection type", "Pointing device", "Processor ARK ID", "Processor boost frequency", "Processor cache", "Processor cache type", "Processor code", "Processor codename", "Processor cores", "Processor family", "Processor frequency", "Processor generation", "Processor lithography", "Processor manufacturer", "Processor model", "Processor operating modes", "Processor package size", "Processor socket", "Processor threads", "Product colour", "Product type", "SSD capacity", "SSD form factor", "Screen shape", "Speaker power", "Stepping", "Storage media", "Supported instruction sets", "Sustainability certificates", "System bus rate", "Thermal Design Power (TDP)", "Thunderbolt 3 ports quantity", "Thunderbolt ports quantity", "Tjunction", "Top Wi-Fi standard", "Total storage capacity", "USB 20 ports quantity", "USB 32 Gen 1 (31 Gen 1) Type-A ports quantity", "USB 32 Gen 1 (31 Gen 1) Type-C ports quantity", "USB 32 Gen 2 (31 Gen 2) Type-A ports quantity", "USB 32 Gen 2 (31 Gen 2) Type-C ports quantity", "USB Sleep-and-Charge ports", "VGA (D-Sub) ports quantity", "Weight", "Wi-Fi standards", "Width"]}
{"id": "135330915", "title": "Lenovo ThinkPad T14 Gen 4 (Intel) Intel® Core™ i7 i7-1355U Laptop 35.6 cm (14\") WUXGA 16 GB DDR5-SDRAM 512 GB SSD Wi-Fi 6E (802.11ax) Windows 11 Pro English Black", "brand": "Lenovo", "description": "Lenovo ThinkPad T14 Gen 4 (Intel) Intel® Core™ i7 i7-1355U Laptop 35.6 cm (14\") WUXGA 16 GB DDR5-SDRAM 512 GB SSD Wi-Fi 6E (802.11ax) Windows 11 Pro English Black\n\n\nKey Specifications:\n- **Weight & dimensions**: Weight: 1.37 kg; Width: 317.7 mm; Depth: 226.9 mm; Height: 17.9 mm\n- **Certificates**: Certification: ENERGY STAR,TCO,EPEAT Gold,RoHS\n- **Security**: Cable lock slot type: Kensington; Trusted Platform Module (TPM) version: 2.0\n- **Power**: AC adapter power: 65 W\n- **Battery**: Battery capacity: 52.5 Wh\n- **Software**: Operating system installed: Windows 11 Pro; Operating system language: English\n- **Keyboard**: Pointing device: ThinkPad UltraNav; Keyboard language: English\n- **Performance**: Motherboard chipset: Intel SoC\n- **Ports & interfaces**: USB 2.0 ports quantity: 0; USB 3.2 Gen 1 (3.1 Gen 1) Type-A ports quantity: 2; USB 3.2 Gen 1 (3.1 Gen 1) Type-C ports quantity: 0; HDMI ports quantity: 1; Ethernet LAN (RJ-45) ports: 1; HDMI version: 2.1; Thunderbolt 4 ports quantity: 2\n- **Network**: Top Wi-Fi standard: Wi-Fi 6E (802.11ax); Wi-Fi standards: Wi-Fi 6E (802.11ax); Antenna type: 2x2; WLAN controller model: Intel Wi-Fi 6E AX211; WLAN controller manufacturer: Intel; Ethernet LAN data rates: 100,1000 Mbit/s; Bluetooth version: 5.3; WWAN: Upgradable\n- **Camera**: Front camera resolution: 1920 x 1080 pixels; Front camera HD type: Full HD; Privacy type: Privacy shutter\n- **Audio**: Audio chip: Realtek ALC3287; Number of built-in speakers: 2; Speaker power: 2 W; Number of microphones: 2\n- **Graphics**: Discrete graphics card model: Not available; On-board graphics card model: Intel Iris Xe Graphics; On-board GPU manufacturer: Intel\n- **Storage**: Total storage capacity: 512 GB; Storage media: SSD; Total SSDs capacity: 512 GB; Number of SSDs installed: 1; SSD capacity: 512 GB; SSD interface: PCI Express 4.0; SSD form factor: M.2\n- **Memory**: Internal memory: 16 GB; Maximum internal memory: 32 GB; Internal memory type: DDR5-SDRAM; Memory clock speed: 5200 MHz; Memory form factor: On-board + SO-DIMM\n- **Processor**: Processor family: Intel® Core™ i7; Processor manufacturer: Intel; Processor model: i7-1355U; Processor frequency: 1.7 GHz; Processor cores: 10; Processor boost frequency: 5 GHz\n- **Display**: Display diagonal: 35.6 cm (14\"); Display resolution: 1920 x 1200 pixels; HD type: WUXGA; Panel type: IPS; Native aspect ratio: 16:10; Display brightness: 300 cd/m²; RGB colour space: NTSC; Colour gamut: 45%\n- **Design**: Product type: Laptop; Product colour: Black; Form factor: Clamshell; Colour name: Thunder Black", "image_url": "https://images.icecat.biz/img/gallery_mediums/28bf185905f540d1145619796665cddcaafc353c.jpg", "price": 1382.71, "currency": "EUR", "categories": ["Laptops"], "attrs": {"Product type": "Laptop", "Product colour": "Black", "Form factor": "Clamshell", "Colour name": "Thunder Black", "Display diagonal": "35.6 cm (14\")", "Display resolution": "1920 x 1200 pixels", "HD type": "WUXGA", "Panel type": "IPS", "Native aspect ratio": "16:10", "Display brightness": "300 cd/m²", "RGB colour space": "NTSC", "Colour gamut": "45%", "Processor family": "Intel® Core™ i7", "Processor manufacturer": "Intel", "Processor model": "i7-1355U", "Processor frequency": "1.7 GHz", "Processor cores": "10", "Processor boost frequency": "5 GHz", "Internal memory": "16 GB", "Maximum internal memory": "32 GB", "Internal memory type": "DDR5-SDRAM", "Memory clock speed": "5200 MHz", "Memory form factor": "On-board + SO-DIMM", "Total storage capacity": "512 GB", "Storage media": "SSD", "Total SSDs capacity": "512 GB", "Number of SSDs installed": "1", "SSD capacity": "512 GB", "SSD interface": "PCI Express 4.0", "SSD form factor": "M.2", "Discrete graphics card model": "Not available", "On-board graphics card model": "Intel Iris Xe Graphics", "On-board GPU manufacturer": "Intel", "Audio chip": "Realtek ALC3287", "Number of built-in speakers": "2", "Speaker power": "2 W", "Number of microphones": "2", "Front camera resolution": "1920 x 1080 pixels", "Front camera HD type": "Full HD", "Privacy type": "Privacy shutter", "Top Wi-Fi standard": "Wi-Fi 6E (802.11ax)", "Wi-Fi standards": "Wi-Fi 6E (802.11ax)", "Antenna type": "2x2", "WLAN controller model": "Intel Wi-Fi 6E AX211", "WLAN controller manufacturer": "Intel", "Ethernet LAN data rates": "100,1000 Mbit/s", "Bluetooth version": "5.3", "WWAN": "Upgradable", "USB 20 ports quantity": "0", "USB 32 Gen 1 (31 Gen 1) Type-A ports quantity": "2", "USB 32 Gen 1 (31 Gen 1) Type-C ports quantity": "0", "HDMI ports quantity": "1", "Ethernet LAN (RJ-45) ports": "1", "HDMI version": "2.1", "Thunderbolt 4 ports quantity": "2", "Motherboard chipset": "Intel SoC", "Pointing device": "ThinkPad UltraNav", "Keyboard language": "English", "Operating system installed": "Windows 11 Pro", "Operating system language": "English", "Battery capacity": "52.5 Wh", "AC adapter power": "65 W", "Cable lock slot type": "Kensington", "Trusted Platform Module (TPM) version": "2.0", "Certification": "ENERGY STAR,TCO,EPEAT Gold,RoHS", "Weight": "1.37 kg", "Width": "317.7 mm", "Depth": "226.9 mm", "Height": "17.9 mm"}, "attr_keys": ["AC adapter power", "Antenna type", "Audio chip", "Battery capacity", "Bluetooth version", "Cable lock slot type", "Certification", "Colour gamut", "Colour name", "Depth", "Discrete graphics card model", "Display brightness", "Display diagonal", "Display resolution", "Ethernet LAN (RJ-45) ports", "Ethernet LAN data rates", "Form factor", "Front camera HD type", "Front camera resolution", "HD type", "HDMI ports quantity", "HDMI version", "Height", "Internal memory", "Internal memory type", "Keyboard language", "Maximum internal memory", "Memory clock speed", "Memory form factor", "Motherboard chipset", "Native aspect ratio", "Number of SSDs installed", "Number of built-in speakers", "Number of microphones", "On-board GPU manufacturer", "On-board graphics card model", "Operating system installed", "Operating system language", "Panel type", "Pointing device", "Privacy type", "Processor boost frequency", "Processor cores", "Processor family", "Processor frequency", "Processor manufacturer", "Processor model", "Product colour", "Product type", "RGB colour space", "SSD capacity", "SSD form factor", "SSD interface", "Speaker power", "Storage media", "Thunderbolt 4 ports quantity", "Top Wi-Fi standard", "Total SSDs capacity", "Total storage capacity", "Trusted Platform Module (TPM) version", "USB 20 ports quantity", "USB 32 Gen 1 (31 Gen 1) Type-A ports quantity", "USB 32 Gen 1 (31 Gen 1) Type-C ports quantity", "WLAN controller manufacturer", "WLAN controller model", "WWAN", "Weight", "Wi-Fi standards", "Width"]}
{"id": "30223774", "title": "Lenovo ThinkPad T440p Intel® Core™ i7 i7-4910MQ Laptop 35.6 cm (14\") Full HD 16 GB DDR3L-SDRAM 500 GB Windows 7 Professional Black", "brand": "Lenovo", "description": "Lenovo ThinkPad T440p Intel® Core™ i7 i7-4910MQ Laptop 35.6 cm (14\") Full HD 16 GB DDR3L-SDRAM 500 GB Windows 7 Professional Black\n\n\n4th Generation Intel® Core™ Processors 4th generation Intel® Core™ processors deliver the performance to increase productivity for your business. Devices turn on in an instant and are always up-to-date. You can multitask quickly and move effortlessly between applications, collaborate wirelessly in a high quality videoconference — all with the convenience of longer battery life. Plus, you can guard against identity theft and ensure safe access to your network with built-in security features. In fact, the only thing more amazing than an Intel Core processor-based PC is what your users will do with it. Windows 8 Select a model with the new Windows 8 or Windows 8 Pro to enjoy the best of both work and play. Precision Keyboard Enhanced for Windows 8 Full-sized and spill-resistant, the ergonomic ThinkPad keyboard is renowned for its array of keys, excellent feel and TrackPoint® pointing. Optimized for Windows 8 with convenient multimedia buttons and immediate access to view apps, it has LED status indicators and function-lock capability. With a larger, smooth trackpad and 5-point click integration—indicated by subtle bumps and stripes, the keyboard can be configured multiple ways, while the optional backlight makes working in the dark effortless. 14” HD, HD+ and FHD Display The powerful HD, HD+, and FHD display options deliver bright, crisp visuals and a wide viewing range. Anti-glare technology makes the screen comfortable to look at even over the long haul. NVIDIA GeForce Graphics With the NVIDIA® GeForce® GT 730M graphics processor, you are assured of a richer visual and faster gaming experience. You can also preview/create HD video up to 4x faster and perfect/share photos in less than half the time Massive Storage and USB 3.0 Store data locally on your choice of a standard hard disc drive or ultrafast solid state drive. And transfer data ten times faster with two USB 3.0 ports. Ultradurable and MIL-SPEC Tested The T440p meets eight US military-spec tests for ruggedness, durability, and quality: high pressure, humidity, vibration, high temperature, temperature shock, low pressure (15,000 ft), low temperature, and dust. In addition, innovative roll-cage technology, a glass-fiber reinforced top and a light-weight carbon-fiber reinforced bottom add extra strength and rigidity. Dolby Advanced Audio V2 A suite of audio technology from Dolby delivers a crisp, clear cinematic surround sound for music, movies, games, and more. Hear every detail clearly and experience the full impact of your entertainment anywhere. VGA Port A VGA port for projector connections in conference rooms is still a business must-have, and a native VGA means no dongles to buy/lose/replace.\n\n\nKey Specifications:\n- **Other features**: Maximum internal memory (64-bit): 16 GB\n- **Weight & dimensions**: Width: 335 mm; Depth: 229.1 mm; Height (front): 2.79 cm; Height (rear): 3 cm\n- **Sustainability**: Sustainability certificates: EPEAT Gold, ENERGY STAR\n- **Certificates**: Compliance certificates: RoHS; Certification: MIL-STD-810G\n- **Security**: Password protection type: HDD, Power on, Supervisor\n- **Power**: AC adapter frequency: 50 - 60 Hz; AC adapter input voltage: 100 - 240 V\n- **Battery**: Battery technology: Lithium-Ion (Li-Ion)\n- **Processor special features**: Intel® Turbo Boost Technology: 2.0; Processor package size: 37.5 x 37.5 x 4.7 mm; Supported instruction sets: AVX 2.0, SSE4.1, SSE4.2; Processor code: SR15K; CPU configuration (max): 1; Intel Identity Protection Technology version: 1.00; Intel Secure Key Technology version: 1.00; Intel TSX-NI version: 0.00; Processor ARK ID: 78939\n- **Software**: Operating system installed: Windows 7 Professional; Operating system architecture: 64-bit\n- **Keyboard**: Pointing device: ThinkPad UltraNav\n- **Ports & interfaces**: USB 2.0 ports quantity: 2; USB 3.2 Gen 1 (3.1 Gen 1) Type-A ports quantity: 2; USB 3.2 Gen 1 (3.1 Gen 1) Type-C ports quantity: 0; HDMI ports quantity: 0; USB 3.2 Gen 2 (3.1 Gen 2) Type-A ports quantity: 0; USB 3.2 Gen 2 (3.1 Gen 2) Type-C ports quantity: 0; Ethernet LAN (RJ-45) ports: 1; DisplayPorts quantity: 0; Mini DisplayPorts quantity: 1; VGA (D-Sub) ports quantity: 1; Thunderbolt 3 ports quantity: 0; USB Sleep-and-Charge ports: 1\n- **Network**: Ethernet LAN data rates: 10,100,1000 Mbit/s; Bluetooth version: 4.0\n- **Camera**: Front camera resolution: 1280 x 720 pixels; Front camera signal format: 720p; Front camera HD type: HD\n- **Audio**: Audio chip: Realtek ALC3232; Audio system: Dolby Advanced Audio; Number of built-in speakers: 2; Speaker power: 1 W\n- **Graphics**: On-board graphics card model: Intel® HD Graphics 4600; On-board graphics card family: Intel® HD Graphics; On-board graphics card base frequency: 400 MHz; On-board graphics card dynamic frequency (max): 1300 MHz; Maximum on-board graphics card memory: 1.74 GB; On-board graphics card DirectX version: 11.1; On-board graphics card ID: 0x416\n- **Storage**: Total storage capacity: 500 GB; Optical drive type: DVD±RW; Compatible memory cards: MMC, SD, SDHC, SDXC\n- **Memory**: Internal memory: 16 GB; Maximum internal memory: 16 GB; Internal memory type: DDR3L-SDRAM; Memory clock speed: 1600 MHz; Memory form factor: SO-DIMM; Memory slots: 2x SO-DIMM\n- **Processor**: Processor family: Intel® Core™ i7; Processor manufacturer: Intel; Processor model: i7-4910MQ; Processor frequency: 2.9 GHz; Processor generation: 4th gen Intel® Core™ i7; Processor cores: 4; Processor threads: 8; Processor boost frequency: 3.9 GHz; Processor cache: 8 MB; Processor cache type: Smart Cache; Processor socket: PGA946; Processor lithography: 22 nm; Processor operating modes: 64-bit; Processor codename: Haswell; Bus type: DMI2; Stepping: C0; Thermal Design Power (TDP): 47 W; Tjunction: 100 °C; Maximum number of PCI Express lanes: 16; PCI Express slots version: 3.0; PCI Express configurations: 1x8, 2x8, 1x8+2x4\n- **Display**: Display diagonal: 35.6 cm (14\"); Display resolution: 1920 x 1080 pixels; HD type: Full HD; Native aspect ratio: 16:9; Display surface: Matt\n- **Design**: Product type: Laptop; Product colour: Black; Form factor: Clamshell; Housing material: Glass-reinforced plastic (GRP); Market positioning: Business", "image_url": "https://images.icecat.biz/img/gallery_mediums/29898716_4490.jpg", "price": 1203.7, "currency": "EUR", "categories": ["Laptops"], "attrs": {"Product type": "Laptop", "Product colour": "Black", "Form factor": "Clamshell", "Housing material": "Glass-reinforced plastic (GRP)", "Market positioning": "Business", "Display diagonal": "35.6 cm (14\")", "Display resolution": "1920 x 1080 pixels", "HD type": "Full HD", "Native aspect ratio": "16:9", "Display surface": "Matt", "Processor family": "Intel® Core™ i7", "Processor manufacturer": "Intel", "Processor model": "i7-4910MQ", "Processor frequency": "2.9 GHz", "Processor generation": "4th gen Intel® Core™ i7", "Processor cores": "4", "Processor threads": "8", "Processor boost frequency": "3.9 GHz", "Processor cache": "8 MB", "Processor cache type": "Smart Cache", "Processor socket": "PGA946", "Processor lithography": "22 nm", "Processor operating modes": "64-bit", "Processor codename": "Haswell", "Bus type": "DMI2", "Stepping": "C0", "Thermal Design Power (TDP)": "47 W", "Tjunction": "100 °C", "Maximum number of PCI Express lanes": "16", "PCI Express slots version": "3.0", "PCI Express configurations": "1x8, 2x8, 1x8+2x4", "Internal memory": "16 GB", "Maximum internal memory": "16 GB", "Internal memory type": "DDR3L-SDRAM", "Memory clock speed": "1600 MHz", "Memory form factor": "SO-DIMM", "Memory slots": "2x SO-DIMM", "Total storage capacity": "500 GB", "Optical drive type": "DVD±RW", "Compatible memory cards": "MMC, SD, SDHC, SDXC", "On-board graphics card model": "Intel® HD Graphics 4600", "On-board graphics card family": "Intel® HD Graphics", "On-board graphics card base frequency": "400 MHz", "On-board graphics card dynamic frequency (max)": "1300 MHz", "Maximum on-board graphics card memory": "1.74 GB", "On-board graphics card DirectX version": "11.1", "On-board graphics card ID": "0x416", "Audio chip": "Realtek ALC3232", "Audio system": "Dolby Advanced Audio", "Number of built-in speakers": "2", "Speaker power": "1 W", "Front camera resolution": "1280 x 720 pixels", "Front camera signal format": "720p", "Front camera HD type": "HD", "Ethernet LAN data rates": "10,100,1000 Mbit/s", "Bluetooth version": "4.0", "USB 20 ports quantity": "2", "USB 32 Gen 1 (31 Gen 1) Type-A ports quantity": "2", "USB 32 Gen 1 (31 Gen 1) Type-C ports quantity": "0", "HDMI ports quantity": "0", "USB 32 Gen 2 (31 Gen 2) Type-A ports quantity": "0", "USB 32 Gen 2 (31 Gen 2) Type-C ports quantity": "0", "Ethernet LAN (RJ-45) ports": "1", "DisplayPorts quantity": "0", "Mini DisplayPorts quantity": "1", "VGA (D-Sub) ports quantity": "1", "Thunderbolt 3 ports quantity": "0", "USB Sleep-and-Charge ports": "1", "Pointing device": "ThinkPad UltraNav", "Operating system installed": "Windows 7 Professional", "Operating system architecture": "64-bit", "Intel® Turbo Boost Technology": "2.0", "Processor package size": "37.5 x 37.5 x 4.7 mm", "Supported instruction sets": "AVX 2.0, SSE4.1, SSE4.2", "Processor code": "SR15K", "CPU configuration (max)": "1", "Intel Identity Protection Technology version": "1.00", "Intel Secure Key Technology version": "1.00", "Intel TSX-NI version": "0.00", "Processor ARK ID": "78939", "Battery technology": "Lithium-Ion (Li-Ion)", "AC adapter frequency": "50 - 60 Hz", "AC adapter input voltage": "100 - 240 V", "Password protection type": "HDD, Power on, Supervisor", "Compliance certificates": "RoHS", "Certification": "MIL-STD-810G", "Sustainability certificates": "EPEAT Gold, ENERGY STAR", "Width": "335 mm", "Depth": "229.1 mm", "Height (front)": "2.79 cm", "Height (rear)": "3 cm", "Maximum internal memory (64-bit)": "16 GB"}, "attr_keys": ["AC adapter frequency", "AC adapter input voltage", "Audio chip", "Audio system", "Battery technology", "Bluetooth version", "Bus type", "CPU configuration (max)", "Certification", "Compatible memory cards", "Compliance certificates", "Depth", "Display diagonal", "Display resolution", "Display surface", "DisplayPorts quantity", "Ethernet LAN (RJ-45) ports", "Ethernet LAN data rates", "Form factor", "Front camera HD type", "Front camera resolution", "Front camera signal format", "HD type", "HDMI ports quantity", "Height (front)", "Height (rear)", "Housing material", "Intel Identity Protection Technology version", "Intel Secure Key Technology version", "Intel TSX-NI version", "Intel® Turbo Boost Technology", "Internal memory", "Internal memory type", "Market positioning", "Maximum internal memory", "Maximum internal memory (64-bit)", "Maximum number of PCI Express lanes", "Maximum on-board graphics card memory", "Memory clock speed", "Memory form factor", "Memory slots", "Mini DisplayPorts quantity", "Native aspect ratio", "Number of built-in speakers", "On-board graphics card DirectX version", "On-board graphics card ID", "On-board graphics card base frequency", "On-board graphics card dynamic frequency (max)", "On-board graphics card family", "On-board graphics card model", "Operating system architecture", "Operating system installed", "Optical drive type", "PCI Express configurations", "PCI Express slots version", "Password protection type", "Pointing device", "Processor ARK ID", "Processor boost frequency", "Processor cache", "Processor cache type", "Processor code", "Processor codename", "Processor cores", "Processor family", "Processor frequency", "Processor generation", "Processor lithography", "Processor manufacturer", "Processor model", "Processor operating modes", "Processor package size", "Processor socket", "Processor threads", "Product colour", "Product type", "Speaker power", "Stepping", "Supported instruction sets", "Sustainability certificates", "Thermal Design Power (TDP)", "Thunderbolt 3 ports quantity", "Tjunction", "Total storage capacity", "USB 20 ports quantity", "USB 32 Gen 1 (31 Gen 1) Type-A ports quantity", "USB 32 Gen 1 (31 Gen 1) Type-C ports quantity", "USB 32 Gen 2 (31 Gen 2) Type-A ports quantity", "USB 32 Gen 2 (31 Gen 2) Type-C ports quantity", "USB Sleep-and-Charge ports", "VGA (D-Sub) ports quantity", "Width"]}
{"id": "3875254", "title": "Lenovo ThinkPad W500 T9800-2.93G 320GB Intel® Core™2 Duo 39.1 cm (15.4\") 4 GB DDR3-SDRAM AMD Mobility FireGL V5700 Windows 7 Professional", "brand": "Neomounts", "description": "Lenovo ThinkPad W500 T9800-2.93G 320GB Intel® Core™2 Duo 39.1 cm (15.4\") 4 GB DDR3-SDRAM AMD Mobility FireGL V5700 Windows 7 Professional\n\n\nThe superhero of mobile workstations Faster than a speeding bullet, W Series is our most powerful, responsive ThinkPad® ever! Plow through computationally and graphics-intensive applications with lightning-fast Intel® processors, advanced nVIDIA® graphics, cutting-edge technology and the durability and rock-solid reliability you'd expect from Lenovo's ultimate mobile workstation. Unstoppable performance - Powerful Intel® Core™ i7 Quadcore Extreme processors with Turbo Boost technology, Hyper-Threading technology and Smart Cache (on select models) give you more power when you need it most and make multitasking even easier. - Intel® Core™2 processors and Intel® Core™ i7 with Intel Active Management Technology (AMT) (on select models) offer superior performance along with enhanced management and security. - W Series laptops come preloaded with up to Windows® 7 OS for a premium user experience. - Hard drives up to 640GB and RAID 0, RAID 1 gives you more reliable storage. - Solid-state drives (SSDs) offer improved performance, reliability and battery life. - High-performing DDR3 memory lowers power consumption. while providing high capacity. - Intel® Turbo Memory and Turbo Boost helps speed boot time, loads applications faster and save energy. Graphics horsepower - The nVIDIA® Quadro 3D FX® MXM-based graphics solution on select W Series mobile workstations is stable, compatible and optimized for all professional applications. - OpenGL (Open Graphics Library) with up to 1GB of dedicated video memory enables graphic-intensive applications. - High-resolution, premium WSXGA+ or WUXGA ( W500, W700) - HD/HD + FHD/FHD Multi-touch ( W510) panels provide an improved viewing experience. - Next-generation DisplayPort technology provides clearer, crisper images and a larger viewing area. - ThinkPad W700 and W510 mobile workstations offer X-Rite® PANTONE® color calibration for greater image accuracy, more precise color matching and a consistently true display. - W510 models feature a 95% NTSC gamut, multitouch panel for enhanced true-life 2-D and 3-D images and easy-to-use touch-screen technology. Palm-rest digitizer and pen ThinkPad W700 mobile workstations offer a 120mm x 80mm Wacom® palm-rest digitizer and pen, ideal for digital content creation and CAD/CAM applications. The digitizer can be configured to map to the entire screen or a user-defined area, and is compatible with a wide range of applications, from Windows® Paint to Adobe® Photoshop®. Dual-screen functionality The ThinkPad W700ds features a second, retractable 10.6\" screen that expands the display area by 39%. Dual-screen functionality lets you work in multiple applications simultaneously without switching views or compromising your workspace. Enhance your productivity and enjoy a more desktop-like computing experience! ISV certifications Photographers, light CAD/CAM users, digital content creators and other industry pros require proven performance and stability with today's demanding applications. An extensive independent software vendor testing and certification process verifies that your ThinkPad W Series can run some of the most demanding, graphics-intensive workstation applications. Built-in solutions and security The Lenovo Advantage includes great warranty protection and superior support and services. But there's more, such as our exclusive ThinkVantage® Technologies – tools, software and services that help you deploy, connect, protect and support your Lenovo notebook. Among them are: - Rescue and Recovery™: Recover from system crashes quickly, even if the primary operating system will not boot. - Active Protection System™: Like an airbag's sensor, Active Protection System can detect sudden changes in motion and temporarily stop the hard drive to help protect it from damage (not applicable to models with Solid State Drives). Ultimate connectivity Power and portability mean little if you can't get – and stay – connected. So ThinkPad W Series mobile workstations offer a wide range of connectivity options. - Wireless LAN - Wireless WAN - Gigabit Ethernet - Bluetooth\n\n\nKey Specifications:\n- **Other features**: Type: PC; Dimensions (WxDxH): 357.5 x 255 x 33.5 mm; Intel segment tagging: Professional\n- **Weight & dimensions**: Weight: 2.63 kg\n- **Battery**: Number of battery cells: 6\n- **Processor special features**: Processor package size: 35 x 35 mm; Processor code: SLGES; Processor ARK ID: 37005\n- **Software**: Operating system installed: Windows 7 Professional\n- **Keyboard**: Keyboard layout: AZERTY\n- **Ports & interfaces**: USB 2.0 ports quantity: 3; HDMI ports quantity: 0; Ethernet LAN (RJ-45) ports: 1; VGA (D-Sub) ports quantity: 1; Firewire (IEEE 1394) ports: 1; Headphone outputs: 1; CardBus PCMCIA slots quantity: 0; Modem (RJ-11) ports: 0; PS/2 ports quantity: 0; Parallel ports quantity: 0; Serial ports quantity: 0\n- **Network**: Mobile network generation: 3G; Networking features: 10/100/1000 LAN; Bluetooth version: 2.0+EDR\n- **Graphics**: Discrete graphics card model: AMD Mobility FireGL V5700; Discrete graphics card memory: 0.512 GB\n- **Storage**: Total storage capacity: 320 GB; HDD interface: SATA; HDD speed: 5400 RPM\n- **Memory**: Internal memory: 4 GB; Maximum internal memory: 8 GB; Internal memory type: DDR3-SDRAM; Memory clock speed: 1066 MHz\n- **Processor**: Processor family: Intel® Core™2 Duo; Processor manufacturer: Intel; Processor model: T9800; Processor frequency: 2.93 GHz; Processor cores: 2; Processor threads: 2; Processor cache: 6 MB; Processor cache type: L2; Processor socket: Socket 479; Processor front side bus: 1066 MHz; Processor lithography: 45 nm; Processor operating modes: 64-bit; Processor series: Intel Core 2 Duo T9000 Series; Processor codename: Penryn; Bus type: FSB; Stepping: E0; Thermal Design Power (TDP): 35 W; Tjunction: 105 °C; Number of Processing Die Transistors: 410 M; Processing Die size: 107 mm²; CPU multiplier (bus/core ratio): 11\n- **Display**: Display diagonal: 39.1 cm (15.4\"); Display resolution: 1920 x 1200 pixels; Native aspect ratio: 16:10; Display surface: Matt", "image_url": "https://images.icecat.biz/img/gallery_mediums/img_3875254_medium_1481107490_8532_23568.jpg", "price": 639.72, "currency": "EUR", "categories": ["Laptops"], "attrs": {"Display diagonal": "39.1 cm (15.4\")", "Display resolution": "1920 x 1200 pixels", "Native aspect ratio": "16:10", "Display surface": "Matt", "Processor family": "Intel® Core™2 Duo", "Processor manufacturer": "Intel", "Processor model": "T9800", "Processor frequency": "2.93 GHz", "Processor cores": "2", "Processor threads": "2", "Processor cache": "6 MB", "Processor cache type": "L2", "Processor socket": "Socket 479", "Processor front side bus": "1066 MHz", "Processor lithography": "45 nm", "Processor operating modes": "64-bit", "Processor series": "Intel Core 2 Duo T9000 Series", "Processor codename": "Penryn", "Bus type": "FSB", "Stepping": "E0", "Thermal Design Power (TDP)": "35 W", "Tjunction": "105 °C", "Number of Processing Die Transistors": "410 M", "Processing Die size": "107 mm²", "CPU multiplier (bus/core ratio)": "11", "Internal memory": "4 GB", "Maximum internal memory": "8 GB", "Internal memory type": "DDR3-SDRAM", "Memory clock speed": "1066 MHz", "Total storage capacity": "320 GB", "HDD interface": "SATA", "HDD speed": "5400 RPM", "Discrete graphics card model": "AMD Mobility FireGL V5700", "Discrete graphics card memory": "0.512 GB", "Mobile network generation": "3G", "Networking features": "10/100/1000 LAN", "Bluetooth version": "2.0+EDR", "USB 20 ports quantity": "3", "HDMI ports quantity": "0", "Ethernet LAN (RJ-45) ports": "1", "VGA (D-Sub) ports quantity": "1", "Firewire (IEEE 1394) ports": "1", "Headphone outputs": "1", "CardBus PCMCIA slots quantity": "0", "Modem (RJ-11) ports": "0", "PS/2 ports quantity": "0", "Parallel ports quantity": "0", "Serial ports quantity": "0", "Keyboard layout": "AZERTY", "Operating system installed": "Windows 7 Professional", "Processor package size": "35 x 35 mm", "Processor code": "SLGES", "Processor ARK ID": "37005", "Number of battery cells": "6", "Weight": "2.63 kg", "Type": "PC", "Dimensions (WxDxH)": "357.5 x 255 x 33.5 mm", "Intel segment tagging": "Professional"}, "attr_keys": ["Bluetooth version", "Bus type", "CPU multiplier (bus/core ratio)", "CardBus PCMCIA slots quantity", "Dimensions (WxDxH)", "Discrete graphics card memory", "Discrete graphics card model", "Display diagonal", "Display resolution", "Display surface", "Ethernet LAN (RJ-45) ports", "Firewire (IEEE 1394) ports", "HDD interface", "HDD speed", "HDMI ports quantity", "Headphone outputs", "Intel segment tagging", "Internal memory", "Internal memory type", "Keyboard layout", "Maximum internal memory", "Memory clock speed", "Mobile network generation", "Modem (RJ-11) ports", "Native aspect ratio", "Networking features", "Number of Processing Die Transistors", "Number of battery cells", "Operating system installed", "PS/2 ports quantity", "Parallel ports quantity", "Processing Die size", "Processor ARK ID", "Processor cache", "Processor cache type", "Processor code", "Processor codename", "Processor cores", "Processor family", "Processor frequency", "Processor front side bus", "Processor lithography", "Processor manufacturer", "Processor model", "Processor operating modes", "Processor package size", "Processor series", "Processor socket", "Processor threads", "Serial ports quantity", "Stepping", "Thermal Design Power (TDP)", "Tjunction", "Total storage capacity", "Type", "USB 20 ports quantity", "VGA (D-Sub) ports quantity", "Weight"]}
{"id": "133067256", "title": "HP 255R G10 AMD Ryzen™ 5 7535U Laptop 39.6 cm (15.6\") Full HD 8 GB DDR5-SDRAM 256 GB SSD Wi-Fi 6 (802.11ax) Windows 11 Pro Silver", "brand": "HP", "description": "HP 255R G10 AMD Ryzen™ 5 7535U Laptop 39.6 cm (15.6\") Full HD 8 GB DDR5-SDRAM 256 GB SSD Wi-Fi 6 (802.11ax) Windows 11 Pro Silver\n\n\nBoost workflows with affordable AMD power and DDR5 efficiency The HP 255R 15.6 inch G10 Notebook provides essential business-ready features in a thin and light design that’s easy to take everywhere you go. This laptop is powered for productivity with a robust AMD processor [2] , super-fast DDR5 memory, and storage options—all at a price you can value.\n\n\nKey Specifications:\n- **Technical details**: General Product Safety Regulation (GPSR) URL: https://support.hp.com/us-en/document/ish_6126692-6126777-16?openCLC=true\n- **Other features**: Number of speakers: 2; Manufacturer warranty: HP Services offers 1-year or 3-year limited warranties and 90 day software limited warranty options depending on country. Batteries have a default one year limited warranty except for Long Life batteries which will have same 1-year or 3-year limited warranty as the platform. Refer to http://www.hp.com/support/batterywarranty/ for additional battery information. On-site service and extended coverage is also available. HP Care Pack Services are optional extended service contracts that go beyond the standard limited warranties. To choose the right level of service for your HP product, use the HP Care Pack Services Lookup Tool at: http://www.hp.com/go/cpc .; UNSPSC-code: 43211503\n- **Logistics data**: Harmonized System (HS) code: 8471300000\n- **Packaging data**: Package width: 69 mm; Package depth: 483 mm; Package height: 305 mm\n- **Weight & dimensions**: Weight: 1.66 kg; Width: 359.8 mm; Depth: 236 mm; Height (front): 1.17 cm; Height (rear): 1.57 cm\n- **Sustainability**: Sustainability certificates: ENERGY STAR, TCO; Sustainable technologies and materials: Outside box and corrugated cushions are 100% sustainably sourced and recyclable; Recycled plastic cushions; 2% post-consumer recycled plastic; Halogen-free\n- **Security**: Password protection type: BIOS, Power on\n- **Power**: AC adapter power: 65 W; AC adapter frequency: 50 - 60 Hz; AC adapter input voltage: 100 - 240 V\n- **Battery**: Battery capacity: 41 Wh; Battery technology: Lithium Polymer (LiPo); Number of battery cells: 3; Battery weight: 190 g\n- **Brand-specific features**: HP speaker type: HP Dual Speakers; HP front camera: HP Webcam FHD; HP segment: Business; HP GTIN (EAN/UPC): 199485910994\n- **Software**: Operating system installed: Windows 11 Pro; Trial software: McAfee Online Protection 30-day trial\n- **Keyboard**: Pointing device: Touchpad; Keyboard colour name: Flint opaque\n- **Ports & interfaces**: USB 3.2 Gen 1 (3.1 Gen 1) Type-A ports quantity: 2; HDMI ports quantity: 1; USB 3.2 Gen 2 (3.1 Gen 2) Type-C ports quantity: 1; HDMI version: 1.4b; USB Sleep-and-Charge ports: 1\n- **Network**: Top Wi-Fi standard: Wi-Fi 6 (802.11ax); Wi-Fi standards: Wi-Fi 6 (802.11ax); Antenna type: 2x2; WLAN controller model: Realtek RTL8852BE-VT; WLAN controller manufacturer: Realtek; Bluetooth version: 5.4\n- **Camera**: Front camera resolution: 1920 x 1080 pixels; Front camera HD type: Full HD\n- **Audio**: Number of built-in speakers: 2; Number of microphones: 2\n- **Graphics**: Discrete graphics card model: Not available; On-board graphics card model: AMD Radeon 660M; On-board GPU manufacturer: AMD; On-board graphics card family: AMD Radeon Graphics\n- **Storage**: Total storage capacity: 256 GB; Storage media: SSD; Total SSDs capacity: 256 GB; Number of SSDs installed: 1; SSD capacity: 256 GB; SSD interface: PCI Express; SSD form factor: M.2\n- **Memory**: Internal memory: 8 GB; Maximum internal memory: 32 GB; Internal memory type: DDR5-SDRAM; Memory clock speed: 4800 MHz; Memory form factor: SO-DIMM; Memory layout (slots x size): 1 x 8 GB; Memory slots: 2x SO-DIMM; Memory data transfer rate: 4800 MT/s\n- **Processor**: Processor family: AMD Ryzen™ 5; Processor manufacturer: AMD; Processor model: 7535U; Processor frequency: 2.9 GHz; Processor generation: AMD Ryzen 7000 Series; Processor cores: 6; Processor threads: 12; Processor boost frequency: 4.5 GHz; Processor cache: 16 MB; Processor cache type: L3\n- **Display**: Display diagonal: 39.6 cm (15.6\"); Display resolution: 1920 x 1080 pixels; HD type: Full HD; Panel type: IPS; Display bezel technology: Narrow Border; Display brightness: 250 cd/m²; Display diagonal (metric): 39.6 cm; RGB colour space: NTSC; Colour gamut: 45%; NTSC coverage (typical): 45%\n- **Design**: Product type: Laptop; Product colour: Silver; Form factor: Clamshell; Colour name: Turbo silver; Market positioning: Everyday; Introduction year: 2025; Country of origin: China, Thailand; Original brand name: HP", "image_url": "https://images.icecat.biz/img/gallery_mediums/503a7bdd110ee3ebaa3d6f4510e0c51260f1298a.jpg", "price": 1458.52, "currency": "EUR", "categories": ["Laptops"], "attrs": {"Product type": "Laptop", "Product colour": "Silver", "Form factor": "Clamshell", "Colour name": "Turbo silver", "Market positioning": "Everyday", "Introduction year": "2025", "Country of origin": "China, Thailand", "Original brand name": "HP", "Display diagonal": "39.6 cm (15.6\")", "Display resolution": "1920 x 1080 pixels", "HD type": "Full HD", "Panel type": "IPS", "Display bezel technology": "Narrow Border", "Display brightness": "250 cd/m²", "Display diagonal (metric)": "39.6 cm", "RGB colour space": "NTSC", "Colour gamut": "45%", "NTSC coverage (typical)": "45%", "Processor family": "AMD Ryzen™ 5", "Processor manufacturer": "AMD", "Processor model": "7535U", "Processor frequency": "2.9 GHz", "Processor generation": "AMD Ryzen 7000 Series", "Processor cores": "6", "Processor threads": "12", "Processor boost frequency": "4.5 GHz", "Processor cache": "16 MB", "Processor cache type": "L3", "Internal memory": "8 GB", "Maximum internal memory": "32 GB", "Internal memory type": "DDR5-SDRAM", "Memory clock speed": "4800 MHz", "Memory form factor": "SO-DIMM", "Memory layout (slots x size)": "1 x 8 GB", "Memory slots": "2x SO-DIMM", "Memory data transfer rate": "4800 MT/s", "Total storage capacity": "256 GB", "Storage media": "SSD", "Total SSDs capacity": "256 GB", "Number of SSDs installed": "1", "SSD capacity": "256 GB", "SSD interface": "PCI Express", "SSD form factor": "M.2", "Discrete graphics card model": "Not available", "On-board graphics card model": "AMD Radeon 660M", "On-board GPU manufacturer": "AMD", "On-board graphics card family": "AMD Radeon Graphics", "Number of built-in speakers": "2", "Number of microphones": "2", "Front camera resolution": "1920 x 1080 pixels", "Front camera HD type": "Full HD", "Top Wi-Fi standard": "Wi-Fi 6 (802.11ax)", "Wi-Fi standards": "Wi-Fi 6 (802.11ax)", "Antenna type": "2x2", "WLAN controller model": "Realtek RTL8852BE-VT", "WLAN controller manufacturer": "Realtek", "Bluetooth version": "5.4", "USB 32 Gen 1 (31 Gen 1) Type-A ports quantity": "2", "HDMI ports quantity": "1", "USB 32 Gen 2 (31 Gen 2) Type-C ports quantity": "1", "HDMI version": "1.4b", "USB Sleep-and-Charge ports": "1", "Pointing device": "Touchpad", "Keyboard colour name": "Flint opaque", "Operating system installed": "Windows 11 Pro", "Trial software": "McAfee Online Protection 30-day trial", "HP speaker type": "HP Dual Speakers", "HP front camera": "HP Webcam FHD", "HP segment": "Business", "Battery capacity": "41 Wh", "Battery technology": "Lithium Polymer (LiPo)", "Number of battery cells": "3", "Battery weight": "190 g", "AC adapter power": "65 W", "AC adapter frequency": "50 - 60 Hz", "AC adapter input voltage": "100 - 240 V", "Password protection type": "BIOS, Power on", "Sustainability certificates": "ENERGY STAR, TCO", "Sustainable technologies and materials": "Outside box and corrugated cushions are 100% sustainably sourced and recyclable; Recycled plastic cushions; 2% post-consumer recycled plastic; Halogen-free", "Weight": "1.66 kg", "Width": "359.8 mm", "Depth": "236 mm", "Height (front)": "1.17 cm", "Height (rear)": "1.57 cm", "Package width": "69 mm", "Package depth": "483 mm", "Package height": "305 mm", "Harmonized System (HS) code": "8471300000", "General Product Safety Regulation (GPSR) URL": "https://support.hp.com/us-en/document/ish_6126692-6126777-16?openCLC=true", "Number of speakers": "2", "Manufacturer warranty": "HP Services offers 1-year or 3-year limited warranties and 90 day software limited warranty options depending on country. Batteries have a default one year limited warranty except for Long Life batteries which will have same 1-year or 3-year limited warranty as the platform. Refer to http://www.hp.com/support/batterywarranty/ for additional battery information. On-site service and extended coverage is also available. HP Care Pack Services are optional extended service contracts that go beyond the standard limited warranties. To choose the right level of service for your HP product, use the HP Care Pack Services Lookup Tool at: http://www.hp.com/go/cpc .", "HP GTIN (EAN/UPC)": "199485910994", "UNSPSC-code": "43211503"}, "attr_keys": ["AC adapter frequency", "AC adapter input voltage", "AC adapter power", "Antenna type", "Battery capacity", "Battery technology", "Battery weight", "Bluetooth version", "Colour gamut", "Colour name", "Country of origin", "Depth", "Discrete graphics card model", "Display bezel technology", "Display brightness", "Display diagonal", "Display diagonal (metric)", "Display resolution", "Form factor", "Front camera HD type", "Front camera resolution", "General Product Safety Regulation (GPSR) URL", "HD type", "HDMI ports quantity", "HDMI version", "HP GTIN (EAN/UPC)", "HP front camera", "HP segment", "HP speaker type", "Harmonized System (HS) code", "Height (front)", "Height (rear)", "Internal memory", "Internal memory type", "Introduction year", "Keyboard colour name", "Manufacturer warranty", "Market positioning", "Maximum internal memory", "Memory clock speed", "Memory data transfer rate", "Memory form factor", "Memory layout (slots x size)", "Memory slots", "NTSC coverage (typical)", "Number of SSDs installed", "Number of battery cells", "Number of built-in speakers", "Number of microphones", "Number of speakers", "On-board GPU manufacturer", "On-board graphics card family", "On-board graphics card model", "Operating system installed", "Original brand name", "Package depth", "Package height", "Package width", "Panel type", "Password protection type", "Pointing device", "Processor boost frequency", "Processor cache", "Processor cache type", "Processor cores", "Processor family", "Processor frequency", "Processor generation", "Processor manufacturer", "Processor model", "Processor threads", "Product colour", "Product type", "RGB colour space", "SSD capacity", "SSD form factor", "SSD interface", "Storage media", "Sustainability certificates", "Sustainable technologies and materials", "Top Wi-Fi standard", "Total SSDs capacity", "Total storage capacity", "Trial software", "UNSPSC-code", "USB 32 Gen 1 (31 Gen 1) Type-A ports quantity", "USB 32 Gen 2 (31 Gen 2) Type-C ports quantity", "USB Sleep-and-Charge ports", "WLAN controller manufacturer", "WLAN controller model", "Weight", "Wi-Fi standards", "Width"]}
{"id": "35785854", "title": "Lenovo IdeaPad 320 Intel® Core™ i7 i7-7500U Laptop 39.6 cm (15.6\") HD 16 GB DDR4-SDRAM 1 TB HDD Windows 10 Home Grey, Platinum", "brand": "Lenovo", "description": "Lenovo IdeaPad 320 Intel® Core™ i7 i7-7500U Laptop 39.6 cm (15.6\") HD 16 GB DDR4-SDRAM 1 TB HDD Windows 10 Home Grey, Platinum\n\n\nLife Just Got Easier. Everything about the IdeaPad 320 is designed to simplify your life. It will handle any task with ease, thanks to powerful processing and discrete graphics options. Preloaded with Windows 10 Home, you'll have the personal assistance of Cortana, designed to help open apps and answer your questions — whether typed or spoken. From the new streamlined design to a cleaner desktop interface, you'll enjoy the simplicity that IdeaPad 320 offers. Performance You Can Count On Up to top-of-the-line 7th Gen Intel® Core™ i5 processing, plus up to 4 GB DDR4 memory, guarantee lightning-fast responsiveness and reliable performance. Run multiple programs simultaneously, and transition seamlessly between web tabs — you'll be able to multitask with ease. Durability Down to the Finish We redesigned the IdeaPad 320 with a sleek unibody chassis. Better yet, it is designed to keep up with you. We treated it with a special protective finish to guard against wear and tear, and added rubber detailing on the bottom cover to maximize ventilation and extend product life. Advanced Graphics Power With NVIDIA The IdeaPad 320 offers a range of graphics options, including a powerful NVIDIA® GeForce™ 940MX graphics card. Discrete graphics cards rely on their own processing power, so you'll experience smoother graphics, less screen tearing and better gaming performance without compromising overall speed and responsiveness. Whether you're playing a game or creating or editing content, you'll enjoy crisp visuals. Brilliant Resolution The IdeaPad 320 offers up to Full High Definition resolution, and features anti-glare technology. You'll enjoy true visual clarity when you watch movies, browse the web, and more. Powerful Storage Choose 1 TB SATA HDD, you'll have more than enough room to build your collection of photos, movies and more — without spending extra money. Streamline Your Day With Windows 10 The IdeaPad 320 brings you Windows 10 Home, featuring a host of exciting new features. Want to find a local Indian restaurant, or need gift suggestions? Ask Cortana — your very own digital personal assistant. Cortana works with more than a thousand apps and services to ensure you'll always have the answers you need. Best of all, it works across all your Windows 10 devices to keep you organized. Keep it Simple With Lenovo App Explorer With Lenovo App Explorer, choose only the apps you want. It's a straightforward and secure way to personalize your computer, and an essential part of Lenovo's commitment to cleaner, safer PCs. Redesigned Touchpad, for Improved Responsiveness We redesigned the touchpad on the IdeaPad 320, for a better user experience with multifinger gestures. Touch, click and zoom — you'll feel the difference. Easy Access to Movies and More The IdeaPad 320 comes equipped with a DVD drive, so you'll be able to watch and listen to the movies and music you already own and love. Audio Clarity at any Volume Featuring Dolby Audio-optimized speakers, the IdeaPad 320 delivers crystal-clear audio with minimal distortion at any volume. Stream your favorite playlist or video chat with family — you'll hear every detail.\n\n\nKey Specifications:\n- **Other features**: Maximum internal memory (64-bit): 16 GB\n- **Weight & dimensions**: Weight: 2.02 kg; Width: 378 mm; Depth: 260 mm; Height: 22.9 mm\n- **Sustainability**: Sustainability certificates: ENERGY STAR\n- **Certificates**: Compliance certificates: RoHS\n- **Security**: Cable lock slot type: Kensington; Password protection type: HDD, Power on, Supervisor\n- **Power**: AC adapter frequency: 50 - 60 Hz; AC adapter input voltage: 100 - 240 V\n- **Battery**: Battery technology: Lithium Polymer (LiPo); Number of battery cells: 2\n- **Processor special features**: Intel® Turbo Boost Technology: 2.0; Processor package size: 42 x 24 mm; Supported instruction sets: AVX 2.0, SSE4.1, SSE4.2; Processor code: SR2ZV; CPU configuration (max): 1; Graphics & IMC lithography: 14 nm; Intel Identity Protection Technology version: 1.00; Intel Smart Response Technology version: 1.00; Intel Stable Image Platform Program (SIPP) version: 0.00; Intel Secure Key Technology version: 1.00; Intel TSX-NI version: 0.00; Processor ARK ID: 95451\n- **Software**: Operating system installed: Windows 10 Home; Operating system architecture: 64-bit\n- **Keyboard**: Pointing device: Touchpad\n- **Ports & interfaces**: USB 2.0 ports quantity: 0; USB 3.2 Gen 1 (3.1 Gen 1) Type-A ports quantity: 2; USB 3.2 Gen 1 (3.1 Gen 1) Type-C ports quantity: 1; HDMI ports quantity: 1; USB 3.2 Gen 2 (3.1 Gen 2) Type-A ports quantity: 0; USB 3.2 Gen 2 (3.1 Gen 2) Type-C ports quantity: 0; Ethernet LAN (RJ-45) ports: 1; HDMI version: 1.4b; DisplayPorts quantity: 0; VGA (D-Sub) ports quantity: 0; Thunderbolt ports quantity: 0; Thunderbolt 3 ports quantity: 0\n- **Network**: Wi-Fi standards: 802.11a, Wi-Fi 5 (802.11ac), 802.11b, 802.11g, Wi-Fi 4 (802.11n); Ethernet LAN data rates: 10,100,1000 Mbit/s; Bluetooth version: 4.1\n- **Camera**: Front camera resolution (numeric): 0.3 MP\n- **Audio**: Audio system: Dolby Audio; Number of built-in speakers: 2; Speaker power: 1.5 W\n- **Graphics**: Discrete graphics card model: Not available; On-board graphics card model: Intel® HD Graphics 620; On-board graphics card base frequency: 300 MHz; On-board graphics card dynamic frequency (max): 1050 MHz; Maximum on-board graphics card memory: 32 GB; On-board graphics card DirectX version: 12.0; On-board graphics card OpenGL version: 4.4; On-board graphics card ID: 0x5916\n- **Storage**: Total storage capacity: 1 TB; Storage media: HDD; Optical drive type: DVD±RW; Number of HDDs installed: 1; HDD capacity: 1 TB; HDD interface: SATA III; HDD size: 2.5\"; Compatible memory cards: MMC, SD, SDHC, SDXC\n- **Memory**: Internal memory: 16 GB; Internal memory type: DDR4-SDRAM; Memory clock speed: 2133 MHz; Memory slots: 1x SO-DIMM\n- **Processor**: Processor family: Intel® Core™ i7; Processor manufacturer: Intel; Processor model: i7-7500U; Processor frequency: 2.7 GHz; Processor generation: 7th gen Intel® Core™ i7; Processor cores: 2; Processor threads: 4; Processor boost frequency: 3.5 GHz; System bus rate: 4 GT/s; Processor cache: 4 MB; Processor cache type: Smart Cache; Processor socket: BGA 1356; Processor lithography: 14 nm; Processor operating modes: 64-bit; Processor codename: Kaby Lake; Bus type: OPI; Stepping: H0; Thermal Design Power (TDP): 15 W; Configurable TDP-up frequency: 2.9 GHz; Configurable TDP-up: 25 W; Configurable TDP-down: 7.5 W; Configurable TDP-down frequency: 0.8 GHz; Tjunction: 100 °C; Maximum number of PCI Express lanes: 12; PCI Express slots version: 3.0; PCI Express configurations: 1x2+2x1, 1x4, 2x2, 4x1\n- **Display**: Display diagonal: 39.6 cm (15.6\"); Display resolution: 1366 x 768 pixels; HD type: HD; Native aspect ratio: 16:9; Screen shape: Flat\n- **Design**: Product type: Laptop; Product colour: Grey, Platinum; Form factor: Clamshell; Housing material: Acrylonitrile butadiene styrene (ABS)", "image_url": "https://images.icecat.biz/img/gallery_mediums/40339759_3108145589.jpg", "price": 986.08, "currency": "EUR", "categories": ["Laptops"], "attrs": {"Product type": "Laptop", "Product colour": "Grey, Platinum", "Form factor": "Clamshell", "Housing material": "Acrylonitrile butadiene styrene (ABS)", "Display diagonal": "39.6 cm (15.6\")", "Display resolution": "1366 x 768 pixels", "HD type": "HD", "Native aspect ratio": "16:9", "Screen shape": "Flat", "Processor family": "Intel® Core™ i7", "Processor manufacturer": "Intel", "Processor model": "i7-7500U", "Processor frequency": "2.7 GHz", "Processor generation": "7th gen Intel® Core™ i7", "Processor cores": "2", "Processor threads": "4", "Processor boost frequency": "3.5 GHz", "System bus rate": "4 GT/s", "Processor cache": "4 MB", "Processor cache type": "Smart Cache", "Processor socket": "BGA 1356", "Processor lithography": "14 nm", "Processor operating modes": "64-bit", "Processor codename": "Kaby Lake", "Bus type": "OPI", "Stepping": "H0", "Thermal Design Power (TDP)": "15 W", "Configurable TDP-up frequency": "2.9 GHz", "Configurable TDP-up": "25 W", "Configurable TDP-down": "7.5 W", "Configurable TDP-down frequency": "0.8 GHz", "Tjunction": "100 °C", "Maximum number of PCI Express lanes": "12", "PCI Express slots version": "3.0", "PCI Express configurations": "1x2+2x1, 1x4, 2x2, 4x1", "Internal memory": "16 GB", "Internal memory type": "DDR4-SDRAM", "Memory clock speed": "2133 MHz", "Memory slots": "1x SO-DIMM", "Total storage capacity": "1 TB", "Storage media": "HDD", "Optical drive type": "DVD±RW", "Number of HDDs installed": "1", "HDD capacity": "1 TB", "HDD interface": "SATA III", "HDD size": "2.5\"", "Compatible memory cards": "MMC, SD, SDHC, SDXC", "Discrete graphics card model": "Not available", "On-board graphics card model": "Intel® HD Graphics 620", "On-board graphics card base frequency": "300 MHz", "On-board graphics card dynamic frequency (max)": "1050 MHz", "Maximum on-board graphics card memory": "32 GB", "On-board graphics card DirectX version": "12.0", "On-board graphics card OpenGL version": "4.4", "On-board graphics card ID": "0x5916", "Audio system": "Dolby Audio", "Number of built-in speakers": "2", "Speaker power": "1.5 W", "Front camera resolution (numeric)": "0.3 MP", "Wi-Fi standards": "802.11a, Wi-Fi 5 (802.11ac), 802.11b, 802.11g, Wi-Fi 4 (802.11n)", "Ethernet LAN data rates": "10,100,1000 Mbit/s", "Bluetooth version": "4.1", "USB 20 ports quantity": "0", "USB 32 Gen 1 (31 Gen 1) Type-A ports quantity": "2", "USB 32 Gen 1 (31 Gen 1) Type-C ports quantity": "1", "HDMI ports quantity": "1", "USB 32 Gen 2 (31 Gen 2) Type-A ports quantity": "0", "USB 32 Gen 2 (31 Gen 2) Type-C ports quantity": "0", "Ethernet LAN (RJ-45) ports": "1", "HDMI version": "1.4b", "DisplayPorts quantity": "0", "VGA (D-Sub) ports quantity": "0", "Thunderbolt ports quantity": "0", "Thunderbolt 3 ports quantity": "0", "Pointing device": "Touchpad", "Operating system installed": "Windows 10 Home", "Operating system architecture": "64-bit", "Intel® Turbo Boost Technology": "2.0", "Processor package size": "42 x 24 mm", "Supported instruction sets": "AVX 2.0, SSE4.1, SSE4.2", "Processor code": "SR2ZV", "CPU configuration (max)": "1", "Graphics & IMC lithography": "14 nm", "Intel Identity Protection Technology version": "1.00", "Intel Smart Response Technology version": "1.00", "Intel Stable Image Platform Program (SIPP) version": "0.00", "Intel Secure Key Technology version": "1.00", "Intel TSX-NI version": "0.00", "Processor ARK ID": "95451", "Battery technology": "Lithium Polymer (LiPo)", "Number of battery cells": "2", "AC adapter frequency": "50 - 60 Hz", "AC adapter input voltage": "100 - 240 V", "Cable lock slot type": "Kensington", "Password protection type": "HDD, Power on, Supervisor", "Compliance certificates": "RoHS", "Sustainability certificates": "ENERGY STAR", "Weight": "2.02 kg", "Width": "378 mm", "Depth": "260 mm", "Height": "22.9 mm", "Maximum internal memory (64-bit)": "16 GB"}, "attr_keys": ["AC adapter frequency", "AC adapter input voltage", "Audio system", "Battery technology", "Bluetooth version", "Bus type", "CPU configuration (max)", "Cable lock slot type", "Compatible memory cards", "Compliance certificates", "Configurable TDP-down", "Configurable TDP-down frequency", "Configurable TDP-up", "Configurable TDP-up frequency", "Depth", "Discrete graphics card model", "Display diagonal", "Display resolution", "DisplayPorts quantity", "Ethernet LAN (RJ-45) ports", "Ethernet LAN data rates", "Form factor", "Front camera resolution (numeric)", "Graphics & IMC lithography", "HD type", "HDD capacity", "HDD interface", "HDD size", "HDMI ports quantity", "HDMI version", "Height", "Housing material", "Intel Identity Protection Technology version", "Intel Secure Key Technology version", "Intel Smart Response Technology version", "Intel Stable Image Platform Program (SIPP) version", "Intel TSX-NI version", "Intel® Turbo Boost Technology", "Internal memory", "Internal memory type", "Maximum internal memory (64-bit)", "Maximum number of PCI Express lanes", "Maximum on-board graphics card memory", "Memory clock speed", "Memory slots", "Native aspect ratio", "Number of HDDs installed", "Number of battery cells", "Number of built-in speakers", "On-board graphics card DirectX version", "On-board graphics card ID", "On-board graphics card OpenGL version", "On-board graphics card base frequency", "On-board graphics card dynamic frequency (max)", "On-board graphics card model", "Operating system architecture", "Operating system installed", "Optical drive type", "PCI Express configurations", "PCI Express slots version", "Password protection type", "Pointing device", "Processor ARK ID", "Processor boost frequency", "Processor cache", "Processor cache type", "Processor code", "Processor codename", "Processor cores", "Processor family", "Processor frequency", "Processor generation", "Processor lithography", "Processor manufacturer", "Processor model", "Processor operating modes", "Processor package size", "Processor socket", "Processor threads", "Product colour", "Product type", "Screen shape", "Speaker power", "Stepping", "Storage media", "Supported instruction sets", "Sustainability certificates", "System bus rate", "Thermal Design Power (TDP)", "Thunderbolt 3 ports quantity", "Thunderbolt ports quantity", "Tjunction", "Total storage capacity", "USB 20 ports quantity", "USB 32 Gen 1 (31 Gen 1) Type-A ports quantity", "USB 32 Gen 1 (31 Gen 1) Type-C ports quantity", "USB 32 Gen 2 (31 Gen 2) Type-A ports quantity", "USB 32 Gen 2 (31 Gen 2) Type-C ports quantity", "VGA (D-Sub) ports quantity", "Weight", "Wi-Fi standards", "Width"]}
{"id": "71207436", "title": "DELL Latitude 5500 Intel® Core™ i7 i7-8665U Laptop 39.6 cm (15.6\") Full HD 16 GB DDR4-SDRAM 512 GB SSD Wi-Fi 5 (802.11ac) Windows 10 Pro Black", "brand": "R-Go Tools", "description": "DELL Latitude 5500 Intel® Core™ i7 i7-8665U Laptop 39.6 cm (15.6\") Full HD 16 GB DDR4-SDRAM 512 GB SSD Wi-Fi 5 (802.11ac) Windows 10 Pro Black\n\n\nRedesigned and ready for business The world’s smallest 15” mainstream business-class notebook lets you get to work faster than ever thanks to its scalable features, powerful performance and ExpressCharge.\n\n\nKey Specifications:\n- **Other features**: Maximum internal memory (64-bit): 32 GB\n- **Weight & dimensions**: Weight: 1.82 kg; Width: 359.1 mm; Depth: 236.2 mm; Height (front): 2.03 cm; Height (rear): 2.2 cm\n- **Sustainability**: Sustainability certificates: ENERGY STAR\n- **Operational conditions**: Operating temperature (T-T): 0 - 35 °C; Storage temperature (T-T): -40 - 65 °C; Operating relative humidity (H-H): 10 - 80%; Storage relative humidity (H-H): 0 - 95%; Operating altitude: -15.2 - 3048 m; Non-operating altitude: -15.2 - 10668 m; Operating shock: 105 G; Non-operating shock: 40 G; Operating vibration: 0.26 G; Non-operating vibration: 1.37 G\n- **Power**: AC adapter power: 65 W; AC adapter frequency: 50 - 60 Hz; AC adapter input voltage: 100 - 240 V; AC adapter output current: 3.34 A; AC adapter output voltage: 19.5 V\n- **Battery**: Battery capacity: 68 Wh; Battery technology: Lithium-Ion (Li-Ion); Number of battery cells: 4; Battery voltage: 7.6 V; Battery weight: 340 g\n- **Processor special features**: Intel® Turbo Boost Technology: 2.0; Processor package size: 46x24 mm; Supported instruction sets: SSE4.1, SSE4.2, AVX 2.0; CPU configuration (max): 1; Processor ARK ID: 193563\n- **Software**: Operating system installed: Windows 10 Pro; Operating system architecture: 64-bit; Operating system language: Multilingual\n- **Keyboard**: Pointing device: DualPoint\n- **Ports & interfaces**: USB 2.0 ports quantity: 0; USB 3.2 Gen 1 (3.1 Gen 1) Type-A ports quantity: 3; USB 3.2 Gen 1 (3.1 Gen 1) Type-C ports quantity: 0; HDMI ports quantity: 1; USB 3.2 Gen 2 (3.1 Gen 2) Type-A ports quantity: 0; USB 3.2 Gen 2 (3.1 Gen 2) Type-C ports quantity: 0; Ethernet LAN (RJ-45) ports: 1; HDMI version: 1.4b; DisplayPorts quantity: 0; Thunderbolt 3 ports quantity: 1; Number of USB ports with PowerShare support: 1\n- **Network**: Top Wi-Fi standard: Wi-Fi 5 (802.11ac); Wi-Fi standards: 802.11a, Wi-Fi 5 (802.11ac), 802.11b, 802.11g, Wi-Fi 4 (802.11n); Antenna type: 2x2; WLAN controller model: Intel Dual Band Wireless-AC 9560; Ethernet LAN data rates: 10,100,1000 Mbit/s; Bluetooth version: 5.0\n- **Camera**: Front camera resolution: 1280 x 720 pixels; Front camera signal format: 720p; Front camera HD type: HD; Video capturing speed: 30 fps\n- **Audio**: Audio chip: Realtek ALC3204; Audio system: MaxxAudio Pro; Number of built-in speakers: 2; Speakers manufacturer: Waves; Speaker power: 2 W\n- **Graphics**: Discrete graphics card model: Not available; On-board graphics card model: Intel® UHD Graphics 620; On-board graphics card family: Intel® UHD Graphics; On-board graphics card base frequency: 300 MHz; On-board graphics card dynamic frequency (max): 1150 MHz; Maximum on-board graphics card memory: 32 GB; On-board graphics card DirectX version: 12.0; On-board graphics card OpenGL version: 4.5; On-board graphics card ID: 0x3EA0\n- **Storage**: Total storage capacity: 512 GB; Storage media: SSD; Total SSDs capacity: 512 GB; Number of SSDs installed: 1; SSD capacity: 512 GB; SSD interface: PCI Express; SSD form factor: M.2; Compatible memory cards: MicroSD (TransFlash)\n- **Memory**: Internal memory: 16 GB; Maximum internal memory: 32 GB; Internal memory type: DDR4-SDRAM; Memory clock speed: 2666 MHz; Memory form factor: SO-DIMM; Memory layout (slots x size): 1 x 16 GB; Memory slots: 2x SO-DIMM\n- **Processor**: Processor family: Intel® Core™ i7; Processor manufacturer: Intel; Processor model: i7-8665U; Processor frequency: 1.9 GHz; Processor generation: 8th gen Intel® Core™ i7; Processor cores: 4; Processor threads: 8; Processor boost frequency: 4.8 GHz; System bus rate: 4 GT/s; Processor cache: 8 MB; Processor cache type: Smart Cache; Processor socket: BGA 1528; Processor lithography: 14 nm; Processor operating modes: 64-bit; Processor codename: Whiskey Lake; Thermal Design Power (TDP): 15 W; Configurable TDP-up frequency: 2.1 GHz; Configurable TDP-up: 25 W; Configurable TDP-down: 10 W; Configurable TDP-down frequency: 0.8 GHz; Tjunction: 100 °C; Maximum number of PCI Express lanes: 16; PCI Express slots version: 3.0; PCI Express configurations: 1x4, 2x2, 1x2+2x1, 4x1\n- **Display**: Display diagonal: 39.6 cm (15.6\"); Display resolution: 1920 x 1080 pixels; HD type: Full HD; Native aspect ratio: 16:9; Display brightness: 220 cd/m²; Pixel density: 141 ppi; Maximum refresh rate: 60 Hz; Contrast ratio (typical): 700:1\n- **Design**: Product type: Laptop; Product colour: Black; Form factor: Clamshell", "image_url": "https://images.icecat.biz/img/gallery_mediums/71207444_5596718938.jpg", "price": 1161.9, "currency": "EUR", "categories": ["Laptops"], "attrs": {"Product type": "Laptop", "Product colour": "Black", "Form factor": "Clamshell", "Display diagonal": "39.6 cm (15.6\")", "Display resolution": "1920 x 1080 pixels", "HD type": "Full HD", "Native aspect ratio": "16:9", "Display brightness": "220 cd/m²", "Pixel density": "141 ppi", "Maximum refresh rate": "60 Hz", "Contrast ratio (typical)": "700:1", "Processor family": "Intel® Core™ i7", "Processor manufacturer": "Intel", "Processor model": "i7-8665U", "Processor frequency": "1.9 GHz", "Processor generation": "8th gen Intel® Core™ i7", "Processor cores": "4", "Processor threads": "8", "Processor boost frequency": "4.8 GHz", "System bus rate": "4 GT/s", "Processor cache": "8 MB", "Processor cache type": "Smart Cache", "Processor socket": "BGA 1528", "Processor lithography": "14 nm", "Processor operating modes": "64-bit", "Processor codename": "Whiskey Lake", "Thermal Design Power (TDP)": "15 W", "Configurable TDP-up frequency": "2.1 GHz", "Configurable TDP-up": "25 W", "Configurable TDP-down": "10 W", "Configurable TDP-down frequency": "0.8 GHz", "Tjunction": "100 °C", "Maximum number of PCI Express lanes": "16", "PCI Express slots version": "3.0", "PCI Express configurations": "1x4, 2x2, 1x2+2x1, 4x1", "Internal memory": "16 GB", "Maximum internal memory": "32 GB", "Internal memory type": "DDR4-SDRAM", "Memory clock speed": "2666 MHz", "Memory form factor": "SO-DIMM", "Memory layout (slots x size)": "1 x 16 GB", "Memory slots": "2x SO-DIMM", "Total storage capacity": "512 GB", "Storage media": "SSD", "Total SSDs capacity": "512 GB", "Number of SSDs installed": "1", "SSD capacity": "512 GB", "SSD interface": "PCI Express", "SSD form factor": "M.2", "Compatible memory cards": "MicroSD (TransFlash)", "Discrete graphics card model": "Not available", "On-board graphics card model": "Intel® UHD Graphics 620", "On-board graphics card family": "Intel® UHD Graphics", "On-board graphics card base frequency": "300 MHz", "On-board graphics card dynamic frequency (max)": "1150 MHz", "Maximum on-board graphics card memory": "32 GB", "On-board graphics card DirectX version": "12.0", "On-board graphics card OpenGL version": "4.5", "On-board graphics card ID": "0x3EA0", "Audio chip": "Realtek ALC3204", "Audio system": "MaxxAudio Pro", "Number of built-in speakers": "2", "Speakers manufacturer": "Waves", "Speaker power": "2 W", "Front camera resolution": "1280 x 720 pixels", "Front camera signal format": "720p", "Front camera HD type": "HD", "Video capturing speed": "30 fps", "Top Wi-Fi standard": "Wi-Fi 5 (802.11ac)", "Wi-Fi standards": "802.11a, Wi-Fi 5 (802.11ac), 802.11b, 802.11g, Wi-Fi 4 (802.11n)", "Antenna type": "2x2", "WLAN controller model": "Intel Dual Band Wireless-AC 9560", "Ethernet LAN data rates": "10,100,1000 Mbit/s", "Bluetooth version": "5.0", "USB 20 ports quantity": "0", "USB 32 Gen 1 (31 Gen 1) Type-A ports quantity": "3", "USB 32 Gen 1 (31 Gen 1) Type-C ports quantity": "0", "HDMI ports quantity": "1", "USB 32 Gen 2 (31 Gen 2) Type-A ports quantity": "0", "USB 32 Gen 2 (31 Gen 2) Type-C ports quantity": "0", "Ethernet LAN (RJ-45) ports": "1", "HDMI version": "1.4b", "DisplayPorts quantity": "0", "Thunderbolt 3 ports quantity": "1", "Number of USB ports with PowerShare support": "1", "Pointing device": "DualPoint", "Operating system installed": "Windows 10 Pro", "Operating system architecture": "64-bit", "Operating system language": "Multilingual", "Intel® Turbo Boost Technology": "2.0", "Processor package size": "46x24 mm", "Supported instruction sets": "SSE4.1, SSE4.2, AVX 2.0", "CPU configuration (max)": "1", "Processor ARK ID": "193563", "Battery capacity": "68 Wh", "Battery technology": "Lithium-Ion (Li-Ion)", "Number of battery cells": "4", "Battery voltage": "7.6 V", "Battery weight": "340 g", "AC adapter power": "65 W", "AC adapter frequency": "50 - 60 Hz", "AC adapter input voltage": "100 - 240 V", "AC adapter output current": "3.34 A", "AC adapter output voltage": "19.5 V", "Operating temperature (T-T)": "0 - 35 °C", "Storage temperature (T-T)": "-40 - 65 °C", "Operating relative humidity (H-H)": "10 - 80%", "Storage relative humidity (H-H)": "0 - 95%", "Operating altitude": "-15.2 - 3048 m", "Non-operating altitude": "-15.2 - 10668 m", "Operating shock": "105 G", "Non-operating shock": "40 G", "Operating vibration": "0.26 G", "Non-operating vibration": "1.37 G", "Sustainability certificates": "ENERGY STAR", "Weight": "1.82 kg", "Width": "359.1 mm", "Depth": "236.2 mm", "Height (front)": "2.03 cm", "Height (rear)": "2.2 cm", "Maximum internal memory (64-bit)": "32 GB"}, "attr_keys": ["AC adapter frequency", "AC adapter input voltage", "AC adapter output current", "AC adapter output voltage", "AC adapter power", "Antenna type", "Audio chip", "Audio system", "Battery capacity", "Battery technology", "Battery voltage", "Battery weight", "Bluetooth version", "CPU configuration (max)", "Compatible memory cards", "Configurable TDP-down", "Configurable TDP-down frequency", "Configurable TDP-up", "Configurable TDP-up frequency", "Contrast ratio (typical)", "Depth", "Discrete graphics card model", "Display brightness", "Display diagonal", "Display resolution", "DisplayPorts quantity", "Ethernet LAN (RJ-45) ports", "Ethernet LAN data rates", "Form factor", "Front camera HD type", "Front camera resolution", "Front camera signal format", "HD type", "HDMI ports quantity", "HDMI version", "Height (front)", "Height (rear)", "Intel® Turbo Boost Technology", "Internal memory", "Internal memory type", "Maximum internal memory", "Maximum internal memory (64-bit)", "Maximum number of PCI Express lanes", "Maximum on-board graphics card memory", "Maximum refresh rate", "Memory clock speed", "Memory form factor", "Memory layout (slots x size)", "Memory slots", "Native aspect ratio", "Non-operating altitude", "Non-operating shock", "Non-operating vibration", "Number of SSDs installed", "Number of USB ports with PowerShare support", "Number of battery cells", "Number of built-in speakers", "On-board graphics card DirectX version", "On-board graphics card ID", "On-board graphics card OpenGL version", "On-board graphics card base frequency", "On-board graphics card dynamic frequency (max)", "On-board graphics card family", "On-board graphics card model", "Operating altitude", "Operating relative humidity (H-H)", "Operating shock", "Operating system architecture", "Operating system installed", "Operating system language", "Operating temperature (T-T)", "Operating vibration", "PCI Express configurations", "PCI Express slots version", "Pixel density", "Pointing device", "Processor ARK ID", "Processor boost frequency", "Processor cache", "Processor cache type", "Processor codename", "Processor cores", "Processor family", "Processor frequency", "Processor generation", "Processor lithography", "Processor manufacturer", "Processor model", "Processor operating modes", "Processor package size", "Processor socket", "Processor threads", "Product colour", "Product type", "SSD capacity", "SSD form factor", "SSD interface", "Speaker power", "Speakers manufacturer", "Storage media", "Storage relative humidity (H-H)", "Storage temperature (T-T)", "Supported instruction sets", "Sustainability certificates", "System bus rate", "Thermal Design Power (TDP)", "Thunderbolt 3 ports quantity", "Tjunction", "Top Wi-Fi standard", "Total SSDs capacity", "Total storage capacity", "USB 20 ports quantity", "USB 32 Gen 1 (31 Gen 1) Type-A ports quantity", "USB 32 Gen 1 (31 Gen 1) Type-C ports quantity", "USB 32 Gen 2 (31 Gen 2) Type-A ports quantity", "USB 32 Gen 2 (31 Gen 2) Type-C ports quantity", "Video capturing speed", "WLAN controller model", "Weight", "Wi-Fi standards", "Width"]}
{"id": "135078819", "title": "Lenovo ThinkPad T14 Gen 6 (Intel) Intel Core Ultra 5 225U Laptop 35.6 cm (14\") WUXGA 16 GB DDR5-SDRAM 512 GB SSD Wi-Fi 6E (802.11ax) Windows 11 Pro English Black", "brand": "Lenovo", "description": "Lenovo ThinkPad T14 Gen 6 (Intel) Intel Core Ultra 5 225U Laptop 35.6 cm (14\") WUXGA 16 GB DDR5-SDRAM 512 GB SSD Wi-Fi 6E (802.11ax) Windows 11 Pro English Black\n\n\nKey Specifications:\n- **Weight & dimensions**: Weight: 1.38 kg; Width: 315.9 mm; Depth: 223.7 mm; Height (front): 1.09 cm; Height (rear): 1.61 cm\n- **Certificates**: Certification: ENERGY STAR,TCO,EPEAT Gold,RoHS\n- **Security**: Cable lock slot type: Kensington; Trusted Platform Module (TPM) version: 2.0\n- **Power**: AC adapter power: 65 W\n- **Battery**: Battery capacity: 57 Wh\n- **Software**: Operating system installed: Windows 11 Pro; Operating system language: English, French, German, Dutch, Italian\n- **Keyboard**: Pointing device: ThinkPad UltraNav; Keyboard language: English\n- **Performance**: Motherboard chipset: Intel SoC\n- **Ports & interfaces**: USB 2.0 ports quantity: 0; USB 3.2 Gen 1 (3.1 Gen 1) Type-A ports quantity: 2; USB 3.2 Gen 1 (3.1 Gen 1) Type-C ports quantity: 0; HDMI ports quantity: 1; Ethernet LAN (RJ-45) ports: 1; HDMI version: 2.1; Thunderbolt 4 ports quantity: 2\n- **Network**: Top Wi-Fi standard: Wi-Fi 6E (802.11ax); Wi-Fi standards: Wi-Fi 6E (802.11ax); Antenna type: 2x2; WLAN controller model: Intel Wi-Fi 6E AX211; WLAN controller manufacturer: Intel; Ethernet LAN data rates: 100,1000 Mbit/s; Bluetooth version: 5.3; WWAN: Upgradable\n- **Camera**: Front camera resolution (numeric): 5 MP; Privacy type: Privacy shutter\n- **Audio**: Audio chip: Realtek ALC3287; Number of built-in speakers: 2; Speaker power: 2 W; Number of microphones: 2\n- **Graphics**: Discrete graphics card model: Not available; On-board graphics card model: Intel Graphics; On-board GPU manufacturer: Intel; On-board graphics card family: Intel Graphics\n- **Storage**: Total storage capacity: 512 GB; Storage media: SSD; Total SSDs capacity: 512 GB; Number of SSDs installed: 1; SSD capacity: 512 GB; SSD interface: PCI Express 4.0; SSD form factor: M.2\n- **Memory**: Internal memory: 16 GB; Maximum internal memory: 64 GB; Internal memory type: DDR5-SDRAM; Memory clock speed: 5600 MHz; Memory form factor: SO-DIMM; Memory layout (slots x size): 1 x 16 GB\n- **Processor**: Processor family: Intel Core Ultra 5; Processor manufacturer: Intel; Processor model: 225U; Processor cores: 12\n- **Display**: Display diagonal: 35.6 cm (14\"); Display resolution: 1920 x 1200 pixels; HD type: WUXGA; Panel type: IPS; Native aspect ratio: 16:10; Display brightness: 500 cd/m²; RGB colour space: sRGB; Colour gamut: 100%; Maximum refresh rate: 60 Hz\n- **Design**: Product type: Laptop; Product colour: Black; Form factor: Clamshell", "image_url": "https://images.icecat.biz/img/gallery_mediums/a9090ab0628f31a7dc1f9dfb886109ead1a9424c.jpg", "price": 1307.59, "currency": "EUR", "categories": ["Laptops"], "attrs": {"Product type": "Laptop", "Product colour": "Black", "Form factor": "Clamshell", "Display diagonal": "35.6 cm (14\")", "Display resolution": "1920 x 1200 pixels", "HD type": "WUXGA", "Panel type": "IPS", "Native aspect ratio": "16:10", "Display brightness": "500 cd/m²", "RGB colour space": "sRGB", "Colour gamut": "100%", "Maximum refresh rate": "60 Hz", "Processor family": "Intel Core Ultra 5", "Processor manufacturer": "Intel", "Processor model": "225U", "Processor cores": "12", "Internal memory": "16 GB", "Maximum internal memory": "64 GB", "Internal memory type": "DDR5-SDRAM", "Memory clock speed": "5600 MHz", "Memory form factor": "SO-DIMM", "Memory layout (slots x size)": "1 x 16 GB", "Total storage capacity": "512 GB", "Storage media": "SSD", "Total SSDs capacity": "512 GB", "Number of SSDs installed": "1", "SSD capacity": "512 GB", "SSD interface": "PCI Express 4.0", "SSD form factor": "M.2", "Discrete graphics card model": "Not available", "On-board graphics card model": "Intel Graphics", "On-board GPU manufacturer": "Intel", "On-board graphics card family": "Intel Graphics", "Audio chip": "Realtek ALC3287", "Number of built-in speakers": "2", "Speaker power": "2 W", "Number of microphones": "2", "Front camera resolution (numeric)": "5 MP", "Privacy type": "Privacy shutter", "Top Wi-Fi standard": "Wi-Fi 6E (802.11ax)", "Wi-Fi standards": "Wi-Fi 6E (802.11ax)", "Antenna type": "2x2", "WLAN controller model": "Intel Wi-Fi 6E AX211", "WLAN controller manufacturer": "Intel", "Ethernet LAN data rates": "100,1000 Mbit/s", "Bluetooth version": "5.3", "WWAN": "Upgradable", "USB 20 ports quantity": "0", "USB 32 Gen 1 (31 Gen 1) Type-A ports quantity": "2", "USB 32 Gen 1 (31 Gen 1) Type-C ports quantity": "0", "HDMI ports quantity": "1", "Ethernet LAN (RJ-45) ports": "1", "HDMI version": "2.1", "Thunderbolt 4 ports quantity": "2", "Motherboard chipset": "Intel SoC", "Pointing device": "ThinkPad UltraNav", "Keyboard language": "English", "Operating system installed": "Windows 11 Pro", "Operating system language": "English, French, German, Dutch, Italian", "Battery capacity": "57 Wh", "AC adapter power": "65 W", "Cable lock slot type": "Kensington", "Trusted Platform Module (TPM) version": "2.0", "Certification": "ENERGY STAR,TCO,EPEAT Gold,RoHS", "Weight": "1.38 kg", "Width": "315.9 mm", "Depth": "223.7 mm", "Height (front)": "1.09 cm", "Height (rear)": "1.61 cm"}, "attr_keys": ["AC adapter power", "Antenna type", "Audio chip", "Battery capacity", "Bluetooth version", "Cable lock slot type", "Certification", "Colour gamut", "Depth", "Discrete graphics card model", "Display brightness", "Display diagonal", "Display resolution", "Ethernet LAN (RJ-45) ports", "Ethernet LAN data rates", "Form factor", "Front camera resolution (numeric)", "HD type", "HDMI ports quantity", "HDMI version", "Height (front)", "Height (rear)", "Internal memory", "Internal memory type", "Keyboard language", "Maximum internal memory", "Maximum refresh rate", "Memory clock speed", "Memory form factor", "Memory layout (slots x size)", "Motherboard chipset", "Native aspect ratio", "Number of SSDs installed", "Number of built-in speakers", "Number of microphones", "On-board GPU manufacturer", "On-board graphics card family", "On-board graphics card model", "Operating system installed", "Operating system language", "Panel type", "Pointing device", "Privacy type", "Processor cores", "Processor family", "Processor manufacturer", "Processor model", "Product colour", "Product type", "RGB colour space", "SSD capacity", "SSD form factor", "SSD interface", "Speaker power", "Storage media", "Thunderbolt 4 ports quantity", "Top Wi-Fi standard", "Total SSDs capacity", "Total storage capacity", "Trusted Platform Module (TPM) version", "USB 20 ports quantity", "USB 32 Gen 1 (31 Gen 1) Type-A ports quantity", "USB 32 Gen 1 (31 Gen 1) Type-C ports quantity", "WLAN controller manufacturer", "WLAN controller model", "WWAN", "Weight", "Wi-Fi standards", "Width"]}
{"id": "20428159", "title": "Lenovo IdeaPad U330 Touch", "brand": "Lenovo", "description": "Lenovo IdeaPad U330 Touch", "image_url": "https://images.icecat.biz/img/norm/medium/19622108-Lenovo.jpg", "price": 1324.44, "currency": "EUR", "categories": ["Laptops"], "attrs": {}, "attr_keys": []}
{"id": "4559566", "title": "Lenovo ThinkPad W701 Intel® Core™ i7 43.2 cm (17\") 4 GB DDR3-SDRAM 640 GB NVIDIA® Quadro® FX 3800M Windows 7 Professional", "brand": "Neomounts", "description": "Lenovo ThinkPad W701 Intel® Core™ i7 43.2 cm (17\") 4 GB DDR3-SDRAM 640 GB NVIDIA® Quadro® FX 3800M Windows 7 Professional\n\n\nFaster than a speeding bullet, W Series is our most powerful, responsive ThinkPad® ever! Plow through computationally and graphics-intensive applications with lightning-fast Intel® processors, advanced nVIDIA® graphics, cutting-edge technology and the durability and rock-solid reliability you'd expect from Lenovo's ultimate mobile workstation.\n\n\nKey Specifications:\n- **Other features**: Wireless technology: IEEE 802.11a/g/n; Type: PC; Display: LCD; Modem speed: 56 Kbit/s; Modem type: V.92; Intel segment tagging: Professional\n- **Weight & dimensions**: Weight: 4.07 kg\n- **Security**: Cable lock slot type: IBM\n- **Battery**: Number of battery cells: 9\n- **Software**: Operating system installed: Windows 7 Professional\n- **Keyboard**: Pointing device: ThinkPad UltraNav\n- **Ports & interfaces**: USB 2.0 ports quantity: 4; USB 3.2 Gen 1 (3.1 Gen 1) Type-A ports quantity: 1; HDMI ports quantity: 0; eSATA ports quantity: 1; Ethernet LAN (RJ-45) ports: 1; VGA (D-Sub) ports quantity: 1; Firewire (IEEE 1394) ports: 0; Headphone outputs: 1; CardBus PCMCIA slots quantity: 0; Modem (RJ-11) ports: 1; PS/2 ports quantity: 0; Parallel ports quantity: 0; Serial ports quantity: 0\n- **Network**: Networking features: Gigabit Ethernet; Bluetooth version: 2.1+EDR\n- **Graphics**: Discrete graphics card model: NVIDIA® Quadro® FX 3800M\n- **Storage**: Total storage capacity: 640 GB; Optical drive type: DVD±RW; Number of HDDs installed: 2; HDD capacity: 320 GB; HDD interface: SATA; HDD speed: 7200 RPM; Compatible memory cards: MMC, MS PRO, SD, xD\n- **Memory**: Internal memory: 4 GB; Maximum internal memory: 16 GB; Internal memory type: DDR3-SDRAM; Memory clock speed: 1333 MHz\n- **Processor**: Processor family: Intel® Core™ i7; Processor frequency: 2 GHz; System bus rate: 2.5 GT/s; Processor cache: 8 MB; Processor cache type: L3\n- **Display**: Display diagonal: 43.2 cm (17\"); Display resolution: 1920 x 1200 pixels; Native aspect ratio: 16:10; Display brightness: 280 cd/m²", "image_url": "https://images.icecat.biz/img/norm/medium/4559566-4741.jpg", "price": 794.7, "currency": "EUR", "categories": ["Laptops"], "attrs": {"Display diagonal": "43.2 cm (17\")", "Display resolution": "1920 x 1200 pixels", "Native aspect ratio": "16:10", "Display brightness": "280 cd/m²", "Processor family": "Intel® Core™ i7", "Processor frequency": "2 GHz", "System bus rate": "2.5 GT/s", "Processor cache": "8 MB", "Processor cache type": "L3", "Internal memory": "4 GB", "Maximum internal memory": "16 GB", "Internal memory type": "DDR3-SDRAM", "Memory clock speed": "1333 MHz", "Total storage capacity": "640 GB", "Optical drive type": "DVD±RW", "Number of HDDs installed": "2", "HDD capacity": "320 GB", "HDD interface": "SATA", "HDD speed": "7200 RPM", "Compatible memory cards": "MMC, MS PRO, SD, xD", "Discrete graphics card model": "NVIDIA® Quadro® FX 3800M", "Networking features": "Gigabit Ethernet", "Bluetooth version": "2.1+EDR", "USB 20 ports quantity": "4", "USB 32 Gen 1 (31 Gen 1) Type-A ports quantity": "1", "HDMI ports quantity": "0", "eSATA ports quantity": "1", "Ethernet LAN (RJ-45) ports": "1", "VGA (D-Sub) ports quantity": "1", "Firewire (IEEE 1394) ports": "0", "Headphone outputs": "1", "CardBus PCMCIA slots quantity": "0", "Modem (RJ-11) ports": "1", "PS/2 ports quantity": "0", "Parallel ports quantity": "0", "Serial ports quantity": "0", "Pointing device": "ThinkPad UltraNav", "Operating system installed": "Windows 7 Professional", "Number of battery cells": "9", "Cable lock slot type": "IBM", "Weight": "4.07 kg", "Wireless technology": "IEEE 802.11a/g/n", "Type": "PC", "Display": "LCD", "Modem speed": "56 Kbit/s", "Modem type": "V.92", "Intel segment tagging": "Professional"}, "attr_keys": ["Bluetooth version", "Cable lock slot type", "CardBus PCMCIA slots quantity", "Compatible memory cards", "Discrete graphics card model", "Display", "Display brightness", "Display diagonal", "Display resolution", "Ethernet LAN (RJ-45) ports", "Firewire (IEEE 1394) ports", "HDD capacity", "HDD interface", "HDD speed", "HDMI ports quantity", "Headphone outputs", "Intel segment tagging", "Internal memory", "Internal memory type", "Maximum internal memory", "Memory clock speed", "Modem (RJ-11) ports", "Modem speed", "Modem type", "Native aspect ratio", "Networking features", "Number of HDDs installed", "Number of battery cells", "Operating system installed", "Optical drive type", "PS/2 ports quantity", "Parallel ports quantity", "Pointing device", "Processor cache", "Processor cache type", "Processor family", "Processor frequency", "Serial ports quantity", "System bus rate", "Total storage capacity", "Type", "USB 20 ports quantity", "USB 32 Gen 1 (31 Gen 1) Type-A ports quantity", "VGA (D-Sub) ports quantity", "Weight", "Wireless technology", "eSATA ports quantity"]}
