{"id": "5915327", "title": "Samsung SGH-U700B", "brand": "CoreParts", "description": "Samsung SGH-U700B", "image_url": "https://images.icecat.biz/img/gallery_mediums/img_5915327_medium_1481198225_0927_8346.jpg", "price": 637.1, "currency": "EUR", "categories": ["Mobile Phones"], "attrs": {}, "attr_keys": []}
{"id": "3797164", "title": "Samsung GT-S7550 7.62 cm (3\") 119 g Blue", "brand": "Samsung", "description": "Samsung GT-S7550 7.62 cm (3\") 119 g Blue\n\n\nKey Specifications:\n- **Certificates**: Specific absorption rate (SAR) value (EU): 1.08 W/kg\n- **Other features**: Bundled software: PowerPoint, Office; USB 2.0 ports quantity: 1\n- **Phone features**: Form factor: Bar; Personal info management (PIM): Alarm clock, Calculator, Calendar, Countdown timer, Notes, Stopwatch, To-do list; Phonebook capacity: 1000 entries; Text prediction system type: T9\n- **Weight & dimensions**: Weight: 119 g; Width: 54 mm; Depth: 14.2 mm; Height: 109 mm\n- **Power**: Battery capacity: 1080 mAh; Talk time (2G): 4.2 h; Standby time (2G): 300 h; Battery technology: Lithium-Ion (Li-Ion)\n- **Audio**: Ringer type: Polyphonic\n- **Video**: Video capture resolution (max): 320 x 240 pixels\n- **Ports & interfaces**: Headphone connectivity: 3.5 mm\n- **Data transmission**: Bluetooth version: 2.1+EDR\n- **Network**: SIM card capability: Single SIM; Mobile network generation: 3G; Data network: 3G\n- **Camera**: Digital zoom: 4x; Photo effects: Negative film, Sepia\n- **Memory**: Internal memory: 130 MB; Maximum memory card size: 16 GB\n- **Display**: Display diagonal: 7.62 cm (3\"); Display resolution: 400 x 240 pixels; Display number of colours: 16.78 million colours\n- **Design**: Product colour: Blue", "image_url": "https://images.icecat.biz/img/gallery_mediums/img_3797164_medium_1481101725_0253_23568.jpg", "price": 640.25, "currency": "EUR", "categories": ["Mobile Phones"], "attrs": {"Product colour": "Blue", "Display diagonal": "7.62 cm (3\")", "Display resolution": "400 x 240 pixels", "Display number of colours": "16.78 million colours", "Internal memory": "130 MB", "Maximum memory card size": "16 GB", "Digital zoom": "4x", "Photo effects": "Negative film, Sepia", "SIM card capability": "Single SIM", "Mobile network generation": "3G", "Data network": "3G", "Bluetooth version": "2.1+EDR", "Headphone connectivity": "3.5 mm", "Video capture resolution (max)": "320 x 240 pixels", "Ringer type": "Polyphonic", "Battery capacity": "1080 mAh", "Talk time (2G)": "4.2 h", "Standby time (2G)": "300 h", "Battery technology": "Lithium-Ion (Li-Ion)", "Weight": "119 g", "Width": "54 mm", "Depth": "14.2 mm", "Height": "109 mm", "Form factor": "Bar", "Personal info management (PIM)": "Alarm clock, Calculator, Calendar, Countdown timer, Notes, Stopwatch, To-do list", "Phonebook capacity": "1000 entries", "Text prediction system type": "T9", "Bundled software": "PowerPoint, Office", "USB 20 ports quantity": "1", "Specific absorption rate (SAR) value (EU)": "1.08 W/kg"}, "attr_keys": ["Battery capacity", "Battery technology", "Bluetooth version", "Bundled software", "Data network", "Depth", "Digital zoom", "Display diagonal", "Display number of colours", "Display resolution", "Form factor", "Headphone connectivity", "Height", "Internal memory", "Maximum memory card size", "Mobile network generation", "Personal info management (PIM)", "Phonebook capacity", "Photo effects", "Product colour", "Ringer type", "SIM card capability", "Specific absorption rate (SAR) value (EU)", "Standby time (2G)", "Talk time (2G)", "Text prediction system type", "USB 20 ports quantity", "Video capture resolution (max)", "Weight", "Width"]}
{"id": "5914910", "title": "Samsung SGH-Z240", "brand": "Samsung", "description": "Samsung SGH-Z240", "image_url": "https://images.icecat.biz/img/gallery_mediums/img_5914910_medium_1481198167_3991_8346.jpg", "price": 646.88, "currency": "EUR", "categories": ["Mobile Phones"], "attrs": {}, "attr_keys": []}
{"id": "3541465", "title": "Samsung S7220 5.59 cm (2.2\") 88 g Black", "brand": "Samsung", "description": "Samsung S7220 5.59 cm (2.2\") 88 g Black\n\n\nSAMSUNG’s Ultra features a premium bar design derived from understatement; a slender form, slight curve and vibrant accent. Equally impressive is the industry’s best display. The mobile phone turns into an absolute eye-catcher when the photos taken with the 5-megapixel camera are shown on the 2.2\" AMOLED display. ultimate design What you use everyday is extension of your personal style. You will benefit from sleek design and premium metal detail. Stylish users will be enticed by the simplistic yet sophisticated beauty of this bar. The compact size is portable, and won’t break a wrinkle when slipped into the pocket or bag. ultimate camera You can capture precious memories easily in the form of incredibly high quality photographs. Handy and easy to use, the embedded camera offers the user a convenient way to preserve their memories in digital form. Professional functions eliminate the need to carry a separate camera. music entertainment This mobile is always on hand, so you can enjoy convenient access to music without needing a second device. You will be able to experience a true MP3 like interface while listening to their favorite songs, all of which are accessible 24/7 thanks to ample microSD storage. connectivity You can access other networks and mobile peripherals, including mobile printers and stereo headsets, using Bluetooth 2.1 EDR or USB 2.0. Both services enables you to make speedy downloads of contents. In addition, HSDPA connectivity offers fast OTA connections for content downloading. ultimate display You will be impressed by the incredible quality of the display when viewing various applications. Brighter and more vibrant than any other mobile display, the AMOLED screen will enhance photo and video browsing as well as web-surfing. video recording Able to capture not just pictures but also videos. You will be able to preserve memories as they happen. You will enjoy playing back video, too, thanks to clear view of AMOLED. FM radio You can enjoy instant access to popular music and up-to-date information and news. You will appreciate the audio variety offered, which is all free-of-charge with no prior downloading necessary. RDS provides info like station identification, name of songs and radio show info so you always know what you’re listening to.\n\n\nKey Specifications:\n- **Other features**: USB 2.0 ports quantity: 1; Playback formats: MP3, WMA, AAC, AAC+, e-AAC+, AMR\n- **Phone features**: Form factor: Bar; Personal info management (PIM): Alarm clock, Calculator, Calendar, To-do list; Phonebook capacity: 1000 entries; Text prediction system type: T9\n- **Weight & dimensions**: Weight: 88 g; Width: 48 mm; Depth: 11.8 mm; Height: 114 mm\n- **Power**: Battery capacity: 960 mAh; Talk time (2G): 4 h; Standby time (2G): 350 h; Battery technology: Lithium-Ion (Li-Ion)\n- **Audio**: Ringer type: Polyphonic\n- **Video**: Video compression formats: H.263, MPEG4\n- **Data transmission**: Bluetooth version: 2.1+EDR\n- **Network**: Data network: Edge, GPRS\n- **Camera**: Rear camera resolution (numeric): 5 MP; Digital zoom: 4x\n- **Memory**: Internal memory: 117 MB; Internal storage capacity: 8 GB\n- **Display**: Display diagonal: 5.59 cm (2.2\"); Display resolution: 240 x 320 pixels; Display type: AMOLED; Panel type: AMOLED; Display number of colours: 262144 colours\n- **Design**: Product colour: Black", "image_url": "https://images.icecat.biz/img/gallery_mediums/img_3541465_medium_1481108513_9932_23531.jpg", "price": 833.69, "currency": "EUR", "categories": ["Mobile Phones"], "attrs": {"Product colour": "Black", "Display diagonal": "5.59 cm (2.2\")", "Display resolution": "240 x 320 pixels", "Display type": "AMOLED", "Panel type": "AMOLED", "Display number of colours": "262144 colours", "Internal memory": "117 MB", "Internal storage capacity": "8 GB", "Rear camera resolution (numeric)": "5 MP", "Digital zoom": "4x", "Data network": "Edge, GPRS", "Bluetooth version": "2.1+EDR", "Video compression formats": "H.263, MPEG4", "Ringer type": "Polyphonic", "Battery capacity": "960 mAh", "Talk time (2G)": "4 h", "Standby time (2G)": "350 h", "Battery technology": "Lithium-Ion (Li-Ion)", "Weight": "88 g", "Width": "48 mm", "Depth": "11.8 mm", "Height": "114 mm", "Form factor": "Bar", "Personal info management (PIM)": "Alarm clock, Calculator, Calendar, To-do list", "Phonebook capacity": "1000 entries", "Text prediction system type": "T9", "USB 20 ports quantity": "1", "Playback formats": "MP3, WMA, AAC, AAC+, e-AAC+, AMR"}, "attr_keys": ["Battery capacity", "Battery technology", "Bluetooth version", "Data network", "Depth", "Digital zoom", "Display diagonal", "Display number of colours", "Display resolution", "Display type", "Form factor", "Height", "Internal memory", "Internal storage capacity", "Panel type", "Personal info management (PIM)", "Phonebook capacity", "Playback formats", "Product colour", "Rear camera resolution (numeric)", "Ringer type", "Standby time (2G)", "Talk time (2G)", "Text prediction system type", "USB 20 ports quantity", "Video compression formats", "Weight", "Width"]}
{"id": "5913758", "title": "Samsung GT-E1310B", "brand": "Samsung", "description": "Samsung GT-E1310B", "image_url": "https://images.icecat.biz/img/gallery_mediums/img_5913758_medium_1481198041_6419_8346.jpg", "price": 780.65, "currency": "EUR", "categories": ["Mobile Phones"], "attrs": {}, "attr_keys": []}
{"id": "113160618", "title": "Emporia emporiaPRIME-LTE 5.87 cm (2.31\") 107 g Black Senior phone", "brand": "Emporia", "description": "Emporia emporiaPRIME-LTE 5.87 cm (2.31\") 107 g Black Senior phone\n\n\nKey Specifications:\n- **Certificates**: Specific absorption rate (SAR) value (EU): 1.36 W/kg\n- **Other features**: Warranty period: 2 year(s)\n- **Packaging content**: Cables included: USB Type-C\n- **Keyboard**: Keyboard layout: Alphanumeric keypad\n- **Phone features**: Form factor: Bar\n- **Technical details**: Standby time: 185 h; Talk time: 390 h\n- **Weight & dimensions**: Weight: 107 g; Width: 61 mm; Depth: 120 mm; Height: 13 mm\n- **Power**: Battery capacity: 1400 mAh; Battery technology: Lithium-Ion (Li-Ion)\n- **Ports & interfaces**: USB connector type: USB Type-C\n- **Data transmission**: Bluetooth version: 5.0\n- **Network**: SIM card capability: Single SIM; Mobile network generation: 4G; Data network: LTE, WCDMA; SIM card type: NanoSIM; 2G bands (primary SIM): 900,2100 MHz; WCDMA bands supported: 900,2100 MHz\n- **Camera**: Rear camera resolution (numeric): 2 MP\n- **Memory**: Compatible memory cards: MicroSD (TransFlash); Flash memory: 8 MB; RAM capacity: 64 MB; ROM capacity: 128 MB\n- **Display**: Display diagonal: 5.87 cm (2.31\"); Display resolution: 320 x 240 pixels\n- **Design**: Product colour: Black; Type: Senior phone", "image_url": "https://images.icecat.biz/img/gallery_mediums/d0128eedf44127d6d0e5dae6c1d2376a468328e1.jpg", "price": 495.5, "currency": "EUR", "categories": ["Mobile Phones"], "attrs": {"Product colour": "Black", "Type": "Senior phone", "Display diagonal": "5.87 cm (2.31\")", "Display resolution": "320 x 240 pixels", "Compatible memory cards": "MicroSD (TransFlash)", "Flash memory": "8 MB", "RAM capacity": "64 MB", "ROM capacity": "128 MB", "Rear camera resolution (numeric)": "2 MP", "SIM card capability": "Single SIM", "Mobile network generation": "4G", "Data network": "LTE, WCDMA", "SIM card type": "NanoSIM", "2G bands (primary SIM)": "900,2100 MHz", "WCDMA bands supported": "900,2100 MHz", "Bluetooth version": "5.0", "USB connector type": "USB Type-C", "Battery capacity": "1400 mAh", "Battery technology": "Lithium-Ion (Li-Ion)", "Weight": "107 g", "Width": "61 mm", "Depth": "120 mm", "Height": "13 mm", "Standby time": "185 h", "Talk time": "390 h", "Form factor": "Bar", "Keyboard layout": "Alphanumeric keypad", "Cables included": "USB Type-C", "Warranty period": "2 year(s)", "Specific absorption rate (SAR) value (EU)": "1.36 W/kg"}, "attr_keys": ["2G bands (primary SIM)", "Battery capacity", "Battery technology", "Bluetooth version", "Cables included", "Compatible memory cards", "Data network", "Depth", "Display diagonal", "Display resolution", "Flash memory", "Form factor", "Height", "Keyboard layout", "Mobile network generation", "Product colour", "RAM capacity", "ROM capacity", "Rear camera resolution (numeric)", "SIM card capability", "SIM card type", "Specific absorption rate (SAR) value (EU)", "Standby time", "Talk time", "Type", "USB connector type", "WCDMA bands supported", "Warranty period", "Weight", "Width"]}
{"id": "3744761", "title": "LG GD900 CRYSTAL 7.62 cm (3\") 127 g", "brand": "LG", "description": "LG GD900 CRYSTAL 7.62 cm (3\") 127 g\n\n\nUNWRAP THE FUTURE OF TOUCH LG are proud to unveil a new touch sensation, the LG GD900 Crystal. The transparent Crystal Touchpad is used like a mouse pad allowing you to glide, stroke and navigate with ease. Surfing the internet is effortless with high–speed browsing and it’s simple to edit photos taken with the 8 megapixel camera. Crystal Touchpad Crystal Touchpad delivers a more intuitive and controlled experience. The Crystal Touchpad uses Multi Finger Touch to allow you to zoom in and out, Mouse Mode to allow you to navigate a webpage without touching the screen as well as Finger Writing Recognition. 8 Megapixel Camera Enjoy clear, high-quality mobile phone pictures and advanced camera functions in every setting with a built-in 8 megapixel camera featuring Smartlight™ technology. 3 inch Full Touchscreen The LG GD900 Crystal offers a great viewing experience with a wide and sharp 3-inch WVGA screen. It is so easy to use with its super fast S Class UI allowing you to revolve the playful 3D cube to get into four different home screens – contacts, widgets, shortcuts and a customisable home screen. Gesture Shortcut When using the Gesture shortcut function on the LG GD900 Crystal, you can command 9 multitasking applications by drawing the designated characters on the Touchpad. You will be taken directly to your music, messages and many more.\n\n\nKey Specifications:\n- **Other features**: Interface: MicroUSB; Networking type: GSM/GPRS/EDGE/UMTS/HSDPA; Operating frequency: 850/900/1800/1900/2100 MHz; Wireless technology: 802.11 b/g; Browser supported: xHTML 1.1, HTML 4.01; Playback formats: MP3, AAC/AAC+/E-AAC+/AMR-NB/WB/WB+, WMA/WMAPro, Ogg-Vorbis, AC3, MIDI\n- **Keyboard**: Keyboard layout: QWERTY\n- **Phone features**: Form factor: Slider; Personal info management (PIM): Alarm clock, Calculator, Calendar, Notes; Phonebook capacity: 1000 entries; Embedded games: 2; Text prediction system type: T9\n- **Weight & dimensions**: Weight: 127 g; Width: 52.5 mm; Depth: 13.5 mm; Height: 105 mm\n- **Power**: Battery capacity: 1000 mAh; Talk time (2G): 6 h; Standby time (2G): 300 h; Battery technology: Lithium-Ion (Li-Ion)\n- **Audio**: Ringer type: Polyphonic; Polyphonic rings quantity: 64\n- **Video**: Video capture resolution (max): 720 x 480 pixels; Video compression formats: 3gp, DivX, H.263, Mpeg4; Maximum frame rate: 30 fps\n- **Data transmission**: Bluetooth version: 2.1+EDR\n- **Network**: Mobile network generation: 3G; Data network: 3G, Edge, GPRS\n- **Camera**: Rear camera resolution (numeric): 8 MP; Rear camera resolution: 3264 x 2448 pixels; Digital zoom: 4x\n- **Memory**: Internal memory: 1536 MB; Internal storage capacity: 32 GB\n- **Display**: Display diagonal: 7.62 cm (3\"); Display resolution: 480 x 800 pixels; Display type: TFT; Panel type: TFT; Display number of colours: 16.78 million colours", "image_url": "https://images.icecat.biz/img/gallery_mediums/img_3663433_medium_1481116632_3685_23531.jpg", "price": 603.5, "currency": "EUR", "categories": ["Mobile Phones"], "attrs": {"Display diagonal": "7.62 cm (3\")", "Display resolution": "480 x 800 pixels", "Display type": "TFT", "Panel type": "TFT", "Display number of colours": "16.78 million colours", "Internal memory": "1536 MB", "Internal storage capacity": "32 GB", "Rear camera resolution (numeric)": "8 MP", "Rear camera resolution": "3264 x 2448 pixels", "Digital zoom": "4x", "Mobile network generation": "3G", "Data network": "3G, Edge, GPRS", "Bluetooth version": "2.1+EDR", "Video capture resolution (max)": "720 x 480 pixels", "Video compression formats": "3gp, DivX, H.263, Mpeg4", "Maximum frame rate": "30 fps", "Ringer type": "Polyphonic", "Polyphonic rings quantity": "64", "Battery capacity": "1000 mAh", "Talk time (2G)": "6 h", "Standby time (2G)": "300 h", "Battery technology": "Lithium-Ion (Li-Ion)", "Weight": "127 g", "Width": "52.5 mm", "Depth": "13.5 mm", "Height": "105 mm", "Form factor": "Slider", "Personal info management (PIM)": "Alarm clock, Calculator, Calendar, Notes", "Phonebook capacity": "1000 entries", "Embedded games": "2", "Text prediction system type": "T9", "Keyboard layout": "QWERTY", "Interface": "MicroUSB", "Networking type": "GSM/GPRS/EDGE/UMTS/HSDPA", "Operating frequency": "850/900/1800/1900/2100 MHz", "Wireless technology": "802.11 b/g", "Browser supported": "xHTML 1.1, HTML 4.01", "Playback formats": "MP3, AAC/AAC+/E-AAC+/AMR-NB/WB/WB+, WMA/WMAPro, Ogg-Vorbis, AC3, MIDI"}, "attr_keys": ["Battery capacity", "Battery technology", "Bluetooth version", "Browser supported", "Data network", "Depth", "Digital zoom", "Display diagonal", "Display number of colours", "Display resolution", "Display type", "Embedded games", "Form factor", "Height", "Interface", "Internal memory", "Internal storage capacity", "Keyboard layout", "Maximum frame rate", "Mobile network generation", "Networking type", "Operating frequency", "Panel type", "Personal info management (PIM)", "Phonebook capacity", "Playback formats", "Polyphonic rings quantity", "Rear camera resolution", "Rear camera resolution (numeric)", "Ringer type", "Standby time (2G)", "Talk time (2G)", "Text prediction system type", "Video capture resolution (max)", "Video compression formats", "Weight", "Width", "Wireless technology"]}
{"id": "5916150", "title": "Samsung GT-E1107", "brand": "Samsung", "description": "Samsung GT-E1107", "image_url": "https://images.icecat.biz/img/gallery_mediums/img_5913746_medium_1481198038_9056_8346.jpg", "price": 463.58, "currency": "EUR", "categories": ["Mobile Phones"], "attrs": {}, "attr_keys": []}
{"id": "2095382", "title": "Sony T707 5.59 cm (2.2\") 95 g Pink", "brand": "Sony", "description": "Sony T707 5.59 cm (2.2\") 95 g Pink\n\n\nLet your friends light it up Give your best friends their own, unique pulsating light effects. When a call from one of them comes in, you'll know who it is in a flash. Glamour and magic The lustrous colours of the T707 add some extra glamour into your life. And there's magic, too - you control your phone with a wave of your hand. Share your life Capture life as it happens around you with the 3.2 megapixel camera. Share with friends - post your pictures on your blog with just a few clicks.\n\n\nKey Specifications:\n- **Other features**: Interface: USB; Networking type: EDGE, GSM, UMTS, HSDPA; Operating frequency: 850/900/1800/1900/2100 MHz; Browser supported: Access NetFront; USB 2.0 ports quantity: 1; Playback formats: MP3/eAAC+/WMA\n- **Phone features**: Form factor: Clamshell; Personal info management (PIM): Alarm clock, Calculator, Calendar, Countdown timer, Notes, Stopwatch, To-do list; Phonebook capacity: 1000 entries; Text prediction system type: T9\n- **Weight & dimensions**: Weight: 95 g; Width: 50 mm; Depth: 14.1 mm; Height: 93 mm\n- **Power**: Talk time (2G): 10 h; Standby time (2G): 400 h; Talk time (3G): 4 h; Standby time (3G): 400 h\n- **Audio**: Ringer type: Polyphonic\n- **Data transmission**: Bluetooth version: 2.0+EDR\n- **Network**: SIM card capability: Single SIM; Mobile network generation: 3G; Data network: 3G, Edge, GPRS, HSDPA; GSM bands supported: 850,900,1800,1900 MHz; WCDMA bands supported: 2100 MHz\n- **Camera**: Rear camera resolution (numeric): 3.2 MP; Rear camera resolution: 2048 x 1536 pixels\n- **Memory**: Internal memory: 100 MB; Maximum memory card size: 16 GB\n- **Display**: Display diagonal: 5.59 cm (2.2\"); Display resolution: 240 x 320 pixels; Display type: TFT; Panel type: TFT; Display number of colours: 262144 colours; External display resolution: 128 x 36 pixels\n- **Design**: Product colour: Pink", "image_url": "https://images.icecat.biz/img/gallery_mediums/img_2095382_medium_1481022200_8438_12184.jpg", "price": 700.7, "currency": "EUR", "categories": ["Mobile Phones"], "attrs": {"Product colour": "Pink", "Display diagonal": "5.59 cm (2.2\")", "Display resolution": "240 x 320 pixels", "Display type": "TFT", "Panel type": "TFT", "Display number of colours": "262144 colours", "External display resolution": "128 x 36 pixels", "Internal memory": "100 MB", "Maximum memory card size": "16 GB", "Rear camera resolution (numeric)": "3.2 MP", "Rear camera resolution": "2048 x 1536 pixels", "SIM card capability": "Single SIM", "Mobile network generation": "3G", "Data network": "3G, Edge, GPRS, HSDPA", "GSM bands supported": "850,900,1800,1900 MHz", "WCDMA bands supported": "2100 MHz", "Bluetooth version": "2.0+EDR", "Ringer type": "Polyphonic", "Talk time (2G)": "10 h", "Standby time (2G)": "400 h", "Talk time (3G)": "4 h", "Standby time (3G)": "400 h", "Weight": "95 g", "Width": "50 mm", "Depth": "14.1 mm", "Height": "93 mm", "Form factor": "Clamshell", "Personal info management (PIM)": "Alarm clock, Calculator, Calendar, Countdown timer, Notes, Stopwatch, To-do list", "Phonebook capacity": "1000 entries", "Text prediction system type": "T9", "Interface": "USB", "Networking type": "EDGE, GSM, UMTS, HSDPA", "Operating frequency": "850/900/1800/1900/2100 MHz", "Browser supported": "Access NetFront", "USB 20 ports quantity": "1", "Playback formats": "MP3/eAAC+/WMA"}, "attr_keys": ["Bluetooth version", "Browser supported", "Data network", "Depth", "Display diagonal", "Display number of colours", "Display resolution", "Display type", "External display resolution", "Form factor", "GSM bands supported", "Height", "Interface", "Internal memory", "Maximum memory card size", "Mobile network generation", "Networking type", "Operating frequency", "Panel type", "Personal info management (PIM)", "Phonebook capacity", "Playback formats", "Product colour", "Rear camera resolution", "Rear camera resolution (numeric)", "Ringer type", "SIM card capability", "Standby time (2G)", "Standby time (3G)", "Talk time (2G)", "Talk time (3G)", "Text prediction system type", "USB 20 ports quantity", "WCDMA bands supported", "Weight", "Width"]}
{"id": "4567870", "title": "Samsung S3550 5.08 cm (2\") 79 g White", "brand": "Samsung", "description": "Samsung S3550 5.08 cm (2\") 79 g White\n\n\nStylish design, camera 2 megapixel, bluetooth stereo memory expandable to 30MB are characteristics differentiating of new Samsung Shark Slide. Comfortable Sleek, Curvilinear Chic Curvilinear shapes updates the mobile form with twists and curves. Patterned metallic back cover enforces the premium look of the slider. Compact size offers sleek portability and ergonomic comfort The Paragon of the Mobile User Experience 3 soft keys adopt to your needs, helping you intuitively navigate through the mobile. Optimised scenarios streamline navigation paths for commonly used functions such as message composition. Effective layout increases visibility and readability of the menu screens Your Mobile Social Life Easily share your pictures with your online social communities – instant uploads of photos to your favourite social networking sites. Multi instant messenger consolidates friends lists from various IM services into one unified contact list for easy access on the go.\n\n\nKey Specifications:\n- **Other features**: Networking type: GSM; Operating frequency: 900/ 1800/ 1900/ 850 MHz; USB 2.0 ports quantity: 1; Playback formats: MP3/WAV/eAAC+/WMA\n- **Phone features**: Form factor: Slider; Personal info management (PIM): Alarm clock, Calculator, Calendar, Countdown timer, Notes, Stopwatch, To-do list; Phonebook capacity: 1000 entries; Text prediction system type: T9\n- **Weight & dimensions**: Weight: 79 g; Width: 46 mm; Depth: 14.4 mm; Height: 96 mm\n- **Power**: Battery capacity: 800 mAh; Talk time (2G): 7.5 h; Standby time (2G): 430 h; Battery technology: Lithium-Ion (Li-Ion)\n- **Audio**: Ringer type: Polyphonic\n- **Data transmission**: Bluetooth version: 2.1+EDR\n- **Network**: SIM card capability: Single SIM; Data network: Edge, GPRS\n- **Camera**: Rear camera resolution (numeric): 2 MP; Rear camera resolution: 1600 x 1200 pixels; Digital zoom: 2x\n- **Memory**: Internal memory: 42 MB; Internal storage capacity: 8 GB\n- **Display**: Display diagonal: 5.08 cm (2\"); Display resolution: 240 x 320 pixels; Display type: TFT; Panel type: TFT; Display number of colours: 262144 colours\n- **Design**: Product colour: White", "image_url": "https://images.icecat.biz/img/gallery_mediums/img_4567870_medium_1481117865_9996_23752.jpg", "price": 824.33, "currency": "EUR", "categories": ["Mobile Phones"], "attrs": {"Product colour": "White", "Display diagonal": "5.08 cm (2\")", "Display resolution": "240 x 320 pixels", "Display type": "TFT", "Panel type": "TFT", "Display number of colours": "262144 colours", "Internal memory": "42 MB", "Internal storage capacity": "8 GB", "Rear camera resolution (numeric)": "2 MP", "Rear camera resolution": "1600 x 1200 pixels", "Digital zoom": "2x", "SIM card capability": "Single SIM", "Data network": "Edge, GPRS", "Bluetooth version": "2.1+EDR", "Ringer type": "Polyphonic", "Battery capacity": "800 mAh", "Talk time (2G)": "7.5 h", "Standby time (2G)": "430 h", "Battery technology": "Lithium-Ion (Li-Ion)", "Weight": "79 g", "Width": "46 mm", "Depth": "14.4 mm", "Height": "96 mm", "Form factor": "Slider", "Personal info management (PIM)": "Alarm clock, Calculator, Calendar, Countdown timer, Notes, Stopwatch, To-do list", "Phonebook capacity": "1000 entries", "Text prediction system type": "T9", "Networking type": "GSM", "Operating frequency": "900/ 1800/ 1900/ 850 MHz", "USB 20 ports quantity": "1", "Playback formats": "MP3/WAV/eAAC+/WMA"}, "attr_keys": ["Battery capacity", "Battery technology", "Bluetooth version", "Data network", "Depth", "Digital zoom", "Display diagonal", "Display number of colours", "Display resolution", "Display type", "Form factor", "Height", "Internal memory", "Internal storage capacity", "Networking type", "Operating frequency", "Panel type", "Personal info management (PIM)", "Phonebook capacity", "Playback formats", "Product colour", "Rear camera resolution", "Rear camera resolution (numeric)", "Ringer type", "SIM card capability", "Standby time (2G)", "Talk time (2G)", "Text prediction system type", "USB 20 ports quantity", "Weight", "Width"]}
