{"id": "23207885", "title": "Hama Slim mobile phone case Folio White", "brand": "Hama", "description": "Hama Slim mobile phone case Folio White\n\n\n- Optimum protection for the Samsung Galaxy S5 mini from dirt and scratches as the smartphone can be used in the folding case - Slip-in compartment for safely storing cards or the like - Openings for full access to connections - Slim smartphone case with a pleasant silky surface - Without fastener\n\n\nKey Specifications:\n- **Packaging content**: Quantity per pack: 1 pc(s)\n- **Features**: Case type: Folio; Material: Polyurethane; Product colour: White; Brand compatibility: Samsung; Compatibility: Galaxy S5 mini; Protection features: Scratch resistant", "image_url": "https://images.icecat.biz/img/gallery_mediums/img_23097659_medium_1483437997_9334_15232.jpg", "price": 19.7, "currency": "EUR", "categories": ["Mobile Phone Cases"], "attrs": {"Case type": "Folio", "Material": "Polyurethane", "Product colour": "White", "Brand compatibility": "Samsung", "Compatibility": "Galaxy S5 mini", "Protection features": "Scratch resistant", "Quantity per pack": "1 pc(s)"}, "attr_keys": ["Brand compatibility", "Case type", "Compatibility", "Material", "Product colour", "Protection features", "Quantity per pack"]}
{"id": "125204077", "title": "iDeal of Sweden Seamless Case Galaxy S22P Coal Black", "brand": "iDeal of Sweden", "description": "iDeal of Sweden Seamless Case Galaxy S22P Coal Black\n\n\nThe Seamless Case in Coal Black presents an ultra-minimalist design that seamlessly embraces the phone. The muted shades and matte finish add a serene note, while the logo in matching shades enhances the design’s sleek appearance.\n\n\nKey Specifications:\n- **Logistics data**: Harmonized System (HS) code: 3926909790; Master (outer) case width: 404 mm; Master (outer) case length: 300 mm; Master (outer) case height: 525 mm; Master (outer) case gross weight: 14.1 kg; Products per master (outer) case: 80 pc(s); Master (outer) case GTIN (EAN/UPC): 7340205151644; Shipping (inner) case width: 25 cm; Shipping (inner) case length: 13.5 cm; Shipping (inner) case height: 38.4 cm; Shipping (inner) case gross weight: 3.02 kg; Products per shipping (inner) case: 20 pc(s); Shipping (inner) case GTIN (EAN/UPC): 7340205151637\n- **Packaging data**: Package width: 112 mm; Package depth: 199 mm; Package height: 22 mm; Package weight: 115 g\n- **Weight & dimensions**: Width: 79 mm; Depth: 160 mm; Height: 11 mm; Weight: 45 g\n- **Features**: Product colour: Black; Brand compatibility: Samsung; Compatibility: S22 Plus; Country of origin: China", "image_url": "https://images.icecat.biz/img/gallery_mediums/7bc3efa0677af65569837421ad343c40e87ba5bd.jpg", "price": 20.29, "currency": "EUR", "categories": ["Mobile Phone Cases"], "attrs": {"Product colour": "Black", "Brand compatibility": "Samsung", "Compatibility": "S22 Plus", "Country of origin": "China", "Width": "79 mm", "Depth": "160 mm", "Height": "11 mm", "Weight": "45 g", "Package width": "112 mm", "Package depth": "199 mm", "Package height": "22 mm", "Package weight": "115 g", "Harmonized System (HS) code": "3926909790", "Master (outer) case width": "404 mm", "Master (outer) case length": "300 mm", "Master (outer) case height": "525 mm", "Master (outer) case gross weight": "14.1 kg", "Products per master (outer) case": "80 pc(s)", "Master (outer) case GTIN (EAN/UPC)": "7340205151644", "Shipping (inner) case width": "25 cm", "Shipping (inner) case length": "13.5 cm", "Shipping (inner) case height": "38.4 cm", "Shipping (inner) case gross weight": "3.02 kg", "Products per shipping (inner) case": "20 pc(s)", "Shipping (inner) case GTIN (EAN/UPC)": "7340205151637"}, "attr_keys": ["Brand compatibility", "Compatibility", "Country of origin", "Depth", "Harmonized System (HS) code", "Height", "Master (outer) case GTIN (EAN/UPC)", "Master (outer) case gross weight", "Master (outer) case height", "Master (outer) case length", "Master (outer) case width", "Package depth", "Package height", "Package weight", "Package width", "Product colour", "Products per master (outer) case", "Products per shipping (inner) case", "Shipping (inner) case GTIN (EAN/UPC)", "Shipping (inner) case gross weight", "Shipping (inner) case height", "Shipping (inner) case length", "Shipping (inner) case width", "Weight", "Width"]}
{"id": "29796907", "title": "Speck Grip mobile phone case 14 cm (5.5\") Cover Pink", "brand": "Speck", "description": "Speck Grip mobile phone case 14 cm (5.5\") Cover Pink\n\n\nGive your iPhone 6s Plus & 6 Plus all-over protection with the Speck CandyShell Grip + Faceplate. We paired our best-selling CandyShell Grip case with our new Faceplate, which provides 2x shatter protection and features TrueTap technology that bonds to the screen of your iPhone 6s Plus & 6 Plus for a superior touch response. So for sleek style and military-grade protection in one durable iPhone 6s Plus & 6 Plus case, get CandyShell Grip + Faceplate from Speck. Backed by a one-year warranty.\n\n\nKey Specifications:\n- **Other features**: Number of products included: 1 pc(s); Carrying style: Pocket (carrying), Bag, Hand (carrying)\n- **Features**: Maximum screen size: 14 cm (5.5\"); Case type: Cover; Material: Polycarbonate; Product colour: Pink; Brand compatibility: Apple; Compatibility: iPhone 6s Plus; Protection features: Scratch resistant, Dust resistant, Shock resistant; Certification: MIL-STD-810G", "image_url": "https://images.icecat.biz/img/gallery_mediums/29796907_6868.jpg", "price": 17.91, "currency": "EUR", "categories": ["Mobile Phone Cases"], "attrs": {"Maximum screen size": "14 cm (5.5\")", "Case type": "Cover", "Material": "Polycarbonate", "Product colour": "Pink", "Brand compatibility": "Apple", "Compatibility": "iPhone 6s Plus", "Protection features": "Scratch resistant, Dust resistant, Shock resistant", "Certification": "MIL-STD-810G", "Number of products included": "1 pc(s)", "Carrying style": "Pocket (carrying), Bag, Hand (carrying)"}, "attr_keys": ["Brand compatibility", "Carrying style", "Case type", "Certification", "Compatibility", "Material", "Maximum screen size", "Number of products included", "Product colour", "Protection features"]}
{"id": "18314292", "title": "Targus Snap-On mobile phone case Cover Black", "brand": "Targus", "description": "Targus Snap-On mobile phone case Cover Black\n\n\nThe distinctive feel of the Targus Snap-On Case adds a little flair to your Galaxy S4. Made with the Samsung Galaxy S4 in mind, the Snap-On Shell is designed to fully protect your device without adding bulk. Added protection The Snap-On Shell combines durable hard shell protection with a soft, textured finish inside and out. Design The case is designed to easily snap your phone in and out without any hassle. The slim design provides a sleek profile. Easy access Precision-cut design for easy access to all buttons and ports and does not obstruct the camera lens. Compatibility Designed for the Samsung Galaxy S4 Functionality Slim, sleek profile; Easy snap on design; Soft textured finish inside and out\n\n\nKey Specifications:\n- **Features**: Case type: Cover; Material: Polycarbonate; Product colour: Black; Brand compatibility: Samsung; Compatibility: Galaxy S4", "image_url": "https://images.icecat.biz/img/norm/medium/18314292-747.jpg", "price": 20.05, "currency": "EUR", "categories": ["Mobile Phone Cases"], "attrs": {"Case type": "Cover", "Material": "Polycarbonate", "Product colour": "Black", "Brand compatibility": "Samsung", "Compatibility": "Galaxy S4"}, "attr_keys": ["Brand compatibility", "Case type", "Compatibility", "Material", "Product colour"]}
{"id": "17381383", "title": "Contour Design On The Dot mobile phone case Cover Red", "brand": "Contour Design", "description": "Contour Design On The Dot mobile phone case Cover Red\n\n\nOn the dot iphone 4 & 4s red\n\n\nKey Specifications:\n- **Features**: Case type: Cover; Product colour: Red; Brand compatibility: Apple; Compatibility: iPhone 4/4s", "image_url": "https://images.icecat.biz/img/gallery_mediums/img_17381383_medium_1482148784_7912_19303.jpg", "price": 25.12, "currency": "EUR", "categories": ["Mobile Phone Cases"], "attrs": {"Case type": "Cover", "Product colour": "Red", "Brand compatibility": "Apple", "Compatibility": "iPhone 4/4s"}, "attr_keys": ["Brand compatibility", "Case type", "Compatibility", "Product colour"]}
{"id": "37251694", "title": "Area CRCBMPA7005 mobile phone case Cover Black, Transparent", "brand": "Area", "description": "Area CRCBMPA7005 mobile phone case Cover Black, Transparent\n\n\nKey Specifications:\n- **Packaging data**: Package width: 100 mm; Package depth: 15 mm; Package height: 175 mm; Package weight: 115 g\n- **Features**: Case type: Cover; Material: Rubber; Product colour: Black, Transparent; Brand compatibility: Apple; Compatibility: iPhone 6 Plus, iPhone 6s Plus; Surface coloration: Monochromatic; Protection features: Bump resistant, Shock resistant", "image_url": "https://images.icecat.biz/img/gallery_mediums/37251694_2941735805.jpg", "price": 22.14, "currency": "EUR", "categories": ["Mobile Phone Cases"], "attrs": {"Case type": "Cover", "Material": "Rubber", "Product colour": "Black, Transparent", "Brand compatibility": "Apple", "Compatibility": "iPhone 6 Plus, iPhone 6s Plus", "Surface coloration": "Monochromatic", "Protection features": "Bump resistant, Shock resistant", "Package width": "100 mm", "Package depth": "15 mm", "Package height": "175 mm", "Package weight": "115 g"}, "attr_keys": ["Brand compatibility", "Case type", "Compatibility", "Material", "Package depth", "Package height", "Package weight", "Package width", "Product colour", "Protection features", "Surface coloration"]}
{"id": "33304032", "title": "Speck Presidio mobile phone case 11.9 cm (4.7\") Cover Transparent", "brand": "Speck", "description": "Speck Presidio mobile phone case 11.9 cm (4.7\") Cover Transparent\n\n\nCompletely clear iPhone 7 case with IMPACTIUMTM CLEAR that resists yellowing. Protection - 8-Foot Drop Tested. To ensure that Presidio CLEAR offers the ultimate protection for your iPhone 7, it has been dropped from a height of 8 feet multiple times by a third-party laboratory. - IMPACTIUMTM CLEAR. IMPACTIUMTM CLEAR is a dynamic shock-absorbing material that absorbs and disperses force away from your iPhone 7. - Patented raised-bezel screen protection. IMPACTIUMTM CLEAR raised bezel guards screen from direct drops onto phone face and prevents damage when lying flat. - Responsive button protection. IMPACTIUMTM CLEAR protects volume and power buttons while maintaining true button responsiveness. - Perimeter port and camera protection. IMPACTIUMTM CLEAR protects ports, microphone, and speakers from drops without compromising acoustics or interfering with port accessibility, camera lenses or the camera flash. Design - Dual-layer design. Presidio CLEAR features a dual-layer construction for robust protection. - Slimmest case yet. We’ve created the slimmest dual-layer case Speck has ever made, without sacrificing protection. - Precision-engineered fit. Presidio CLEAR is precision-engineered to fit your iPhone 7 perfectly. Quality - Scratch-resistant. Presidio CLEAR resists scratches and offers a modern style with clear glossy and matte black designs. - Resists UV Yellowing. Presidio CLEAR’s custom-engineered materials resist turning yellow when exposed to UV light from the sun. - Lab-tested durability. All Speck cases are independently lab tested for multiple real-life situations to ensure your device is always protected. We test to protect against extreme drops, extreme temperatures, chemicals, antenna interference, cracks and abrasions, device bending, and more. - Lifetime warranty. All Presidio cases come with a lifetime limited warranty.\n\n\nKey Specifications:\n- **Packaging content**: Quantity per pack: 1 pc(s)\n- **Features**: Maximum screen size: 11.9 cm (4.7\"); Case type: Cover; Material: Polycarbonate; Product colour: Transparent; Brand compatibility: Apple; Compatibility: iPhone 7; Protection features: Dust resistant, Scratch resistant, Shock resistant", "image_url": "https://images.icecat.biz/img/gallery_mediums/33304032_9292556286.jpg", "price": 21.12, "currency": "EUR", "categories": ["Mobile Phone Cases"], "attrs": {"Maximum screen size": "11.9 cm (4.7\")", "Case type": "Cover", "Material": "Polycarbonate", "Product colour": "Transparent", "Brand compatibility": "Apple", "Compatibility": "iPhone 7", "Protection features": "Dust resistant, Scratch resistant, Shock resistant", "Quantity per pack": "1 pc(s)"}, "attr_keys": ["Brand compatibility", "Case type", "Compatibility", "Material", "Maximum screen size", "Product colour", "Protection features", "Quantity per pack"]}
{"id": "72772646", "title": "Hama Protector mobile phone case 17.3 cm (6.8\") Cover Black, Transparent", "brand": "Hama", "description": "Hama Protector mobile phone case 17.3 cm (6.8\") Cover Black, Transparent\n\n\nYou want to prevent your smartphone's edges from splintering when your mobile device falls on the ground? Then all you need is this \"Protector\" cover brought to you by Hama. It features a special anti-shock guard construction which provides perfect protection to your Galaxy Note 10+. - Anti-shock guard technology: shock-absorbing frame protects the smartphone from knocks and bumps - Water-repellent, transparent back: the design of the smartphone remains visible - Raised, bevelled TPU frame for protection of the display - Elastic button for optimal button protection and ease of use\n\n\nKey Specifications:\n- **Packaging content**: Quantity per pack: 1 pc(s)\n- **Features**: Maximum screen size: 17.3 cm (6.8\"); Case type: Cover; Material: Thermoplastic polyurethane (TPU); Product colour: Black, Transparent; Brand compatibility: Samsung; Compatibility: Galaxy Note 10+; Surface coloration: Monochromatic; Closure type: Not applicable; Protection features: Bump resistant, Scratch resistant, Shock resistant, Water resistant", "image_url": "https://images.icecat.biz/img/gallery_mediums/72772646_6611874081.jpg", "price": 11.8, "currency": "EUR", "categories": ["Mobile Phone Cases"], "attrs": {"Maximum screen size": "17.3 cm (6.8\")", "Case type": "Cover", "Material": "Thermoplastic polyurethane (TPU)", "Product colour": "Black, Transparent", "Brand compatibility": "Samsung", "Compatibility": "Galaxy Note 10+", "Surface coloration": "Monochromatic", "Closure type": "Not applicable", "Protection features": "Bump resistant, Scratch resistant, Shock resistant, Water resistant", "Quantity per pack": "1 pc(s)"}, "attr_keys": ["Brand compatibility", "Case type", "Closure type", "Compatibility", "Material", "Maximum screen size", "Product colour", "Protection features", "Quantity per pack", "Surface coloration"]}
{"id": "3787503", "title": "Hama 00095944 mobile phone case Black, Grey", "brand": "Hama", "description": "Hama 00095944 mobile phone case Black, Grey\n\n\n- Universal case for one web´n´walk stick - With snap hook and hook and loop fastener - Material: nylon - Dimensions: W: 2.5 x D: 8.0 x H: 1.5 cm - Model: Web´n Walk Stick - Colour: Black - Material: Nylon - Inside Dimension Width: 2,5 cm - Inside Dimension Height: 1,5 cm - Inside Dimension Depth: 8,0 cm\n\n\nKey Specifications:\n- **Weight & dimensions**: Interior dimensions (W x D x H): 25 x 80 x 15 mm\n- **Features**: Material: Nylon; Product colour: Black, Grey", "image_url": "https://images.icecat.biz/img/gallery_mediums/img_3787503_medium_1481126825_1586_23531.jpg", "price": 18.45, "currency": "EUR", "categories": ["Mobile Phone Cases"], "attrs": {"Material": "Nylon", "Product colour": "Black, Grey", "Interior dimensions (W x D x H)": "25 x 80 x 15 mm"}, "attr_keys": ["Interior dimensions (W x D x H)", "Material", "Product colour"]}
{"id": "15974615", "title": "Targus Wallet Case mobile phone case Cover Black", "brand": "Targus", "description": "Targus Wallet Case mobile phone case Cover Black\n\n\nThe Targus Wallet Case features a functional yet elegant storage for an ID and credit cards as well as protection for your iPhone. Convenient and ideal for those who want to travel light. - Hidden, Secure Storage - Wallet case has space for a credit card and ID in a secure compartment on the back of the phone - Easy Clean - Faux leather exterior material is at once durable, easy to clean, and elegant - Patent-pending design - Innovative design offers a compact solution to carrying an iPhone and a wallet - Functionality - High functionality; Low-profile wallet case; Offers storage for an ID and credit cards; Hand-crafted quality with heat sealing around card slots for added strength; Stain-resistant leatherette exterior - Material - Durable faux leather exterior and poly carbonate iPhone tray is easy to clean.\n\n\nKey Specifications:\n- **Weight & dimensions**: Width: 88.9 mm; Depth: 210 mm; Height: 19.1 mm; Weight: 96.4 g\n- **Features**: Case type: Cover; Material: Leatherette, Polycarbonate; Product colour: Black; Brand compatibility: Apple; Compatibility: iPhone 5", "image_url": "https://images.icecat.biz/img/norm/medium/15974615-6019.jpg", "price": 19.72, "currency": "EUR", "categories": ["Mobile Phone Cases"], "attrs": {"Case type": "Cover", "Material": "Leatherette, Polycarbonate", "Product colour": "Black", "Brand compatibility": "Apple", "Compatibility": "iPhone 5", "Width": "88.9 mm", "Depth": "210 mm", "Height": "19.1 mm", "Weight": "96.4 g"}, "attr_keys": ["Brand compatibility", "Case type", "Compatibility", "Depth", "Height", "Material", "Product colour", "Weight", "Width"]}
