{"id": "31627125", "title": "LG K580 13.2 cm (5.2\") Single SIM Android 6.0 4G Micro-USB 2 GB 16 GB 2520 mAh Metallic", "brand": "LG", "description": "LG K580 13.2 cm (5.2\") Single SIM Android 6.0 4G Micro-USB 2 GB 16 GB 2520 mAh Metallic\n\n\nPrecision 3D Arc Glass Design Bended glass, bold and beautiful. A slim tapered top and bottom bended glass finish in a double wedge design. With a slimness of 6.9mm, it easily slides into your pocket, jacket, or handbag, but feels solid in your hand. Dual Camera with 120º Wide Angle Wider scope, and vivid detail. Capture photos that spread as wide as what your eyes can see, at an impressive 120° wide angle. The dual rear camera shoots 78° regular angle photos at an astounding 13MP resolution. Get it wide, get it in detail. Pop-out Picture Magical moving moments. Tickle yourself with memorable scenes that go forward, backward, loop, and repeat. Spice up your photos and videos with 6 photographical frames and 4 stunning effects (Fisheye, B&W, Vignette, Lens Blur). Images and movies stand out and pop out above all the rest. Tall and Wide Panorama Side to side, up and down. The heightened fullness of dual camera panorama spans not only 120° wide, but also stretches up and down for a view that reveals a whole new realm. 5.2” Full HD Display Treat your eyes to sharpness and clarity. The expansive 5.2” Full HD display gives your eyes so much more to take in. More resolution, detail, colour, and crystal clarity. While watching movies, sports, or playing games, take it all in. 1.14GHz Octa-Core Processor Sheer Octa-core speed and efficiency. The 1.14GHz Octa-core processor equips you with power to multitask, while preserving more battery life. Your phone can do more, faster, and for longer. 2,520mAh Embedded Battery Enjoy the hassle-free convenience of ample power with the 2,520mAh embedded battery. Android Marshmallow Built to get the best out of the world's most popular platform, the LG X cam is the ultimate Android experience.\n\n\nKey Specifications:\n- **Packaging content**: Cables included: USB\n- **Battery**: Battery capacity: 2520 mAh; Battery technology: Lithium-Ion (Li-Ion)\n- **Software**: Platform: Android; Operating system installed: Android 6.0; App distribution platform: Google Play\n- **Keyboard**: Keyboard layout: QWERTZ\n- **Multimedia**: Audio formats supported: AAC, AAC+, AMR-NB, AMR-WB, FLAC, MIDI, MP2, MP3, OGG, WAV, WMA; Video formats supported: H.263, H.264, MPEG4\n- **Performance**: Themes: Wallpapers\n- **Design**: Form factor: Bar; Product colour: Metallic\n- **Ports & interfaces**: USB connector type: Micro-USB; HDMI ports quantity: 0; Headphone connectivity: 3.5 mm\n- **Network**: SIM card capability: Single SIM; Mobile network generation: 4G; SIM card type: NanoSIM; 3G standards: HSDPA, HSUPA, UMTS; 4G standard: LTE; 2G standards: GSM; Wi-Fi standards: 802.11b, 802.11g, Wi-Fi 4 (802.11n); Bluetooth version: 4.2; Bluetooth profiles: A2DP, AVRCP, HFP, HID, HSP, MAP, OPP, PAN, PBA, PBAP, SPP; 2G bands (primary SIM): 900,1800,1900 MHz; 3G bands supported: 850,900,1900,2100 MHz; 4G bands supported: 800,1800,2600 MHz\n- **Camera**: Rear camera type: Dual camera; Rear camera resolution (numeric): 13 MP; Front camera type: Single camera; Front camera resolution (numeric): 8 MP; Rear camera resolution: 4160 x 3120 pixels; Digital zoom: 8x; Flash type: LED; Video capture resolution (max): 1920 x 1080 pixels; Maximum frame rate: 30 fps; Resolution at capture speed: 1920x1080@30fps; Video recording modes: 1080p\n- **Storage**: RAM capacity: 2 GB; Internal storage capacity: 16 GB; Compatible memory cards: MicroSD (TransFlash); Maximum memory card size: 2 TB\n- **Processor**: Processor family: MediaTek; Processor model: MT6753; Processor frequency: 1.14 GHz; Processor cores: 8\n- **Display**: Display diagonal: 13.2 cm (5.2\"); Display resolution: 1920 x 1080 pixels; Panel type: IPS; Display number of colours: 16.78 million colours; Pixel density: 423 ppi", "image_url": "https://images.icecat.biz/img/gallery_mediums/31627125_6073.jpg", "price": 693.6, "currency": "EUR", "categories": ["Smartphones"], "attrs": {"Display diagonal": "13.2 cm (5.2\")", "Display resolution": "1920 x 1080 pixels", "Panel type": "IPS", "Display number of colours": "16.78 million colours", "Pixel density": "423 ppi", "Processor family": "MediaTek", "Processor model": "MT6753", "Processor frequency": "1.14 GHz", "Processor cores": "8", "RAM capacity": "2 GB", "Internal storage capacity": "16 GB", "Compatible memory cards": "MicroSD (TransFlash)", "Maximum memory card size": "2 TB", "Rear camera type": "Dual camera", "Rear camera resolution (numeric)": "13 MP", "Front camera type": "Single camera", "Front camera resolution (numeric)": "8 MP", "Rear camera resolution": "4160 x 3120 pixels", "Digital zoom": "8x", "Flash type": "LED", "Video capture resolution (max)": "1920 x 1080 pixels", "Maximum frame rate": "30 fps", "Resolution at capture speed": "1920x1080@30fps", "Video recording modes": "1080p", "SIM card capability": "Single SIM", "Mobile network generation": "4G", "SIM card type": "NanoSIM", "3G standards": "HSDPA, HSUPA, UMTS", "4G standard": "LTE", "2G standards": "GSM", "Wi-Fi standards": "802.11b, 802.11g, Wi-Fi 4 (802.11n)", "Bluetooth version": "4.2", "Bluetooth profiles": "A2DP, AVRCP, HFP, HID, HSP, MAP, OPP, PAN, PBA, PBAP, SPP", "2G bands (primary SIM)": "900,1800,1900 MHz", "3G bands supported": "850,900,1900,2100 MHz", "4G bands supported": "800,1800,2600 MHz", "USB connector type": "Micro-USB", "HDMI ports quantity": "0", "Headphone connectivity": "3.5 mm", "Form factor": "Bar", "Product colour": "Metallic", "Themes": "Wallpapers", "Audio formats supported": "AAC, AAC+, AMR-NB, AMR-WB, FLAC, MIDI, MP2, MP3, OGG, WAV, WMA", "Video formats supported": "H.263, H.264, MPEG4", "Keyboard layout": "QWERTZ", "Platform": "Android", "Operating system installed": "Android 6.0", "App distribution platform": "Google Play", "Battery capacity": "2520 mAh", "Battery technology": "Lithium-Ion (Li-Ion)", "Cables included": "USB"}, "attr_keys": ["2G bands (primary SIM)", "2G standards", "3G bands supported", "3G standards", "4G bands supported", "4G standard", "App distribution platform", "Audio formats supported", "Battery capacity", "Battery technology", "Bluetooth profiles", "Bluetooth version", "Cables included", "Compatible memory cards", "Digital zoom", "Display diagonal", "Display number of colours", "Display resolution", "Flash type", "Form factor", "Front camera resolution (numeric)", "Front camera type", "HDMI ports quantity", "Headphone connectivity", "Internal storage capacity", "Keyboard layout", "Maximum frame rate", "Maximum memory card size", "Mobile network generation", "Operating system installed", "Panel type", "Pixel density", "Platform", "Processor cores", "Processor family", "Processor frequency", "Processor model", "Product colour", "RAM capacity", "Rear camera resolution", "Rear camera resolution (numeric)", "Rear camera type", "Resolution at capture speed", "SIM card capability", "SIM card type", "Themes", "USB connector type", "Video capture resolution (max)", "Video formats supported", "Video recording modes", "Wi-Fi standards"]}
{"id": "20965706", "title": "LG Optimus L9 P760 11.9 cm (4.7\") Single SIM Android 4.0.4 3G Micro-USB 1 GB 4 GB 2150 mAh Black", "brand": "LG", "description": "LG Optimus L9 P760 11.9 cm (4.7\") Single SIM Android 4.0.4 3G Micro-USB 1 GB 4 GB 2150 mAh Black\n\n\nThe size XL L-Style Optimus L9 has the largest display of the family L-Style. Diagonal of 4.7 \"- the widest in its class - qHD resolution (960x540 pixels) and IPS technology, a guarantee of color fidelity and image quality. Processor \"Tri-Dual\" Optimum performance and extremely fuida Android experience are the hallmarks of Optimus L9 and its Dual Core Processor Dual Channel. Thanks to the kind of Tri-Dual, the flow of information between the two processors and memory is optimized, eliminating the possible \"bottlenecks\" of the traditional dual-core architecture. LG Quick Translator The Quick Translator is the new application from LG can translate in real time any captured text in the preview of the camera. Just frame a text written in a foreign language and will display the Quick Translator translation on the display, simplifying your life when you're on the go. The Quick Translator can be used with or without internet connection. - With Internet connection you can use more than 40 dictionaries using the Google Translate engine. - Without an Internet connection, you can download a free dictionary to translate single words. You can download dictionaries for a fee. Quick Memo You need to take a note on the fly? Just press the volume keys to activate Quick Memo ™ and Optimus L9 will turn into a notepad. You can draw on any screen you are viewing, select the pen color or use a highlighter. With one click you can share your notes on Facebook or send it via e-mail. High capacity battery Optimus L9 has a 2150mAh battery which ensures high autonomy even in the face of heavy use. Thanks to the higher energy density, the technology of SiO + LG allows to realize batteries with very high capacity and reduced dimensions: in fact, the thickness of Optimus L9 is only 8.9mm! Virtual Keypad With Optimus L9 write E-mail is even more comfortable, thanks to the keyboard on the size adaptable. Swiping your finger on the keyboard to the right or to the left you can \"shrink\" the keys to type comfortably with one hand. If you hold the smartphone in horizontal and you have trouble getting the central keys, simply spread your fingers to \"break\" the keyboard into two parts. Photo and Video Quality With the power of Optimus L9 you can record videos in FullHD or apply effects in real time to faces: big mouth, small eyes, and so on (max resolution. VGA). In addition, thanks to the snap to \"Cheese\" you can take pictures by simply saying \"cheese.\" Finally, there are the flash, autofocus and the ability to take panoramic pictures. Full Connectivity DLNA, NFC, Wi-Fi Direct and 21.1Mbps HSPA: Optimus L9 has it all in terms of connectivity. The Smart Share allows you to share videos, photos and PowerPoint presentations on TV without the use of wires while while NFC technology can be used to transfer contact lists and websites, or for the configuration with a gesture of thanks to NFC Tag (sold separately).\n\n\nKey Specifications:\n- **Packaging content**: Cables included: USB\n- **Certificates**: Head SAR (EU): 0.388 W/kg\n- **Weight & dimensions**: Weight: 125 g; Width: 68.2 mm; Depth: 9.1 mm; Height: 131.9 mm\n- **Battery**: Battery capacity: 2150 mAh; Talk time (3G): 11.5 h; Standby time (3G): 628 h; Battery technology: Lithium-Ion (Li-Ion); Talk time (2G): 16.5 h; Standby time (2G): 791 h\n- **Software**: Platform: Android; Operating system installed: Android 4.0.4; App distribution platform: Google Play\n- **Multimedia**: Audio formats supported: AAC, AAC+, AC3, HE-AAC, LC-AAC, MP2, MP3, PCM, WMA; Video formats supported: DIVX, H.263, H.264, MPEG4, VC-1, VP6, VP8, WMV; Image formats supported: GIF, JPG\n- **Performance**: Graphics card: PowerVR SGX544; Personal info management (PIM): Alarm clock, Calculator, Calendar, Converter, Countdown timer, Detailed contact information, Events reminder, Games, Notes, Recorder, Stopwatch, To-do list\n- **Design**: Form factor: Bar; Product colour: Black\n- **Messaging**: Text prediction system type: T9\n- **Ports & interfaces**: USB connector type: Micro-USB; USB version: 2.0; HDMI ports quantity: 0; Headphone connectivity: 3.5 mm\n- **Subscription**: Subscription type: No subscription\n- **Network**: SIM card capability: Single SIM; Mobile network generation: 3G; 3G standards: HSDPA, HSPA+, UMTS; 2G standards: Edge, GPRS, GSM; Wi-Fi standards: 802.11b, 802.11g, Wi-Fi 4 (802.11n); Bluetooth version: 3.0+HS; 2G bands (primary SIM): 850,900,1800,1900 MHz; 3G bands supported: 850,900,1900,2100 MHz; GPRS multislot class: 33; EDGE multislot class: 33\n- **Camera**: Rear camera type: Single camera; Rear camera resolution (numeric): 5 MP; Front camera type: Single camera; Front camera resolution (numeric): 1.3 MP; Digital zoom: 4x; Flash type: LED; Video capture resolution (max): 1920 x 1080 pixels; Video recording modes: 1080p\n- **Storage**: RAM capacity: 1 GB; Internal storage capacity: 4 GB; Compatible memory cards: MicroSD (TransFlash); Maximum memory card size: 32 GB\n- **Processor**: Processor family: STE; Processor model: OMAP4430; Processor frequency: 1 GHz; Processor architecture: ARM Cortex-A9; Processor cores: 2\n- **Display**: Display diagonal: 11.9 cm (4.7\"); Display resolution: 960 x 540 pixels; Panel type: IPS; Display number of colours: 16.78 million colours; Touch technology: Multi-touch; Touchscreen type: Capacitive", "image_url": "https://images.icecat.biz/img/gallery/18059853_4885.jpg", "price": 573.36, "currency": "EUR", "categories": ["Smartphones"], "attrs": {"Display diagonal": "11.9 cm (4.7\")", "Display resolution": "960 x 540 pixels", "Panel type": "IPS", "Display number of colours": "16.78 million colours", "Touch technology": "Multi-touch", "Touchscreen type": "Capacitive", "Processor family": "STE", "Processor model": "OMAP4430", "Processor frequency": "1 GHz", "Processor architecture": "ARM Cortex-A9", "Processor cores": "2", "RAM capacity": "1 GB", "Internal storage capacity": "4 GB", "Compatible memory cards": "MicroSD (TransFlash)", "Maximum memory card size": "32 GB", "Rear camera type": "Single camera", "Rear camera resolution (numeric)": "5 MP", "Front camera type": "Single camera", "Front camera resolution (numeric)": "1.3 MP", "Digital zoom": "4x", "Flash type": "LED", "Video capture resolution (max)": "1920 x 1080 pixels", "Video recording modes": "1080p", "SIM card capability": "Single SIM", "Mobile network generation": "3G", "3G standards": "HSDPA, HSPA+, UMTS", "2G standards": "Edge, GPRS, GSM", "Wi-Fi standards": "802.11b, 802.11g, Wi-Fi 4 (802.11n)", "Bluetooth version": "3.0+HS", "2G bands (primary SIM)": "850,900,1800,1900 MHz", "3G bands supported": "850,900,1900,2100 MHz", "GPRS multislot class": "33", "EDGE multislot class": "33", "Subscription type": "No subscription", "USB connector type": "Micro-USB", "USB version": "2.0", "HDMI ports quantity": "0", "Headphone connectivity": "3.5 mm", "Text prediction system type": "T9", "Form factor": "Bar", "Product colour": "Black", "Graphics card": "PowerVR SGX544", "Personal info management (PIM)": "Alarm clock, Calculator, Calendar, Converter, Countdown timer, Detailed contact information, Events reminder, Games, Notes, Recorder, Stopwatch, To-do list", "Audio formats supported": "AAC, AAC+, AC3, HE-AAC, LC-AAC, MP2, MP3, PCM, WMA", "Video formats supported": "DIVX, H.263, H.264, MPEG4, VC-1, VP6, VP8, WMV", "Image formats supported": "GIF, JPG", "Platform": "Android", "Operating system installed": "Android 4.0.4", "App distribution platform": "Google Play", "Battery capacity": "2150 mAh", "Talk time (3G)": "11.5 h", "Standby time (3G)": "628 h", "Battery technology": "Lithium-Ion (Li-Ion)", "Talk time (2G)": "16.5 h", "Standby time (2G)": "791 h", "Weight": "125 g", "Width": "68.2 mm", "Depth": "9.1 mm", "Height": "131.9 mm", "Head SAR (EU)": "0.388 W/kg", "Cables included": "USB"}, "attr_keys": ["2G bands (primary SIM)", "2G standards", "3G bands supported", "3G standards", "App distribution platform", "Audio formats supported", "Battery capacity", "Battery technology", "Bluetooth version", "Cables included", "Compatible memory cards", "Depth", "Digital zoom", "Display diagonal", "Display number of colours", "Display resolution", "EDGE multislot class", "Flash type", "Form factor", "Front camera resolution (numeric)", "Front camera type", "GPRS multislot class", "Graphics card", "HDMI ports quantity", "Head SAR (EU)", "Headphone connectivity", "Height", "Image formats supported", "Internal storage capacity", "Maximum memory card size", "Mobile network generation", "Operating system installed", "Panel type", "Personal info management (PIM)", "Platform", "Processor architecture", "Processor cores", "Processor family", "Processor frequency", "Processor model", "Product colour", "RAM capacity", "Rear camera resolution (numeric)", "Rear camera type", "SIM card capability", "Standby time (2G)", "Standby time (3G)", "Subscription type", "Talk time (2G)", "Talk time (3G)", "Text prediction system type", "Touch technology", "Touchscreen type", "USB connector type", "USB version", "Video capture resolution (max)", "Video formats supported", "Video recording modes", "Weight", "Wi-Fi standards", "Width"]}
{"id": "33100474", "title": "Samsung Galaxy J3 (2016) SM-J320F 12.7 cm (5\") Single SIM 4G Micro-USB 1.5 GB 8 GB 2600 mAh White", "brand": "mcare", "description": "Samsung Galaxy J3 (2016) SM-J320F 12.7 cm (5\") Single SIM 4G Micro-USB 1.5 GB 8 GB 2600 mAh White\n\n\nKey Specifications:\n- **Certificates**: Head SAR (EU): 0.477 W/kg; Body SAR (EU): 1.27 W/kg\n- **Weight & dimensions**: Weight: 138 g; Width: 71 mm; Depth: 7.9 mm; Height: 142.3 mm\n- **Battery**: Battery capacity: 2600 mAh; Talk time (3G): 13 h; Browsing time (Wi-Fi): 11 h; Browsing time (3G): 9 h; Browsing time (4G): 9 h; Continuous audio playback time: 53 h; Continuous video playback time: 11 h\n- **Software**: Platform: Android; App distribution platform: Google Play; Google applications: Gmail, Google Maps, Google Play\n- **Multimedia**: Audio formats supported: 3GA, AAC, AMR, AWB, FLAC, IMY, M4A, Mid, MIDI, MP3, MXMF, OGA, OGG, OTA, RTTTL, RTX, WAV, WMA, XMF; Video formats supported: 3G2, 3GP, ASF, AVI, FLV, M4V, MKV, MP4, WEBM, WMV\n- **Performance**: Personal info management (PIM): Alarm clock, Calculator, Calendar, Notes\n- **Design**: Form factor: Bar; Product colour: White\n- **Ports & interfaces**: USB connector type: Micro-USB; USB version: 2.0; HDMI ports quantity: 0; Headphone connectivity: 3.5 mm\n- **Subscription**: Subscription type: No subscription\n- **Network**: SIM card capability: Single SIM; Mobile network generation: 4G; SIM card type: MicroSIM; 3G standards: UMTS, WCDMA; 4G standard: LTE; 2G standards: GSM; Wi-Fi standards: 802.11b, 802.11g, Wi-Fi 4 (802.11n); Bluetooth version: 4.0; Bluetooth profiles: A2DP, AVRCP, HFP, HID, HOGP, MAP, OPP, PAN, PBAP, SAP; 2G bands (primary SIM): 850,900,1800,1900 MHz; 3G bands supported: 850,900,1900,2100 MHz; 4G bands supported: 800,850,900,1800,2100,2600 MHz\n- **Camera**: Rear camera type: Single camera; Rear camera resolution (numeric): 8 MP; Front camera type: Single camera; Front camera resolution (numeric): 5 MP; Rear camera resolution: 1280 x 720 pixels; Sensor type: CMOS; Maximum frame rate: 30 fps; Video recording modes: 720p\n- **Storage**: RAM capacity: 1.5 GB; Internal storage capacity: 8 GB; Compatible memory cards: MicroSD (TransFlash); Maximum memory card size: 128 GB\n- **Processor**: Processor frequency: 1.5 GHz; Processor cores: 4\n- **Display**: Display diagonal: 12.7 cm (5\"); Display resolution: 1280 x 720 pixels; Screen shape: Flat; Display technology marketing name: Super AMOLED; Panel type: OLED; Display number of colours: 16.78 million colours; Touch technology: Multi-touch", "image_url": "https://images.icecat.biz/img/gallery_mediums/33100474_4690871197.jpg", "price": 763.08, "currency": "EUR", "categories": ["Smartphones"], "attrs": {"Display diagonal": "12.7 cm (5\")", "Display resolution": "1280 x 720 pixels", "Screen shape": "Flat", "Display technology marketing name": "Super AMOLED", "Panel type": "OLED", "Display number of colours": "16.78 million colours", "Touch technology": "Multi-touch", "Processor frequency": "1.5 GHz", "Processor cores": "4", "RAM capacity": "1.5 GB", "Internal storage capacity": "8 GB", "Compatible memory cards": "MicroSD (TransFlash)", "Maximum memory card size": "128 GB", "Rear camera type": "Single camera", "Rear camera resolution (numeric)": "8 MP", "Front camera type": "Single camera", "Front camera resolution (numeric)": "5 MP", "Rear camera resolution": "1280 x 720 pixels", "Sensor type": "CMOS", "Maximum frame rate": "30 fps", "Video recording modes": "720p", "SIM card capability": "Single SIM", "Mobile network generation": "4G", "SIM card type": "MicroSIM", "3G standards": "UMTS, WCDMA", "4G standard": "LTE", "2G standards": "GSM", "Wi-Fi standards": "802.11b, 802.11g, Wi-Fi 4 (802.11n)", "Bluetooth version": "4.0", "Bluetooth profiles": "A2DP, AVRCP, HFP, HID, HOGP, MAP, OPP, PAN, PBAP, SAP", "2G bands (primary SIM)": "850,900,1800,1900 MHz", "3G bands supported": "850,900,1900,2100 MHz", "4G bands supported": "800,850,900,1800,2100,2600 MHz", "Subscription type": "No subscription", "USB connector type": "Micro-USB", "USB version": "2.0", "HDMI ports quantity": "0", "Headphone connectivity": "3.5 mm", "Form factor": "Bar", "Product colour": "White", "Personal info management (PIM)": "Alarm clock, Calculator, Calendar, Notes", "Audio formats supported": "3GA, AAC, AMR, AWB, FLAC, IMY, M4A, Mid, MIDI, MP3, MXMF, OGA, OGG, OTA, RTTTL, RTX, WAV, WMA, XMF", "Video formats supported": "3G2, 3GP, ASF, AVI, FLV, M4V, MKV, MP4, WEBM, WMV", "Platform": "Android", "App distribution platform": "Google Play", "Google applications": "Gmail, Google Maps, Google Play", "Battery capacity": "2600 mAh", "Talk time (3G)": "13 h", "Browsing time (Wi-Fi)": "11 h", "Browsing time (3G)": "9 h", "Browsing time (4G)": "9 h", "Continuous audio playback time": "53 h", "Continuous video playback time": "11 h", "Weight": "138 g", "Width": "71 mm", "Depth": "7.9 mm", "Height": "142.3 mm", "Head SAR (EU)": "0.477 W/kg", "Body SAR (EU)": "1.27 W/kg"}, "attr_keys": ["2G bands (primary SIM)", "2G standards", "3G bands supported", "3G standards", "4G bands supported", "4G standard", "App distribution platform", "Audio formats supported", "Battery capacity", "Bluetooth profiles", "Bluetooth version", "Body SAR (EU)", "Browsing time (3G)", "Browsing time (4G)", "Browsing time (Wi-Fi)", "Compatible memory cards", "Continuous audio playback time", "Continuous video playback time", "Depth", "Display diagonal", "Display number of colours", "Display resolution", "Display technology marketing name", "Form factor", "Front camera resolution (numeric)", "Front camera type", "Google applications", "HDMI ports quantity", "Head SAR (EU)", "Headphone connectivity", "Height", "Internal storage capacity", "Maximum frame rate", "Maximum memory card size", "Mobile network generation", "Panel type", "Personal info management (PIM)", "Platform", "Processor cores", "Processor frequency", "Product colour", "RAM capacity", "Rear camera resolution", "Rear camera resolution (numeric)", "Rear camera type", "SIM card capability", "SIM card type", "Screen shape", "Sensor type", "Subscription type", "Talk time (3G)", "Touch technology", "USB connector type", "USB version", "Video formats supported", "Video recording modes", "Weight", "Wi-Fi standards", "Width"]}
{"id": "125004590", "title": "Samsung Galaxy S25 Ultra 17.5 cm (6.9\") Dual SIM Android 15 5G USB Type-C 12 GB 1 TB 5000 mAh Silver, White", "brand": "Samsung", "description": "Samsung Galaxy S25 Ultra 17.5 cm (6.9\") Dual SIM Android 15 5G USB Type-C 12 GB 1 TB 5000 mAh Silver, White\n\n\nSimple. Impactful Galaxy S25 Ultra's rounded design expresses a unified identity for the Galaxy S series. With its sleek and strong titanium frame and a built-in S Pen, it's an ultra-modern, vision of bold design. Looks sleek, built tough Shielded in a strong titanium frame, reinforced by Corning® Gorilla® Armor 2 display glass and with an IP68 rating for water and dust resistance, take this Galaxy further than you thought possible. Personalised briefings for your day Get personalised briefings throughout the day from the all-new Now Brief. Start your morning with a run-down of the day ahead, such as checking your latest Energy Score and reminders of a busy schedule. Then, recap on the day's events in the evening with daily activity insights. A sound studio at your fingertips Filter out unwanted background noise from your videos and make them share-worthy with Audio Eraser. Galaxy AI fine-tunes your audio by adjusting different types of sound including voices, music, wind and more. The future of health, now made personal Keep up with your health goals by tracking your Energy Score. Sync with Galaxy Watch or Ring and receive personalised insights and coaching such as an analysis of your sleep, activity and heart rate. Personal data stays personal The Personal Data Engine combines and processes your primary data and provides tailored suggestions. It encrypts this data and saves it on your device with Knox Vault, making it inaccessible to anyone else. You can even monitor the security of other Galaxy devices right from your Galaxy smartphone. Unrivaled Nightography video. Less noise, more clarity Now you can shoot in improved 10-bit HDR for a more stunning videography experience. Our advanced AP also delivers more precise noise removal meaning you won't have to worry about grainy night footage again. The sharpest details from Wide to Tele and even Ultra Wide From Ultra Wide shots to our Telephoto camera, photos are clear and vivid at any angle. Our AI enhanced ProVisual Engine then improves colour and details for next-level clarity. The most powerful processor customised for Galaxy Introducing our most powerful processor, customised for Galaxy. With improved real-time ray tracing and Vulkan optimisation, dive deep into the action with ultra-smooth gameplay thanks to Snapdragon® 8 Elite Mobile Platform for Galaxy. Clearer, more vivid viewing by ProScaler ProScaler enhances resolution by using advanced AI-algorithm processing to deliver a viewing experience in high definition without having to adjust the display settings. Unparalleled battery life Our pioneering mDNIe technology has been built into our custom-made AP, and with software optimisation, battery usage time is enhanced so you can enjoy hours of watching videos. All new One UI 7, built for AI Get access to your Now Brief alerts, music and more from the Now Bar. The new home screen is all yours with highly-customisable layouts and new widgets. Live notifications let you monitor on-going activities such as voice recordings on the Now Bar, status bar or at the top of your notification panel.\n\n\nKey Specifications:\n- **Other features**: Repairability index: 8.5\n- **Technical details**: Security update term: 31 January 2032\n- **Certificates**: Head SAR (EU): 1.246 W/kg; Body SAR (EU): 1.42 W/kg\n- **Weight & dimensions**: Weight: 218 g; Width: 77.6 mm; Depth: 8.2 mm; Height: 162.8 mm\n- **Power**: USB Type-C required charging power (min): 10 W; USB Type-C required charging power (max): 45 W\n- **Endurance**: Energy efficiency class: B; Battery endurance per cycle: 2694 min; Battery endurance in cycles: 2000; Repeated free fall reliability class: A; Repairability class: C; International Protection (IP) code: IP68; Energy efficiency scale: A to G\n- **Battery**: Battery capacity: 5000 mAh; Continuous video playback time: 31 h\n- **Software**: Platform: Android; Operating system installed: Android 15; User interface (UI): One UI 7.0\n- **Multimedia**: Speakers: stereo; Audio formats supported: 3GA, AAC, AMR, APE, AWB, DFF, DSF, FLAC, IMY, M4A, Mid, MIDI, MP3, MXMF, OGA, OGG, OTA, RTTTL, RTX, WAV, XMF; Video formats supported: 3G2, 3GP, AVI, FLV, M4V, MKV, MP4, WEBM\n- **Design**: Form factor: Bar; Product colour: Silver, White; Colour name: Titanium Whitesilver\n- **Ports & interfaces**: USB connector type: USB Type-C; USB version: 3.2 Gen 1 (3.1 Gen 1); Headphone connectivity: USB Type-C\n- **Network**: SIM card capability: Dual SIM; Mobile network generation: 5G; SIM card type: NanoSIM + eSIM; 3G standards: WCDMA; 4G standard: LTE-TDD & LTE-FDD; 5G standard: Sub6 SDL, Sub6 TDD; Top Wi-Fi standard: Wi-Fi 7 (802.11be); 2G standards: GSM; Wi-Fi standards: 802.11a, 802.11b, 802.11g, Wi-Fi 4 (802.11n), Wi-Fi 5 (802.11ac), Wi-Fi 6 (802.11ax), Wi-Fi 6E (802.11ax), Wi-Fi 7 (802.11be); Bluetooth version: 5.4; 3G bands supported: 850,900,1900,2100 MHz; 4G bands supported: 700,800,850,900,1500,1800,1900,2100,2300,2500,2600 MHz; 5G bands supported: 700,800,850,900,1500,1800,1900,2100,2300,2500,2600,3500,3700 MHz; 4G data rate (max): 2000 Mbit/s; 5G data rate (max): 4.66 Gbit/s; Modulation: 4096-QAM\n- **Camera**: Rear camera type: Quad camera; Rear camera resolution (numeric): 200 MP; Front camera type: Single camera; Front camera resolution (numeric): 12 MP; Rear camera sensor size: 1/1.3\"; Second rear camera sensor size: 1/2.52\"; Third rear camera sensor size: 1/2.52\"; Second rear camera resolution (numeric): 50 MP; Third rear camera resolution (numeric): 50 MP; Fourth rear camera resolution (numeric): 10 MP; Rear camera aperture number: 1.7; Second rear camera aperture number: 3.4; Third rear camera aperture number: 1.9; Fourth rear camera aperture number: 2.4; Rear camera pixel size: 0.6 µm; Second rear camera pixel size: 0.7 µm; Third rear camera pixel size: 0.7 µm; Fourth rear camera pixel size: 1.12 µm; Rear camera field of view (FOV) angle: 85°; Second rear camera field of view (FOV) angle: 22°; Third rear camera field of view (FOV) angle: 120°; Optical zoom: 5x; Digital zoom: 100x; Front camera sensor size: 1/3.2\"; Front camera aperture number: 2.2; Front camera pixel size: 1.12 µm; Front camera field of view (FOV) angle: 80°; Flash type: LED; Video capture resolution (max): 7680 x 4320 pixels; Maximum frame rate: 30 fps; Resolution at capture speed: 1280x720@30fps, 1920x1080@30fps, 1920x1080@60fps, 3840x2160@30fps, 3840x2160@60fps; Video recording modes: 720p, 1080p, 2160p, 4320p; Image stabilizer type: Optical Image Stabilization (OIS); Slow motion rate: 240fps @FHD, 120fps @FHD, 120fps @UHD; Camera image formats supported: DNG, HEIF, JPEG\n- **Storage**: RAM capacity: 12 GB; Internal storage capacity: 1 TB; Compatible memory cards: Not supported; User memory: 984.5 GB\n- **Processor**: Processor family: Qualcomm Snapdragon; Processor model: 8 Elite; Processor frequency: 3.5 GHz; Processor cores: 8; Processor boost frequency: 4.47 GHz; AI processor family: Qualcomm\n- **Display**: Display diagonal: 17.5 cm (6.9\"); Display resolution: 3120 x 1440 pixels; Screen shape: Flat; Display technology marketing name: Dynamic AMOLED 2X; Panel type: AMOLED; Display number of colours: 16 million colours; Maximum refresh rate: 120 Hz; Display brightness: 1500 cd/m²; Pixel density: 500 ppi; Brand specific technologies: Always-on display", "image_url": "https://images.icecat.biz/img/gallery_mediums/45729b43eb71865c1f4adc6ff829c64e86c450e6.jpg", "price": 567.06, "currency": "EUR", "categories": ["Smartphones"], "attrs": {"Display diagonal": "17.5 cm (6.9\")", "Display resolution": "3120 x 1440 pixels", "Screen shape": "Flat", "Display technology marketing name": "Dynamic AMOLED 2X", "Panel type": "AMOLED", "Display number of colours": "16 million colours", "Maximum refresh rate": "120 Hz", "Display brightness": "1500 cd/m²", "Pixel density": "500 ppi", "Brand specific technologies": "Always-on display", "Processor family": "Qualcomm Snapdragon", "Processor model": "8 Elite", "Processor frequency": "3.5 GHz", "Processor cores": "8", "Processor boost frequency": "4.47 GHz", "AI processor family": "Qualcomm", "RAM capacity": "12 GB", "Internal storage capacity": "1 TB", "Compatible memory cards": "Not supported", "User memory": "984.5 GB", "Rear camera type": "Quad camera", "Rear camera resolution (numeric)": "200 MP", "Front camera type": "Single camera", "Front camera resolution (numeric)": "12 MP", "Rear camera sensor size": "1/1.3\"", "Second rear camera sensor size": "1/2.52\"", "Third rear camera sensor size": "1/2.52\"", "Second rear camera resolution (numeric)": "50 MP", "Third rear camera resolution (numeric)": "50 MP", "Fourth rear camera resolution (numeric)": "10 MP", "Rear camera aperture number": "1.7", "Second rear camera aperture number": "3.4", "Third rear camera aperture number": "1.9", "Fourth rear camera aperture number": "2.4", "Rear camera pixel size": "0.6 µm", "Second rear camera pixel size": "0.7 µm", "Third rear camera pixel size": "0.7 µm", "Fourth rear camera pixel size": "1.12 µm", "Rear camera field of view (FOV) angle": "85°", "Second rear camera field of view (FOV) angle": "22°", "Third rear camera field of view (FOV) angle": "120°", "Optical zoom": "5x", "Digital zoom": "100x", "Front camera sensor size": "1/3.2\"", "Front camera aperture number": "2.2", "Front camera pixel size": "1.12 µm", "Front camera field of view (FOV) angle": "80°", "Flash type": "LED", "Video capture resolution (max)": "7680 x 4320 pixels", "Maximum frame rate": "30 fps", "Resolution at capture speed": "1280x720@30fps, 1920x1080@30fps, 1920x1080@60fps, 3840x2160@30fps, 3840x2160@60fps", "Video recording modes": "720p, 1080p, 2160p, 4320p", "Image stabilizer type": "Optical Image Stabilization (OIS)", "Slow motion rate": "240fps @FHD, 120fps @FHD, 120fps @UHD", "Camera image formats supported": "DNG, HEIF, JPEG", "SIM card capability": "Dual SIM", "Mobile network generation": "5G", "SIM card type": "NanoSIM + eSIM", "3G standards": "WCDMA", "4G standard": "LTE-TDD & LTE-FDD", "5G standard": "Sub6 SDL, Sub6 TDD", "Top Wi-Fi standard": "Wi-Fi 7 (802.11be)", "2G standards": "GSM", "Wi-Fi standards": "802.11a, 802.11b, 802.11g, Wi-Fi 4 (802.11n), Wi-Fi 5 (802.11ac), Wi-Fi 6 (802.11ax), Wi-Fi 6E (802.11ax), Wi-Fi 7 (802.11be)", "Bluetooth version": "5.4", "3G bands supported": "850,900,1900,2100 MHz", "4G bands supported": "700,800,850,900,1500,1800,1900,2100,2300,2500,2600 MHz", "5G bands supported": "700,800,850,900,1500,1800,1900,2100,2300,2500,2600,3500,3700 MHz", "4G data rate (max)": "2000 Mbit/s", "5G data rate (max)": "4.66 Gbit/s", "Modulation": "4096-QAM", "USB connector type": "USB Type-C", "USB version": "3.2 Gen 1 (3.1 Gen 1)", "Headphone connectivity": "USB Type-C", "Form factor": "Bar", "Product colour": "Silver, White", "Colour name": "Titanium Whitesilver", "Speakers": "stereo", "Audio formats supported": "3GA, AAC, AMR, APE, AWB, DFF, DSF, FLAC, IMY, M4A, Mid, MIDI, MP3, MXMF, OGA, OGG, OTA, RTTTL, RTX, WAV, XMF", "Video formats supported": "3G2, 3GP, AVI, FLV, M4V, MKV, MP4, WEBM", "Platform": "Android", "Operating system installed": "Android 15", "User interface (UI)": "One UI 7.0", "Battery capacity": "5000 mAh", "Continuous video playback time": "31 h", "USB Type-C required charging power (min)": "10 W", "USB Type-C required charging power (max)": "45 W", "Energy efficiency class": "B", "Battery endurance per cycle": "2694 min", "Battery endurance in cycles": "2000", "Repeated free fall reliability class": "A", "Repairability class": "C", "International Protection (IP) code": "IP68", "Energy efficiency scale": "A to G", "Weight": "218 g", "Width": "77.6 mm", "Depth": "8.2 mm", "Height": "162.8 mm", "Head SAR (EU)": "1.246 W/kg", "Body SAR (EU)": "1.42 W/kg", "Repairability index": "8.5", "Security update term": "31 January 2032"}, "attr_keys": ["2G standards", "3G bands supported", "3G standards", "4G bands supported", "4G data rate (max)", "4G standard", "5G bands supported", "5G data rate (max)", "5G standard", "AI processor family", "Audio formats supported", "Battery capacity", "Battery endurance in cycles", "Battery endurance per cycle", "Bluetooth version", "Body SAR (EU)", "Brand specific technologies", "Camera image formats supported", "Colour name", "Compatible memory cards", "Continuous video playback time", "Depth", "Digital zoom", "Display brightness", "Display diagonal", "Display number of colours", "Display resolution", "Display technology marketing name", "Energy efficiency class", "Energy efficiency scale", "Flash type", "Form factor", "Fourth rear camera aperture number", "Fourth rear camera pixel size", "Fourth rear camera resolution (numeric)", "Front camera aperture number", "Front camera field of view (FOV) angle", "Front camera pixel size", "Front camera resolution (numeric)", "Front camera sensor size", "Front camera type", "Head SAR (EU)", "Headphone connectivity", "Height", "Image stabilizer type", "Internal storage capacity", "International Protection (IP) code", "Maximum frame rate", "Maximum refresh rate", "Mobile network generation", "Modulation", "Operating system installed", "Optical zoom", "Panel type", "Pixel density", "Platform", "Processor boost frequency", "Processor cores", "Processor family", "Processor frequency", "Processor model", "Product colour", "RAM capacity", "Rear camera aperture number", "Rear camera field of view (FOV) angle", "Rear camera pixel size", "Rear camera resolution (numeric)", "Rear camera sensor size", "Rear camera type", "Repairability class", "Repairability index", "Repeated free fall reliability class", "Resolution at capture speed", "SIM card capability", "SIM card type", "Screen shape", "Second rear camera aperture number", "Second rear camera field of view (FOV) angle", "Second rear camera pixel size", "Second rear camera resolution (numeric)", "Second rear camera sensor size", "Security update term", "Slow motion rate", "Speakers", "Third rear camera aperture number", "Third rear camera field of view (FOV) angle", "Third rear camera pixel size", "Third rear camera resolution (numeric)", "Third rear camera sensor size", "Top Wi-Fi standard", "USB Type-C required charging power (max)", "USB Type-C required charging power (min)", "USB connector type", "USB version", "User interface (UI)", "User memory", "Video capture resolution (max)", "Video formats supported", "Video recording modes", "Weight", "Wi-Fi standards", "Width"]}
{"id": "26082447", "title": "Samsung Galaxy Note 3 Neo SM-N7505 14 cm (5.5\") Single SIM Android 4.3 4G Micro-USB 2 GB 16 GB 3100 mAh White", "brand": "mcare", "description": "Samsung Galaxy Note 3 Neo SM-N7505 14 cm (5.5\") Single SIM Android 4.3 4G Micro-USB 2 GB 16 GB 3100 mAh White\n\n\nExpanding the groundbreaking Galaxy Note experience, Note3 neo tilts the balance towards distinctive design factor and innovative, remarkably easy functionality. Its winning style starts with attractive leather-look design and fun colour option. Sensational S Pen combines striking “air commands” with powerful usability and awesome multitasking. Perfect host device to Galaxy Gear, a smartwatch companion that provides the most integrated Note experience yet. Leather stitch design Galaxy Note3 Neo sports a distinctively sleek, leather-like back cover with top-stitch design that sets it apart -- it’s no ordinary device. Protective and pleasing to the palm, it’s secure to grip or lay on any surface without slippage. Slim, refined form factor contributes to its unique look and feel. Stay with tried and true colours like White or Black, or for the more adventurous, try the Mint colour option to really stand out. Premium Note Experience The new S Pen reinvents and modernizes the classic note-taking experience by providing the ability to accomplish everyday tasks with just one click. The advanced S Pen is designed to be fully functional by creating essential input and control features. It plays an integral role in how users interface with the device, making all daily routines easier. Hover your S Pen anywhere on the screen and by just clicking a button aside S Pen, it gives you a quick access to 5 useful features. The New S Pen can direct a universal menu in Action Memo, Scrapbooker, Screen Write, S Finder and Pen Window via Air Command which can complete a variety of tasks easily by just clicking a button aside. Discover the ultimate performance in your everyday life. Galaxy Gear Compatibility Note3 neo is designed to integrate with innovative Galaxy Gear technology so you get the best of both worlds. Your Note device hosts Galaxy Gear’s apps for interrelated functionality but you can make and receive calls on your smartwatch alone -- leave your Note3 neo untouched! Any SNS, IM or email alerts on Galaxy Gear are synced with host device, opening apps automatically when you pick up your Note3 neo so you can respond without delay. Auto Lock both locks and unlocks your device when Galaxy Gear is at a distance of 1.5 meters to safeguard against unauthorized use of your Note3 neo and its contents.\n\n\nKey Specifications:\n- **Packaging content**: Cables included: USB\n- **Weight & dimensions**: Weight: 162.5 g; Width: 77.4 mm; Depth: 8.6 mm; Height: 148.4 mm\n- **Battery**: Battery capacity: 3100 mAh; Talk time (3G): 18 h; Standby time (3G): 540 h; Battery technology: Lithium-Ion (Li-Ion); Standby time (4G): 490 h; Browsing time (Wi-Fi): 12 h; Browsing time (3G): 10 h; Browsing time (4G): 10 h; Continuous audio playback time: 64 h; Continuous video playback time: 13 h\n- **Software**: Platform: Android; Operating system installed: Android 4.3; App distribution platform: Google Play; Google applications: Google Maps, Google Play, Google Voice Search\n- **Multimedia**: Audio formats supported: AAC, AAC+, eAAC+, FLAC, MP3, WAV, WMA; Video formats supported: H.263, H.264, MPEG4, VC-1, VP9, WMV7, WMV8; Video compression formats: H.263, H.264, MPEG4; Voice codecs: AMR-NB, AMR-WB\n- **Performance**: Personal info management (PIM): Alarm clock, Calculator, Calendar, Events reminder, Notes, To-do list; Personalization: Icons, Menu, Shortcuts; Themes: Wallpapers\n- **Design**: Form factor: Bar; Product colour: White\n- **Ports & interfaces**: USB connector type: Micro-USB; USB version: 2.0; HDMI ports quantity: 0; Headphone connectivity: 3.5 mm\n- **Subscription**: Subscription type: No subscription\n- **Network**: SIM card capability: Single SIM; Mobile network generation: 4G; SIM card type: MicroSIM; 3G standards: HSPA+; 4G standard: LTE; 2G standards: Edge, GPRS, GSM; Wi-Fi standards: 802.11a, Wi-Fi 5 (802.11ac), 802.11b, 802.11g, Wi-Fi 4 (802.11n); Bluetooth version: 4.0; Bluetooth profiles: A2DP, AVRCP, HFP, HID, HSP, OPP, PAN, PBAP, SAP; 2G bands (primary SIM): 850,900,1800,1900 MHz; 3G bands supported: 850,900,1900,2100 MHz; 4G bands supported: 800,850,900,1800,2100 MHz\n- **Camera**: Rear camera type: Single camera; Rear camera resolution (numeric): 8 MP; Front camera type: Single camera; Front camera resolution (numeric): 2 MP; Rear camera resolution: 3264 x 2448 pixels; Flash type: LED; Video capture resolution (max): 1920 x 1080 pixels; Maximum frame rate: 30 fps; Resolution at capture speed: 1920x1080@30fps; Video recording modes: 1080p\n- **Storage**: RAM capacity: 2 GB; Internal storage capacity: 16 GB; Compatible memory cards: MicroSD (TransFlash); Maximum memory card size: 64 GB\n- **Processor**: Processor frequency: 1.7 GHz; Processor architecture: ARM Cortex-A15; Processor cores: 2; Coprocessor frequency: 1.3 GHz; Coprocessor architecture: ARM Cortex-A7; Coprocessor cores: 4\n- **Display**: Display diagonal: 14 cm (5.5\"); Display resolution: 1280 x 720 pixels; Touch technology: Multi-touch; Touchscreen type: Capacitive", "image_url": "https://images.icecat.biz/img/norm/medium/24495830-1659.jpg", "price": 696.84, "currency": "EUR", "categories": ["Smartphones"], "attrs": {"Display diagonal": "14 cm (5.5\")", "Display resolution": "1280 x 720 pixels", "Touch technology": "Multi-touch", "Touchscreen type": "Capacitive", "Processor frequency": "1.7 GHz", "Processor architecture": "ARM Cortex-A15", "Processor cores": "2", "Coprocessor frequency": "1.3 GHz", "Coprocessor architecture": "ARM Cortex-A7", "Coprocessor cores": "4", "RAM capacity": "2 GB", "Internal storage capacity": "16 GB", "Compatible memory cards": "MicroSD (TransFlash)", "Maximum memory card size": "64 GB", "Rear camera type": "Single camera", "Rear camera resolution (numeric)": "8 MP", "Front camera type": "Single camera", "Front camera resolution (numeric)": "2 MP", "Rear camera resolution": "3264 x 2448 pixels", "Flash type": "LED", "Video capture resolution (max)": "1920 x 1080 pixels", "Maximum frame rate": "30 fps", "Resolution at capture speed": "1920x1080@30fps", "Video recording modes": "1080p", "SIM card capability": "Single SIM", "Mobile network generation": "4G", "SIM card type": "MicroSIM", "3G standards": "HSPA+", "4G standard": "LTE", "2G standards": "Edge, GPRS, GSM", "Wi-Fi standards": "802.11a, Wi-Fi 5 (802.11ac), 802.11b, 802.11g, Wi-Fi 4 (802.11n)", "Bluetooth version": "4.0", "Bluetooth profiles": "A2DP, AVRCP, HFP, HID, HSP, OPP, PAN, PBAP, SAP", "2G bands (primary SIM)": "850,900,1800,1900 MHz", "3G bands supported": "850,900,1900,2100 MHz", "4G bands supported": "800,850,900,1800,2100 MHz", "Subscription type": "No subscription", "USB connector type": "Micro-USB", "USB version": "2.0", "HDMI ports quantity": "0", "Headphone connectivity": "3.5 mm", "Form factor": "Bar", "Product colour": "White", "Personal info management (PIM)": "Alarm clock, Calculator, Calendar, Events reminder, Notes, To-do list", "Personalization": "Icons, Menu, Shortcuts", "Themes": "Wallpapers", "Audio formats supported": "AAC, AAC+, eAAC+, FLAC, MP3, WAV, WMA", "Video formats supported": "H.263, H.264, MPEG4, VC-1, VP9, WMV7, WMV8", "Video compression formats": "H.263, H.264, MPEG4", "Voice codecs": "AMR-NB, AMR-WB", "Platform": "Android", "Operating system installed": "Android 4.3", "App distribution platform": "Google Play", "Google applications": "Google Maps, Google Play, Google Voice Search", "Battery capacity": "3100 mAh", "Talk time (3G)": "18 h", "Standby time (3G)": "540 h", "Battery technology": "Lithium-Ion (Li-Ion)", "Standby time (4G)": "490 h", "Browsing time (Wi-Fi)": "12 h", "Browsing time (3G)": "10 h", "Browsing time (4G)": "10 h", "Continuous audio playback time": "64 h", "Continuous video playback time": "13 h", "Weight": "162.5 g", "Width": "77.4 mm", "Depth": "8.6 mm", "Height": "148.4 mm", "Cables included": "USB"}, "attr_keys": ["2G bands (primary SIM)", "2G standards", "3G bands supported", "3G standards", "4G bands supported", "4G standard", "App distribution platform", "Audio formats supported", "Battery capacity", "Battery technology", "Bluetooth profiles", "Bluetooth version", "Browsing time (3G)", "Browsing time (4G)", "Browsing time (Wi-Fi)", "Cables included", "Compatible memory cards", "Continuous audio playback time", "Continuous video playback time", "Coprocessor architecture", "Coprocessor cores", "Coprocessor frequency", "Depth", "Display diagonal", "Display resolution", "Flash type", "Form factor", "Front camera resolution (numeric)", "Front camera type", "Google applications", "HDMI ports quantity", "Headphone connectivity", "Height", "Internal storage capacity", "Maximum frame rate", "Maximum memory card size", "Mobile network generation", "Operating system installed", "Personal info management (PIM)", "Personalization", "Platform", "Processor architecture", "Processor cores", "Processor frequency", "Product colour", "RAM capacity", "Rear camera resolution", "Rear camera resolution (numeric)", "Rear camera type", "Resolution at capture speed", "SIM card capability", "SIM card type", "Standby time (3G)", "Standby time (4G)", "Subscription type", "Talk time (3G)", "Themes", "Touch technology", "Touchscreen type", "USB connector type", "USB version", "Video capture resolution (max)", "Video compression formats", "Video formats supported", "Video recording modes", "Voice codecs", "Weight", "Wi-Fi standards", "Width"]}
{"id": "133618665", "title": "TCL 60 NXTPAPER Ultra 18.3 cm (7.2\") Dual SIM Android 15 5G USB Type-C 12 GB 256 GB 5200 mAh Black", "brand": "TCL", "description": "TCL 60 NXTPAPER Ultra 18.3 cm (7.2\") Dual SIM Android 15 5G USB Type-C 12 GB 256 GB 5200 mAh Black\n\n\nKey Specifications:\n- **Other features**: Repairability index: 2.85\n- **Packaging content**: Cables included: USB Type-C\n- **Certificates**: Compliance certificates: CE, GCF\n- **Weight & dimensions**: Weight: 209 g; Width: 81.2 mm; Depth: 7.57 mm; Height: 174.4 mm\n- **Power**: USB Type-C required charging power (max): 33 W\n- **Endurance**: Energy efficiency class: B; Battery endurance per cycle: 3048 min; Battery endurance in cycles: 1000; Repeated free fall reliability class: B; Repairability class: B; International Protection (IP) code: IP68; Energy efficiency scale: A to G\n- **Battery**: Battery capacity: 5200 mAh; Battery recharge time: 1.5 h\n- **Software**: Platform: Android; Operating system installed: Android 15\n- **Multimedia**: Number of microphones: 2; Speakers: stereo; Audio formats supported: AAC, AMR, AWB, FLAC, HE-AAC, HE-AAC v2, MIDI, MP3, OGG, OPUS, Vorbis, WAV; Video formats supported: AV1, H.263, H.264, H.265, MPEG4, VP8, VP9\n- **Performance**: Graphics card: Mali-G615\n- **Design**: Form factor: Bar; Product colour: Black; Colour name: Dark Chrome; Housing material: Fibreglass, Plastic\n- **Ports & interfaces**: USB connector type: USB Type-C\n- **Network**: SIM card capability: Dual SIM; Mobile network generation: 5G; 3G standards: HSPA+; 4G standard: LTE; 5G standard: Sub6 SA/NSA; Top Wi-Fi standard: Wi-Fi 6E (802.11ax); Wi-Fi standards: 802.11a, 802.11b, 802.11g, Wi-Fi 4 (802.11n), Wi-Fi 5 (802.11ac), Wi-Fi 6 (802.11ax), Wi-Fi 6E (802.11ax); Bluetooth version: 5.3; 3G data rate (max): 42.2 Mbit/s; 4G data rate (max): 1000 Mbit/s; 5G data rate (max): 3.67 Gbit/s\n- **Camera**: Rear camera type: Triple camera; Rear camera resolution (numeric): 50 MP; Front camera type: Single camera; Front camera resolution (numeric): 32 MP; Rear camera sensor size: 1/55\"; Second rear camera sensor size: 1/2.8\"; Third rear camera sensor size: 1/4\"; Second rear camera resolution (numeric): 50 MP; Third rear camera resolution (numeric): 8 MP; Rear camera aperture number: 1.88; Second rear camera aperture number: 2.4; Third rear camera aperture number: 2.2; Rear camera pixel size: 1 µm; Second rear camera pixel size: 0.64 µm; Third rear camera pixel size: 1.12 µm; Rear camera field of view (FOV) angle: 84°; Second rear camera field of view (FOV) angle: 33.84°; Third rear camera field of view (FOV) angle: 112°; Rear camera lens elements: 6-element lens; Second rear camera lens elements: 5-element lens; Third rear camera lens elements: 5-element lens; Front camera lens elements: 5-element lens; Front camera sensor size: 1/3.1\"; Front camera aperture number: 2; Front camera pixel size: 0.7 µm; Front camera field of view (FOV) angle: 75.3°; Video capture resolution (max): 3840 x 2160 pixels; Resolution at capture speed: 1920x1080@30fps, 3840x2160@30fps; Video recording modes: 1080p\n- **Storage**: RAM capacity: 12 GB; Internal storage capacity: 256 GB; Compatible memory cards: Not supported; User memory: 220 GB; Virtual RAM (max): 12 GB\n- **Processor**: Processor family: MediaTek Dimensity; Processor model: 7400; Processor architecture: ARM Cortex-A78+Cortex-A55; Processor cores: 8; Processor boost frequency: 2.6 GHz\n- **Display**: Display diagonal: 18.3 cm (7.2\"); Display resolution: 1080 x 2340 pixels; Screen to body ratio: 94.5%; Display technology marketing name: NXTPAPER; Native aspect ratio: 19.5:9; Contrast ratio (typical): 1500:1; Maximum refresh rate: 120 Hz; Display brightness: 780 cd/m²; Maximum display brightness (Outdoor): 850 cd/m²; Touchscreen type: Capacitive", "image_url": "https://images.icecat.biz/img/gallery_mediums/3f568727ed7fa6a95b138403fc8c3afa8edd8bd7.jpg", "price": 513.96, "currency": "EUR", "categories": ["Smartphones"], "attrs": {"Display diagonal": "18.3 cm (7.2\")", "Display resolution": "1080 x 2340 pixels", "Screen to body ratio": "94.5%", "Display technology marketing name": "NXTPAPER", "Native aspect ratio": "19.5:9", "Contrast ratio (typical)": "1500:1", "Maximum refresh rate": "120 Hz", "Display brightness": "780 cd/m²", "Maximum display brightness (Outdoor)": "850 cd/m²", "Touchscreen type": "Capacitive", "Processor family": "MediaTek Dimensity", "Processor model": "7400", "Processor architecture": "ARM Cortex-A78+Cortex-A55", "Processor cores": "8", "Processor boost frequency": "2.6 GHz", "RAM capacity": "12 GB", "Internal storage capacity": "256 GB", "Compatible memory cards": "Not supported", "User memory": "220 GB", "Virtual RAM (max)": "12 GB", "Rear camera type": "Triple camera", "Rear camera resolution (numeric)": "50 MP", "Front camera type": "Single camera", "Front camera resolution (numeric)": "32 MP", "Rear camera sensor size": "1/55\"", "Second rear camera sensor size": "1/2.8\"", "Third rear camera sensor size": "1/4\"", "Second rear camera resolution (numeric)": "50 MP", "Third rear camera resolution (numeric)": "8 MP", "Rear camera aperture number": "1.88", "Second rear camera aperture number": "2.4", "Third rear camera aperture number": "2.2", "Rear camera pixel size": "1 µm", "Second rear camera pixel size": "0.64 µm", "Third rear camera pixel size": "1.12 µm", "Rear camera field of view (FOV) angle": "84°", "Second rear camera field of view (FOV) angle": "33.84°", "Third rear camera field of view (FOV) angle": "112°", "Rear camera lens elements": "6-element lens", "Second rear camera lens elements": "5-element lens", "Third rear camera lens elements": "5-element lens", "Front camera lens elements": "5-element lens", "Front camera sensor size": "1/3.1\"", "Front camera aperture number": "2", "Front camera pixel size": "0.7 µm", "Front camera field of view (FOV) angle": "75.3°", "Video capture resolution (max)": "3840 x 2160 pixels", "Resolution at capture speed": "1920x1080@30fps, 3840x2160@30fps", "Video recording modes": "1080p", "SIM card capability": "Dual SIM", "Mobile network generation": "5G", "3G standards": "HSPA+", "4G standard": "LTE", "5G standard": "Sub6 SA/NSA", "Top Wi-Fi standard": "Wi-Fi 6E (802.11ax)", "Wi-Fi standards": "802.11a, 802.11b, 802.11g, Wi-Fi 4 (802.11n), Wi-Fi 5 (802.11ac), Wi-Fi 6 (802.11ax), Wi-Fi 6E (802.11ax)", "Bluetooth version": "5.3", "3G data rate (max)": "42.2 Mbit/s", "4G data rate (max)": "1000 Mbit/s", "5G data rate (max)": "3.67 Gbit/s", "USB connector type": "USB Type-C", "Form factor": "Bar", "Product colour": "Black", "Colour name": "Dark Chrome", "Housing material": "Fibreglass, Plastic", "Graphics card": "Mali-G615", "Number of microphones": "2", "Speakers": "stereo", "Audio formats supported": "AAC, AMR, AWB, FLAC, HE-AAC, HE-AAC v2, MIDI, MP3, OGG, OPUS, Vorbis, WAV", "Video formats supported": "AV1, H.263, H.264, H.265, MPEG4, VP8, VP9", "Platform": "Android", "Operating system installed": "Android 15", "Battery capacity": "5200 mAh", "Battery recharge time": "1.5 h", "USB Type-C required charging power (max)": "33 W", "Energy efficiency class": "B", "Battery endurance per cycle": "3048 min", "Battery endurance in cycles": "1000", "Repeated free fall reliability class": "B", "Repairability class": "B", "International Protection (IP) code": "IP68", "Energy efficiency scale": "A to G", "Weight": "209 g", "Width": "81.2 mm", "Depth": "7.57 mm", "Height": "174.4 mm", "Compliance certificates": "CE, GCF", "Cables included": "USB Type-C", "Repairability index": "2.85"}, "attr_keys": ["3G data rate (max)", "3G standards", "4G data rate (max)", "4G standard", "5G data rate (max)", "5G standard", "Audio formats supported", "Battery capacity", "Battery endurance in cycles", "Battery endurance per cycle", "Battery recharge time", "Bluetooth version", "Cables included", "Colour name", "Compatible memory cards", "Compliance certificates", "Contrast ratio (typical)", "Depth", "Display brightness", "Display diagonal", "Display resolution", "Display technology marketing name", "Energy efficiency class", "Energy efficiency scale", "Form factor", "Front camera aperture number", "Front camera field of view (FOV) angle", "Front camera lens elements", "Front camera pixel size", "Front camera resolution (numeric)", "Front camera sensor size", "Front camera type", "Graphics card", "Height", "Housing material", "Internal storage capacity", "International Protection (IP) code", "Maximum display brightness (Outdoor)", "Maximum refresh rate", "Mobile network generation", "Native aspect ratio", "Number of microphones", "Operating system installed", "Platform", "Processor architecture", "Processor boost frequency", "Processor cores", "Processor family", "Processor model", "Product colour", "RAM capacity", "Rear camera aperture number", "Rear camera field of view (FOV) angle", "Rear camera lens elements", "Rear camera pixel size", "Rear camera resolution (numeric)", "Rear camera sensor size", "Rear camera type", "Repairability class", "Repairability index", "Repeated free fall reliability class", "Resolution at capture speed", "SIM card capability", "Screen to body ratio", "Second rear camera aperture number", "Second rear camera field of view (FOV) angle", "Second rear camera lens elements", "Second rear camera pixel size", "Second rear camera resolution (numeric)", "Second rear camera sensor size", "Speakers", "Third rear camera aperture number", "Third rear camera field of view (FOV) angle", "Third rear camera lens elements", "Third rear camera pixel size", "Third rear camera resolution (numeric)", "Third rear camera sensor size", "Top Wi-Fi standard", "Touchscreen type", "USB Type-C required charging power (max)", "USB connector type", "User memory", "Video capture resolution (max)", "Video formats supported", "Video recording modes", "Virtual RAM (max)", "Weight", "Wi-Fi standards", "Width"]}
{"id": "122256451", "title": "Samsung Galaxy Z Fold6", "brand": "Samsung", "description": "Samsung Galaxy Z Fold6\n\n\nGalaxy AI is here Put PC-like power in your pocket, Galaxy Z Fold6. More powerful than ever with its super-slim, productive screen. Now super-charged with Galaxy AI on foldables. THE LIGHTEST THE THINNEST UNFOLD PERFECTION Thinner and lighter with a pocket-worthy silhouette, and an even brighter, awe-inspiring fold-out screen. Galaxy AI is here on Galaxy Foldables CIRCLE TO SEARCH Circle to search on the big screen It's an efficient way to search on a smartphone — just make a circle. Boost your productivity on the massive fold-out screen, with your finger or the S Pen. NOTE ASSIST The easiest way to summarise notes on Samsung foldables Get lecture notes in just a few taps — even as you multitask. Note Assist transcribes recordings and organises them into notes, producing efficient summaries.2 For everything else there's S Pen, ready to work wonders on the sweeping screen. Chat Assist Need to write something in a hurry? Just type a few keywords to achieve full productivity. Browsing Assist Found a website that you need to understand quickly? AI summarises entire websites in a flash. PHOTO ASSIST Effortless editing. Courtesy of Galaxy AI The object-aware engine lets you edit photos to your heart's content. With Photo Assist, just hold your finger down on an object to move, erase or enlarge it; adjust angles or fill backgrounds just as easily. Portrait Studio Let AI ignite your imagination with Portrait Studio. Self portraits instantly turn into incredible works of art. A photograph is applied with the Portrait Studio feature for Photo Assist. AI effects are applied to the portrait, with vibrant colours. Instant Slow-mo Instant Slow-mo lets you focus on key moments by selectively applying slow motion to a video, and sharing or saving the clip. Sketch to Image Draw from scratch or on any photo. Use AI to transform that sketch into an image. The Sketch to Image feature is activated on a Galaxy Z Fold6 screen. S Pen draws on the photo, to make the sketch into a new image with AI. INTERPRETER Your ultimate interpreter experience with dual screens Traveling and need to talk with the locals? Interpreter translates on the spot whether you're expressing yourself, listening to a global conference or to a tour guide. LIVE TRANSLATE Borderless phone calls Translate phone conversations instantly. Perfect for real-time voice translation on various apps, especially when you're making calls that involve two languages. Chat with Gemini to supercharge your ideas Thanks to Samsung’s longstanding partnership with Google, your Galaxy now comes with the Google Gemini app. Chat with Gemini to get help learning in new ways, writing thank you notes, planning events and more. GET FULLY IMMERSED Our most immersive smartphone gaming Fold open a mobile gaming beast with a massive screen made better with the Vision Booster's powerful brightness and clarity even in broad daylight. Powerful gaming with the fastest processor on a Samsung foldable Enjoy silky-smooth gaming with Vulkan, even in AAA games. Then, Snapdragon® 8 Gen 3 for Galaxy renders graphics that are absolutely fire. Game harder. Game longer Our battery ensures all-day enjoyment. It's not just a massive battery, but also leverages a more efficient display. Game on. Turn Pro. ProVisual Engine Meet Fold's most powerful camera system yet. Topped with an upgraded NPU, mind-blowing specs and ProVisual Engine, it'll transform your multimedia experience. Extremely detail-oriented With our high-resolution, 50MP camera, witness every detail come to life with stunning clarity and vibrancy. Crystal-clear zoom. Powered by AI Zoom way, way, way in while keeping noise down and resolution clear with ProVisual Engine. Its sharp analysis of the zoomed-in region enhances your shot dramatically. Zoom Map Use the Zoom Map to get your bearings when you're zoomed in; it'll make navigation a breeze. Brighten things up with Super HDR See it, believe it. Super HDR puts the right emphasis on details to pop and impress, even before you take the picture.\n\n\nKey Specifications:\n- **Other features**: Repairability index: 7.8\n- **Packaging content**: Cables included: USB Type-C\n- **Weight & dimensions**: Weight: 239 g; Width: 132.6 mm; Depth: 5.6 mm; Height: 153.5 mm; Folded width: 6.81 cm; Folded depth: 1.21 cm; Folded height: 15.3 cm\n- **Power**: USB Type-C required charging power (min): 10 W; USB Type-C required charging power (max): 25 W\n- **Endurance**: International Protection (IP) code: IP48\n- **Battery**: Battery capacity: 4400 mAh; Battery recharge time: 1.4 h; Browsing time (Wi-Fi): 18 h; Browsing time (4G): 18 h; Continuous audio playback time: 77 h; Continuous video playback time: 23 h\n- **Software**: Platform: Android; Operating system installed: Android 14; Virtual assistant: Samsung Bixby\n- **Multimedia**: Speakers: stereo; Audio formats supported: MIDI, APE, AAC, AWB, MP3, RTTTL, RTX, WAV, DFF, MXMF, DSF, OGA, OGG, XMF, M4A, OTA, FLAC, AMR, Mid; Video formats supported: 3GP, AVI, FLV, M4V, MKV, MP4, WEBM\n- **Design**: Form factor: Clamshell; Product colour: Silver; Colour name: Silver Shadow; Protection features: Water resistant; Housing material: Aluminium\n- **Ports & interfaces**: USB connector type: USB Type-C; USB version: 3.2 Gen 1 (3.1 Gen 1); Headphone connectivity: USB Type-C\n- **Subscription**: Subscription type: No subscription\n- **Network**: SIM card capability: Dual SIM; Mobile network generation: 5G; SIM card type: NanoSIM + eSIM; 3G standards: UMTS, WCDMA; 4G standard: LTE-TDD & LTE-FDD; 5G standard: Sub6 FDD, Sub6 SDL, Sub6 TDD; Top Wi-Fi standard: Wi-Fi 6E (802.11ax); 2G standards: GSM; Wi-Fi standards: 802.11a, 802.11b, 802.11g, Wi-Fi 4 (802.11n), Wi-Fi 5 (802.11ac), Wi-Fi 6 (802.11ax), Wi-Fi 6E (802.11ax); Bluetooth version: 5.3; 2G bands (primary SIM): 900,1900,850,1800 MHz; Frequency band: Tri-band; 3G bands supported: 900,850,1900,2100 MHz; 4G bands supported: 1500,2100,700,2300,800,1800,850,1900,2500,900,2600 MHz; 5G bands supported: 2300,700,800,1800,2500,850,1900,2600,900,2100,3500 MHz; Modulation: 1024-QAM\n- **Camera**: Rear camera type: Triple camera; Rear camera resolution (numeric): 50 MP; Front camera type: Single camera; Front camera resolution (numeric): 4 MP; Rear camera sensor size: 1/1.56\"; Second rear camera sensor size: 1/3.2\"; Third rear camera sensor size: 1/3.94\"; Second rear camera resolution (numeric): 12 MP; Third rear camera resolution (numeric): 10 MP; Rear camera resolution: 8160 x 6120 pixels; Rear camera aperture number: 1.8; Second rear camera aperture number: 2.2; Third rear camera aperture number: 2.4; Rear camera pixel size: 1 µm; Second rear camera pixel size: 1.12 µm; Third rear camera pixel size: 1 µm; Rear camera field of view (FOV) angle: 85°; Second rear camera field of view (FOV) angle: 123°; Third rear camera field of view (FOV) angle: 36°; Optical zoom: 3x; Digital zoom: 30x; Front camera aperture number: 1.8; Cover camera resolution (numeric): 10 MP; Cover camera aperture number: 2.2; Flash type: LED; Video capture resolution (max): 7680 x 4320 pixels; Maximum frame rate: 240 fps; Resolution at capture speed: 1280x720@30fps, 1920x1080@120fps, 1920x1080@240fps, 1920x1080@30fps, 1920x1080@60fps, 3840x2160@120fps, 3840x2160@30fps, 3840x2160@60fps, 7680x4320@30fps; Image stabilizer type: Optical Image Stabilization (OIS); Slow motion rate: 240fps @FHD, 120fps @FHD, 120fps @UHD\n- **Storage**: RAM capacity: 12 GB; Internal storage capacity: 512 GB; Compatible memory cards: Not supported\n- **Processor**: Processor family: Qualcomm Snapdragon; Processor model: 8 Gen 3; Processor cores: 8\n- **Display**: Display diagonal: 19.3 cm (7.6\"); Display resolution: 2160 x 1856 pixels; Screen shape: Flat; Display technology marketing name: Dynamic AMOLED 2X; Panel type: AMOLED; Display glass type: Corning Glass; Gorilla Glass version: Gorilla Glass Victus 2; Display number of colours: 16 million colours; Maximum refresh rate: 120 Hz; Display brightness: 1500 cd/m²; Maximum display brightness (Outdoor): 2600 cd/m²; Pixel density: 374 ppi; Brand specific technologies: Always-on display; Second display diagonal: 16 cm (6.3\"); Second display resolution: 968 x 2376 pixels; Second display brightness: 1500 cd/m²; Second display maximum brightness: 2600 cd/m²; Second display type: Dynamic AMOLED 2X; Second display pixel density: 410 ppi; Second display refresh rate: 120 Hz", "image_url": "https://images.icecat.biz/img/gallery_mediums/c1256440e9123fa68c450f4bec1ce82c3ced32a5.jpg", "price": 823.06, "currency": "EUR", "categories": ["Smartphones"], "attrs": {"Display diagonal": "19.3 cm (7.6\")", "Display resolution": "2160 x 1856 pixels", "Screen shape": "Flat", "Display technology marketing name": "Dynamic AMOLED 2X", "Panel type": "AMOLED", "Display glass type": "Corning Glass", "Gorilla Glass version": "Gorilla Glass Victus 2", "Display number of colours": "16 million colours", "Maximum refresh rate": "120 Hz", "Display brightness": "1500 cd/m²", "Maximum display brightness (Outdoor)": "2600 cd/m²", "Pixel density": "374 ppi", "Brand specific technologies": "Always-on display", "Second display diagonal": "16 cm (6.3\")", "Second display resolution": "968 x 2376 pixels", "Second display brightness": "1500 cd/m²", "Second display maximum brightness": "2600 cd/m²", "Second display type": "Dynamic AMOLED 2X", "Second display pixel density": "410 ppi", "Second display refresh rate": "120 Hz", "Processor family": "Qualcomm Snapdragon", "Processor model": "8 Gen 3", "Processor cores": "8", "RAM capacity": "12 GB", "Internal storage capacity": "512 GB", "Compatible memory cards": "Not supported", "Rear camera type": "Triple camera", "Rear camera resolution (numeric)": "50 MP", "Front camera type": "Single camera", "Front camera resolution (numeric)": "4 MP", "Rear camera sensor size": "1/1.56\"", "Second rear camera sensor size": "1/3.2\"", "Third rear camera sensor size": "1/3.94\"", "Second rear camera resolution (numeric)": "12 MP", "Third rear camera resolution (numeric)": "10 MP", "Rear camera resolution": "8160 x 6120 pixels", "Rear camera aperture number": "1.8", "Second rear camera aperture number": "2.2", "Third rear camera aperture number": "2.4", "Rear camera pixel size": "1 µm", "Second rear camera pixel size": "1.12 µm", "Third rear camera pixel size": "1 µm", "Rear camera field of view (FOV) angle": "85°", "Second rear camera field of view (FOV) angle": "123°", "Third rear camera field of view (FOV) angle": "36°", "Optical zoom": "3x", "Digital zoom": "30x", "Front camera aperture number": "1.8", "Cover camera resolution (numeric)": "10 MP", "Cover camera aperture number": "2.2", "Flash type": "LED", "Video capture resolution (max)": "7680 x 4320 pixels", "Maximum frame rate": "240 fps", "Resolution at capture speed": "1280x720@30fps, 1920x1080@120fps, 1920x1080@240fps, 1920x1080@30fps, 1920x1080@60fps, 3840x2160@120fps, 3840x2160@30fps, 3840x2160@60fps, 7680x4320@30fps", "Image stabilizer type": "Optical Image Stabilization (OIS)", "Slow motion rate": "240fps @FHD, 120fps @FHD, 120fps @UHD", "SIM card capability": "Dual SIM", "Mobile network generation": "5G", "SIM card type": "NanoSIM + eSIM", "3G standards": "UMTS, WCDMA", "4G standard": "LTE-TDD & LTE-FDD", "5G standard": "Sub6 FDD, Sub6 SDL, Sub6 TDD", "Top Wi-Fi standard": "Wi-Fi 6E (802.11ax)", "2G standards": "GSM", "Wi-Fi standards": "802.11a, 802.11b, 802.11g, Wi-Fi 4 (802.11n), Wi-Fi 5 (802.11ac), Wi-Fi 6 (802.11ax), Wi-Fi 6E (802.11ax)", "Bluetooth version": "5.3", "2G bands (primary SIM)": "900,1900,850,1800 MHz", "Frequency band": "Tri-band", "3G bands supported": "900,850,1900,2100 MHz", "4G bands supported": "1500,2100,700,2300,800,1800,850,1900,2500,900,2600 MHz", "5G bands supported": "2300,700,800,1800,2500,850,1900,2600,900,2100,3500 MHz", "Modulation": "1024-QAM", "Subscription type": "No subscription", "USB connector type": "USB Type-C", "USB version": "3.2 Gen 1 (3.1 Gen 1)", "Headphone connectivity": "USB Type-C", "Form factor": "Clamshell", "Product colour": "Silver", "Colour name": "Silver Shadow", "Protection features": "Water resistant", "Housing material": "Aluminium", "Speakers": "stereo", "Audio formats supported": "MIDI, APE, AAC, AWB, MP3, RTTTL, RTX, WAV, DFF, MXMF, DSF, OGA, OGG, XMF, M4A, OTA, FLAC, AMR, Mid", "Video formats supported": "3GP, AVI, FLV, M4V, MKV, MP4, WEBM", "Platform": "Android", "Operating system installed": "Android 14", "Virtual assistant": "Samsung Bixby", "Battery capacity": "4400 mAh", "Battery recharge time": "1.4 h", "Browsing time (Wi-Fi)": "18 h", "Browsing time (4G)": "18 h", "Continuous audio playback time": "77 h", "Continuous video playback time": "23 h", "USB Type-C required charging power (min)": "10 W", "USB Type-C required charging power (max)": "25 W", "International Protection (IP) code": "IP48", "Weight": "239 g", "Width": "132.6 mm", "Depth": "5.6 mm", "Height": "153.5 mm", "Folded width": "6.81 cm", "Folded depth": "1.21 cm", "Folded height": "15.3 cm", "Cables included": "USB Type-C", "Repairability index": "7.8"}, "attr_keys": ["2G bands (primary SIM)", "2G standards", "3G bands supported", "3G standards", "4G bands supported", "4G standard", "5G bands supported", "5G standard", "Audio formats supported", "Battery capacity", "Battery recharge time", "Bluetooth version", "Brand specific technologies", "Browsing time (4G)", "Browsing time (Wi-Fi)", "Cables included", "Colour name", "Compatible memory cards", "Continuous audio playback time", "Continuous video playback time", "Cover camera aperture number", "Cover camera resolution (numeric)", "Depth", "Digital zoom", "Display brightness", "Display diagonal", "Display glass type", "Display number of colours", "Display resolution", "Display technology marketing name", "Flash type", "Folded depth", "Folded height", "Folded width", "Form factor", "Frequency band", "Front camera aperture number", "Front camera resolution (numeric)", "Front camera type", "Gorilla Glass version", "Headphone connectivity", "Height", "Housing material", "Image stabilizer type", "Internal storage capacity", "International Protection (IP) code", "Maximum display brightness (Outdoor)", "Maximum frame rate", "Maximum refresh rate", "Mobile network generation", "Modulation", "Operating system installed", "Optical zoom", "Panel type", "Pixel density", "Platform", "Processor cores", "Processor family", "Processor model", "Product colour", "Protection features", "RAM capacity", "Rear camera aperture number", "Rear camera field of view (FOV) angle", "Rear camera pixel size", "Rear camera resolution", "Rear camera resolution (numeric)", "Rear camera sensor size", "Rear camera type", "Repairability index", "Resolution at capture speed", "SIM card capability", "SIM card type", "Screen shape", "Second display brightness", "Second display diagonal", "Second display maximum brightness", "Second display pixel density", "Second display refresh rate", "Second display resolution", "Second display type", "Second rear camera aperture number", "Second rear camera field of view (FOV) angle", "Second rear camera pixel size", "Second rear camera resolution (numeric)", "Second rear camera sensor size", "Slow motion rate", "Speakers", "Subscription type", "Third rear camera aperture number", "Third rear camera field of view (FOV) angle", "Third rear camera pixel size", "Third rear camera resolution (numeric)", "Third rear camera sensor size", "Top Wi-Fi standard", "USB Type-C required charging power (max)", "USB Type-C required charging power (min)", "USB connector type", "USB version", "Video capture resolution (max)", "Video formats supported", "Virtual assistant", "Weight", "Wi-Fi standards", "Width"]}
{"id": "30783187", "title": "LG K4 K120E 11.4 cm (4.5\") Android 5.1 4G 1 GB 8 GB 1940 mAh White", "brand": "LG", "description": "LG K4 K120E 11.4 cm (4.5\") Android 5.1 4G 1 GB 8 GB 1940 mAh White\n\n\nFind Your Own Style You are the hero of your story and you call all the shots. Stand out against convention and follow your intuition. Explore the world around you and capture selfies of every bold move you make! The LG K4 is an original, just like you. Adventure on! 4.5\" Display + Compact Design Meet the wow factor! Impress at every occasion with a sleek, stylish design and a screen where all your colors pop. Gesture Shot Perfect your selfie pose. Just raise your hand, align it in the box, and make a fist to start the 3-second timer. Don’t forget to smile! Flash for Selfie The night is your time to shine! With 2MP front camera, take brilliant selfies with a screen that lights up around the photo preview. 5MP Rear Camera Make memories that go viral. Shoot share-worthy pictures with an easy-to-use 5MP rear camera.\n\n\nKey Specifications:\n- **Weight & dimensions**: Weight: 120 g; Width: 66.7 mm; Depth: 8.9 mm; Height: 131.9 mm\n- **Battery**: Battery capacity: 1940 mAh; Talk time (3G): 9.5 h; Standby time (3G): 500 h; Battery technology: Lithium-Ion (Li-Ion); Talk time (2G): 20 h; Standby time (2G): 510 h; Standby time (4G): 460 h\n- **Software**: Platform: Android; Operating system installed: Android 5.1; App distribution platform: Google Play\n- **Design**: Form factor: Bar; Product colour: White\n- **Ports & interfaces**: HDMI ports quantity: 0\n- **Subscription**: Subscription type: No subscription\n- **Network**: Mobile network generation: 4G; SIM card type: MicroSIM; 3G standards: HSDPA, HSDPA+, HSUPA, UMTS; 4G standard: LTE; 2G standards: Edge, GSM; Wi-Fi standards: 802.11b, 802.11g, Wi-Fi 4 (802.11n)\n- **Camera**: Rear camera type: Single camera; Rear camera resolution (numeric): 5 MP; Front camera type: Single camera; Front camera resolution (numeric): 2 MP; Flash type: LED; Maximum frame rate: 30 fps; Resolution at capture speed: 1280x720@30fps; Video recording modes: 720p\n- **Storage**: RAM capacity: 1 GB; Internal storage capacity: 8 GB; Compatible memory cards: MicroSD (TransFlash); Maximum memory card size: 32 GB\n- **Processor**: Processor family: MediaTek; Processor model: MT6735M; Processor frequency: 1 GHz; Processor architecture: ARM Cortex-A53; Processor cores: 4\n- **Display**: Display diagonal: 11.4 cm (4.5\"); Display resolution: 854 x 480 pixels; Panel type: LCD; Display number of colours: 16.78 million colours", "image_url": "https://images.icecat.biz/img/gallery_mediums/30783187_7201.jpg", "price": 674.16, "currency": "EUR", "categories": ["Smartphones"], "attrs": {"Display diagonal": "11.4 cm (4.5\")", "Display resolution": "854 x 480 pixels", "Panel type": "LCD", "Display number of colours": "16.78 million colours", "Processor family": "MediaTek", "Processor model": "MT6735M", "Processor frequency": "1 GHz", "Processor architecture": "ARM Cortex-A53", "Processor cores": "4", "RAM capacity": "1 GB", "Internal storage capacity": "8 GB", "Compatible memory cards": "MicroSD (TransFlash)", "Maximum memory card size": "32 GB", "Rear camera type": "Single camera", "Rear camera resolution (numeric)": "5 MP", "Front camera type": "Single camera", "Front camera resolution (numeric)": "2 MP", "Flash type": "LED", "Maximum frame rate": "30 fps", "Resolution at capture speed": "1280x720@30fps", "Video recording modes": "720p", "Mobile network generation": "4G", "SIM card type": "MicroSIM", "3G standards": "HSDPA, HSDPA+, HSUPA, UMTS", "4G standard": "LTE", "2G standards": "Edge, GSM", "Wi-Fi standards": "802.11b, 802.11g, Wi-Fi 4 (802.11n)", "Subscription type": "No subscription", "HDMI ports quantity": "0", "Form factor": "Bar", "Product colour": "White", "Platform": "Android", "Operating system installed": "Android 5.1", "App distribution platform": "Google Play", "Battery capacity": "1940 mAh", "Talk time (3G)": "9.5 h", "Standby time (3G)": "500 h", "Battery technology": "Lithium-Ion (Li-Ion)", "Talk time (2G)": "20 h", "Standby time (2G)": "510 h", "Standby time (4G)": "460 h", "Weight": "120 g", "Width": "66.7 mm", "Depth": "8.9 mm", "Height": "131.9 mm"}, "attr_keys": ["2G standards", "3G standards", "4G standard", "App distribution platform", "Battery capacity", "Battery technology", "Compatible memory cards", "Depth", "Display diagonal", "Display number of colours", "Display resolution", "Flash type", "Form factor", "Front camera resolution (numeric)", "Front camera type", "HDMI ports quantity", "Height", "Internal storage capacity", "Maximum frame rate", "Maximum memory card size", "Mobile network generation", "Operating system installed", "Panel type", "Platform", "Processor architecture", "Processor cores", "Processor family", "Processor frequency", "Processor model", "Product colour", "RAM capacity", "Rear camera resolution (numeric)", "Rear camera type", "Resolution at capture speed", "SIM card type", "Standby time (2G)", "Standby time (3G)", "Standby time (4G)", "Subscription type", "Talk time (2G)", "Talk time (3G)", "Video recording modes", "Weight", "Wi-Fi standards", "Width"]}
{"id": "107478824", "title": "TCL 40 403 15.2 cm (6\") Dual SIM Android 12 Go edition 4G Micro-USB B 2 GB 32 GB 3000 mAh Black", "brand": "TCL", "description": "TCL 40 403 15.2 cm (6\") Dual SIM Android 12 Go edition 4G Micro-USB B 2 GB 32 GB 3000 mAh Black\n\n\nEnjoy what you see. Stylishly enlarged 6\" screen with in-hand comfort. Expansive. Captivating. Ultra-wide 18:9 aspect ratio offers movie-like viewing. 2 eye-care modes provide ultimate comfort for your e-reading and streaming time. Dedicated eye comfort. Less harmful blue light while web browsing and streaming. For e-reading sessions. A paper-like screen with soothing grayscale effect. Storage for all that matters. Enjoy getting things done with all essential apps, stored together with your daily snaps and videos. 2GB RAM for snappy multitasking. Run multiple apps and keep several tabs open while web browsing or streaming smoothly. 256/512 GB microSD 32GB memory can be conveniently extended. All-day power for your daily life. Smart power-saving modes optimize the 3000mAh battery, preserving the power you need for web browsing, streaming, and completing daily tasks. Super power saving. Increase battery life by up to 20% while your phone is not in use. 2-in-1 hyper camera Enhanced macro shots. Easily record close-ups and wider scenes with a 2-in-1 hyper camera. Its main 8MP lens smartly works as a macro one. More light. Brighter pics. HDR mode reveals more colors for low-light shots. More pixels. Bigger pics. A 2MP front camera shoots with the clarity effect of 5MP resolution.\n\n\nKey Specifications:\n- **Packaging content**: Cables included: Micro-USB\n- **Certificates**: Certification: REACH,RoHS,SVHC-XVII-17,WEEE; \nCE, FCC, GCF, GCF FT, BT SIG, WIFI Alliance\n- **Weight & dimensions**: Weight: 182 g; Width: 78.2 mm; Depth: 9.6 mm; Height: 159.2 mm; Package width: 162 mm; Package depth: 90 mm; Package height: 42 mm; Package weight: 313 g\n- **Endurance**: International Protection (IP) code: IP52\n- **Battery**: Battery capacity: 3000 mAh; Talk time (3G): 21 h; Standby time (3G): 612 h; Battery technology: Lithium-Ion (Li-Ion); Battery voltage: 5 V; Battery recharge time: 3.5 h; Talk time (4G): 20 h; Standby time (4G): 685 h\n- **Software**: Platform: Android; Operating system installed: Android 12 Go edition\n- **Multimedia**: Speakers: Mono; Speaker power: 1 W; Audio formats supported: AAC, AAC+, AMR, AWB, FLAC, MP3, PCM, Vorbis, eAAC+; Video formats supported: AVC, H.263, H.264, H.265, HEVC, MPEG4, VP8, VP9\n- **Performance**: Graphics card: IMG GE8300; Country of origin: China\n- **Design**: Form factor: Bar; Product colour: Black; Colour name: Prime Black; Housing material: Plastic\n- **Ports & interfaces**: USB connector type: Micro-USB B; Headphone connectivity: 3.5 mm\n- **Subscription**: Subscription type: No subscription\n- **Network**: SIM card capability: Dual SIM; Mobile network generation: 4G; SIM card type: NanoSIM; 3G standards: HSPA+; 4G standard: LTE-TDD & LTE-FDD; 5G standard: Not supported; Wi-Fi standards: 802.11b, 802.11g, Wi-Fi 4 (802.11n); Bluetooth version: 5.0; Frequency band: Single-band\n- **Camera**: Rear camera type: Single camera; Rear camera resolution (numeric): 8 MP; Front camera type: Single camera; Front camera resolution (numeric): 5 MP; Rear camera sensor size: 1/4\"; Rear camera aperture number: 2; Rear camera pixel size: 1.12 µm; Rear camera field of view (FOV) angle: 76.9°; Rear camera lens elements: 4-element lens; Front camera lens elements: 2-element lens; Front camera sensor size: 1/5\"; Front camera aperture number: 2.8; Front camera pixel size: 1.75 µm; Front camera field of view (FOV) angle: 61.4°; Flash type: LED; Video capture resolution (max): 1920 x 1080 pixels; Maximum frame rate: 30 fps\n- **Storage**: RAM capacity: 2 GB; Internal storage capacity: 32 GB; Compatible memory cards: MicroSD (TransFlash), MicroSDHC, MicroSDXC; User memory: 21 GB; RAM type: LPDDR4X; Maximum memory card size: 512 GB; Memory card slot type: Dedicated slot\n- **Processor**: Processor family: MediaTek; Processor model: Helio A22; Processor frequency: 2 GHz; Processor architecture: ARM Cortex-A53; Processor cores: 4\n- **Display**: Display diagonal: 15.2 cm (6\"); Display resolution: 480 x 960 pixels; Screen shape: Flat; Panel type: IPS; Native aspect ratio: 18:9; Contrast ratio (typical): 1000:1; Display brightness: 400 cd/m²; Touchscreen type: Capacitive; Pixel density: 179 ppi", "image_url": "https://images.icecat.biz/img/gallery_mediums/107478824_1145969408.jpg", "price": 455.28, "currency": "EUR", "categories": ["Smartphones"], "attrs": {"Display diagonal": "15.2 cm (6\")", "Display resolution": "480 x 960 pixels", "Screen shape": "Flat", "Panel type": "IPS", "Native aspect ratio": "18:9", "Contrast ratio (typical)": "1000:1", "Display brightness": "400 cd/m²", "Touchscreen type": "Capacitive", "Pixel density": "179 ppi", "Processor family": "MediaTek", "Processor model": "Helio A22", "Processor frequency": "2 GHz", "Processor architecture": "ARM Cortex-A53", "Processor cores": "4", "RAM capacity": "2 GB", "Internal storage capacity": "32 GB", "Compatible memory cards": "MicroSD (TransFlash), MicroSDHC, MicroSDXC", "User memory": "21 GB", "RAM type": "LPDDR4X", "Maximum memory card size": "512 GB", "Memory card slot type": "Dedicated slot", "Rear camera type": "Single camera", "Rear camera resolution (numeric)": "8 MP", "Front camera type": "Single camera", "Front camera resolution (numeric)": "5 MP", "Rear camera sensor size": "1/4\"", "Rear camera aperture number": "2", "Rear camera pixel size": "1.12 µm", "Rear camera field of view (FOV) angle": "76.9°", "Rear camera lens elements": "4-element lens", "Front camera lens elements": "2-element lens", "Front camera sensor size": "1/5\"", "Front camera aperture number": "2.8", "Front camera pixel size": "1.75 µm", "Front camera field of view (FOV) angle": "61.4°", "Flash type": "LED", "Video capture resolution (max)": "1920 x 1080 pixels", "Maximum frame rate": "30 fps", "SIM card capability": "Dual SIM", "Mobile network generation": "4G", "SIM card type": "NanoSIM", "3G standards": "HSPA+", "4G standard": "LTE-TDD & LTE-FDD", "5G standard": "Not supported", "Wi-Fi standards": "802.11b, 802.11g, Wi-Fi 4 (802.11n)", "Bluetooth version": "5.0", "Frequency band": "Single-band", "Subscription type": "No subscription", "USB connector type": "Micro-USB B", "Headphone connectivity": "3.5 mm", "Form factor": "Bar", "Product colour": "Black", "Colour name": "Prime Black", "Housing material": "Plastic", "Graphics card": "IMG GE8300", "Country of origin": "China", "Speakers": "Mono", "Speaker power": "1 W", "Audio formats supported": "AAC, AAC+, AMR, AWB, FLAC, MP3, PCM, Vorbis, eAAC+", "Video formats supported": "AVC, H.263, H.264, H.265, HEVC, MPEG4, VP8, VP9", "Platform": "Android", "Operating system installed": "Android 12 Go edition", "Battery capacity": "3000 mAh", "Talk time (3G)": "21 h", "Standby time (3G)": "612 h", "Battery technology": "Lithium-Ion (Li-Ion)", "Battery voltage": "5 V", "Battery recharge time": "3.5 h", "Talk time (4G)": "20 h", "Standby time (4G)": "685 h", "International Protection (IP) code": "IP52", "Weight": "182 g", "Width": "78.2 mm", "Depth": "9.6 mm", "Height": "159.2 mm", "Package width": "162 mm", "Package depth": "90 mm", "Package height": "42 mm", "Package weight": "313 g", "Certification": "REACH,RoHS,SVHC-XVII-17,WEEE; \nCE, FCC, GCF, GCF FT, BT SIG, WIFI Alliance", "Cables included": "Micro-USB"}, "attr_keys": ["3G standards", "4G standard", "5G standard", "Audio formats supported", "Battery capacity", "Battery recharge time", "Battery technology", "Battery voltage", "Bluetooth version", "Cables included", "Certification", "Colour name", "Compatible memory cards", "Contrast ratio (typical)", "Country of origin", "Depth", "Display brightness", "Display diagonal", "Display resolution", "Flash type", "Form factor", "Frequency band", "Front camera aperture number", "Front camera field of view (FOV) angle", "Front camera lens elements", "Front camera pixel size", "Front camera resolution (numeric)", "Front camera sensor size", "Front camera type", "Graphics card", "Headphone connectivity", "Height", "Housing material", "Internal storage capacity", "International Protection (IP) code", "Maximum frame rate", "Maximum memory card size", "Memory card slot type", "Mobile network generation", "Native aspect ratio", "Operating system installed", "Package depth", "Package height", "Package weight", "Package width", "Panel type", "Pixel density", "Platform", "Processor architecture", "Processor cores", "Processor family", "Processor frequency", "Processor model", "Product colour", "RAM capacity", "RAM type", "Rear camera aperture number", "Rear camera field of view (FOV) angle", "Rear camera lens elements", "Rear camera pixel size", "Rear camera resolution (numeric)", "Rear camera sensor size", "Rear camera type", "SIM card capability", "SIM card type", "Screen shape", "Speaker power", "Speakers", "Standby time (3G)", "Standby time (4G)", "Subscription type", "Talk time (3G)", "Talk time (4G)", "Touchscreen type", "USB connector type", "User memory", "Video capture resolution (max)", "Video formats supported", "Weight", "Wi-Fi standards", "Width"]}
{"id": "30783301", "title": "Samsung Galaxy S6 edge+ SM-G928 14.5 cm (5.7\") Single SIM Android 5.1 4G Micro-USB 4 GB 64 GB 3000 mAh Black", "brand": "mcare", "description": "Samsung Galaxy S6 edge+ SM-G928 14.5 cm (5.7\") Single SIM Android 5.1 4G Micro-USB 4 GB 64 GB 3000 mAh Black\n\n\nBig screen. Big entertainment. Immerse yourself in the content you love with the sleek design and brilliant dual edge screen on the Galaxy S6 edge+. With a 5.7\" Quad HD Super AMOLED 2560x1440 resolution display, you can watch videos and images come to life on your screen. The edge of innovation Keep your top five contacts and apps at your fingertips for quick access. Always see who’s contacting you with a discreet light-up notification on the edge screen. Share live video in real time Share life’s can’t-miss moments with your friends as they happen. Take live video and broadcast it via YouTube™ with this built-in app. Pay Almost Anywhere You Can Swipe or Tap Your Card‡ Introducing Samsung Pay, the mobile payment service that works virtually anywhere you can swipe your card — from local grocery stores to corner coffee shops to your favorite department store. It’s also highly secure and simple to use with your Galaxy S6 edge+. Only compatible with select cards from participating banks/issuers, participating carriers and certain Samsung devices; check the Samsung Pay page for a compatibility list. Breakthrough battery technology The Samsung Galaxy S6 edge+ built-in technology gives you the freedom to recharge wirelessly. Fast Charging lets you power your 3,000mAh battery quickly. Or you can tap Ultra Power Saving Mode at 10% charge and get up to 24 hours of talk and text time. Powerful performance Powered by the Samsung Exynos 7420 Octa-core 64-bit processor and combined with 4GB of RAM, the new Galaxy S6 edge+ gives you our best speed and performance. Load times are faster, so you can browse, work, watch and game in an instant. The easy way to transfer content to a new device Switching to the new Galaxy S6 edge+ has never been simpler — or smarter. With Samsung Smart Switch, you have the freedom to move your contacts, text messages, music and other media from your previous device to your new Samsung Galaxy. The way music should be heard Your favorite tunes have never sounded better on a Samsung smartphone. This breakthrough audio technology can take select music files and enhance the richness and detail. More reasons to love your Galaxy S6 edge+ Get the most out of your Galaxy S6 edge+ with the Samsung+ app. Along with one-touch access to customer support, you’ll discover device tips, a library of resources and more. Plus, you’ll have access to complimentary music and exclusive clips. Samsung+ makes life with the Galaxy S6 edge+ even better.\n\n\nKey Specifications:\n- **Packaging content**: Cables included: USB\n- **Certificates**: Head SAR (EU): 0.291 W/kg; Body SAR (EU): 0.572 W/kg\n- **Weight & dimensions**: Weight: 153 g; Width: 75.8 mm; Depth: 6.9 mm; Height: 154.4 mm\n- **Battery**: Battery capacity: 3000 mAh; Talk time (3G): 20 h; Browsing time (Wi-Fi): 12 h; Browsing time (3G): 10 h; Browsing time (4G): 11 h; Continuous audio playback time: 66 h; Continuous video playback time: 15 h\n- **Software**: Platform: Android; Operating system installed: Android 5.1; App distribution platform: Google Play; Google applications: Google Maps, Google Play, YouTube\n- **Multimedia**: Audio formats supported: 3GA, AAC, AMR, AWB, FLAC, IMY, M4A, Mid, MIDI, MP3, MXMF, OGA, OGG, OTA, RTTTL, RTX, WAV, WMA, XMF; Video formats supported: 3G2, 3GP, ASF, AVI, FLV, M4V, MKV, MP4, WEBM, WMV; Image formats supported: JPG, PNG; Voice codecs: AMR-NB, AMR-WB\n- **Performance**: Personal info management (PIM): Alarm clock, Calculator, Calendar, Events reminder, Notes, To-do list; Personalization: Icons, Menu, Shortcuts; Themes: Wallpapers\n- **Design**: Form factor: Bar; Product colour: Black; Colour name: Black Sapphire\n- **Ports & interfaces**: USB connector type: Micro-USB; USB version: 2.0; HDMI ports quantity: 0; Headphone connectivity: 3.5 mm\n- **Subscription**: Subscription type: Prepaid\n- **Network**: SIM card capability: Single SIM; Mobile network generation: 4G; SIM card type: NanoSIM; 3G standards: UMTS, WCDMA; 4G standard: LTE; 2G standards: GSM; Wi-Fi standards: 802.11a, Wi-Fi 5 (802.11ac), 802.11b, 802.11g, Wi-Fi 4 (802.11n); Bluetooth version: 4.2; Bluetooth profiles: A2DP, AVRCP, HFP, HID, HOGP, HSP, MAP, OPP, PAN, PBAP, SAP; 2G bands (primary SIM): 850,1800,1900 MHz; 3G bands supported: 850,900,1900,2100 MHz; 4G bands supported: 700,800,850,900,1800,1900,2100,2600 MHz\n- **Camera**: Rear camera type: Single camera; Rear camera resolution (numeric): 16 MP; Front camera type: Single camera; Front camera resolution (numeric): 5 MP; Rear camera resolution: 3840 x 2160 pixels; Digital zoom: 8x; Flash type: LED; Sensor type: CMOS; Video capture resolution (max): 3840 x 2160 pixels; Maximum frame rate: 120 fps; Video recording modes: 720p, 1080p, 2160p; ISO sensitivity: Auto; White balance: Auto\n- **Storage**: RAM capacity: 4 GB; Internal storage capacity: 64 GB; Compatible memory cards: Not supported; RAM type: LPDDR4\n- **Processor**: Processor family: Samsung Exynos; Processor model: 7 Octa 7420; Processor frequency: 2.1 GHz; Processor cores: 4; Coprocessor frequency: 1.5 GHz; Coprocessor cores: 4\n- **Display**: Display diagonal: 14.5 cm (5.7\"); Display resolution: 2560 x 1440 pixels; Screen shape: Curved edge screen; Display technology marketing name: Super AMOLED; Panel type: OLED; Display number of colours: 16 million colours; Native aspect ratio: 16:9; Touch technology: Multi-touch; Touchscreen type: Capacitive; Pixel density: 518 ppi", "image_url": "https://images.icecat.biz/img/gallery_mediums/30783301_8305774599.jpg", "price": 711.96, "currency": "EUR", "categories": ["Smartphones"], "attrs": {"Display diagonal": "14.5 cm (5.7\")", "Display resolution": "2560 x 1440 pixels", "Screen shape": "Curved edge screen", "Display technology marketing name": "Super AMOLED", "Panel type": "OLED", "Display number of colours": "16 million colours", "Native aspect ratio": "16:9", "Touch technology": "Multi-touch", "Touchscreen type": "Capacitive", "Pixel density": "518 ppi", "Processor family": "Samsung Exynos", "Processor model": "7 Octa 7420", "Processor frequency": "2.1 GHz", "Processor cores": "4", "Coprocessor frequency": "1.5 GHz", "Coprocessor cores": "4", "RAM capacity": "4 GB", "Internal storage capacity": "64 GB", "Compatible memory cards": "Not supported", "RAM type": "LPDDR4", "Rear camera type": "Single camera", "Rear camera resolution (numeric)": "16 MP", "Front camera type": "Single camera", "Front camera resolution (numeric)": "5 MP", "Rear camera resolution": "3840 x 2160 pixels", "Digital zoom": "8x", "Flash type": "LED", "Sensor type": "CMOS", "Video capture resolution (max)": "3840 x 2160 pixels", "Maximum frame rate": "120 fps", "Video recording modes": "720p, 1080p, 2160p", "ISO sensitivity": "Auto", "White balance": "Auto", "SIM card capability": "Single SIM", "Mobile network generation": "4G", "SIM card type": "NanoSIM", "3G standards": "UMTS, WCDMA", "4G standard": "LTE", "2G standards": "GSM", "Wi-Fi standards": "802.11a, Wi-Fi 5 (802.11ac), 802.11b, 802.11g, Wi-Fi 4 (802.11n)", "Bluetooth version": "4.2", "Bluetooth profiles": "A2DP, AVRCP, HFP, HID, HOGP, HSP, MAP, OPP, PAN, PBAP, SAP", "2G bands (primary SIM)": "850,1800,1900 MHz", "3G bands supported": "850,900,1900,2100 MHz", "4G bands supported": "700,800,850,900,1800,1900,2100,2600 MHz", "Subscription type": "Prepaid", "USB connector type": "Micro-USB", "USB version": "2.0", "HDMI ports quantity": "0", "Headphone connectivity": "3.5 mm", "Form factor": "Bar", "Product colour": "Black", "Colour name": "Black Sapphire", "Personal info management (PIM)": "Alarm clock, Calculator, Calendar, Events reminder, Notes, To-do list", "Personalization": "Icons, Menu, Shortcuts", "Themes": "Wallpapers", "Audio formats supported": "3GA, AAC, AMR, AWB, FLAC, IMY, M4A, Mid, MIDI, MP3, MXMF, OGA, OGG, OTA, RTTTL, RTX, WAV, WMA, XMF", "Video formats supported": "3G2, 3GP, ASF, AVI, FLV, M4V, MKV, MP4, WEBM, WMV", "Image formats supported": "JPG, PNG", "Voice codecs": "AMR-NB, AMR-WB", "Platform": "Android", "Operating system installed": "Android 5.1", "App distribution platform": "Google Play", "Google applications": "Google Maps, Google Play, YouTube", "Battery capacity": "3000 mAh", "Talk time (3G)": "20 h", "Browsing time (Wi-Fi)": "12 h", "Browsing time (3G)": "10 h", "Browsing time (4G)": "11 h", "Continuous audio playback time": "66 h", "Continuous video playback time": "15 h", "Weight": "153 g", "Width": "75.8 mm", "Depth": "6.9 mm", "Height": "154.4 mm", "Head SAR (EU)": "0.291 W/kg", "Body SAR (EU)": "0.572 W/kg", "Cables included": "USB"}, "attr_keys": ["2G bands (primary SIM)", "2G standards", "3G bands supported", "3G standards", "4G bands supported", "4G standard", "App distribution platform", "Audio formats supported", "Battery capacity", "Bluetooth profiles", "Bluetooth version", "Body SAR (EU)", "Browsing time (3G)", "Browsing time (4G)", "Browsing time (Wi-Fi)", "Cables included", "Colour name", "Compatible memory cards", "Continuous audio playback time", "Continuous video playback time", "Coprocessor cores", "Coprocessor frequency", "Depth", "Digital zoom", "Display diagonal", "Display number of colours", "Display resolution", "Display technology marketing name", "Flash type", "Form factor", "Front camera resolution (numeric)", "Front camera type", "Google applications", "HDMI ports quantity", "Head SAR (EU)", "Headphone connectivity", "Height", "ISO sensitivity", "Image formats supported", "Internal storage capacity", "Maximum frame rate", "Mobile network generation", "Native aspect ratio", "Operating system installed", "Panel type", "Personal info management (PIM)", "Personalization", "Pixel density", "Platform", "Processor cores", "Processor family", "Processor frequency", "Processor model", "Product colour", "RAM capacity", "RAM type", "Rear camera resolution", "Rear camera resolution (numeric)", "Rear camera type", "SIM card capability", "SIM card type", "Screen shape", "Sensor type", "Subscription type", "Talk time (3G)", "Themes", "Touch technology", "Touchscreen type", "USB connector type", "USB version", "Video capture resolution (max)", "Video formats supported", "Video recording modes", "Voice codecs", "Weight", "White balance", "Wi-Fi standards", "Width"]}
