{"id": "114407437", "title": "Lenovo Tab P11 (2nd Gen) 6gb 128GB 11.5\" 2k (2000X1200) IPS Tablet ZABF0302TR", "brand": "Lenovo", "description": "Lenovo Tab P11 (2nd Gen) 6gb 128GB 11.5\" 2k (2000X1200) IPS Tablet ZABF0302TR\n\n\nKey Specifications:\n- **Packaging content**: Cables included: USB Type-C\n- **Power**: AC adapter power: 20 W; AC adapter input voltage: 240 V; AC adapter frequency: 60 Hz; AC adapter output voltage: 10 V; AC adapter output current: 2 A\n- **Battery**: Battery technology: Lithium Polymer (LiPo); Battery capacity: 7500 mAh; Battery voltage: 10 V\n- **Software**: Platform: Android; Operating system installed: Android 12\n- **Design**: Form factor: Convertible (Detachable); Product colour: Grey; Device type: Mobile tablet; Colour name: Storm Grey\n- **Ports & interfaces**: USB 2.0 Type-C ports quantity: 1; Headphone connectivity: 3.5 mm\n- **Network**: Top Wi-Fi standard: Wi-Fi 6E (802.11ax); Bluetooth version: 5.2; Wi-Fi standards: 802.11a, 802.11ad, 802.11b, 802.11g, Wi-Fi 4 (802.11n), Wi-Fi 5 (802.11ac), Wi-Fi 6 (802.11ax), Wi-Fi 6E (802.11ax)\n- **Camera**: Rear camera type: Single camera; Rear camera resolution (numeric): 13 MP; Rear camera field of view (FOV) angle: 89°; Video recording modes: 1080p; Resolution at capture speed: 1920x1080@30fps; Video capturing speed: 30 fps; Front camera resolution (numeric): 8 MP; Front camera field of view (FOV) angle: 83°\n- **Audio**: Audio system: Dolby Atmos; Speaker power: 1 W\n- **Graphics**: Graphics card family: ARM; Graphics card: Mali-G57 MC2\n- **Storage**: Internal storage capacity: 128 GB; Storage media: uMCP; Compatible memory cards: MicroSD (TransFlash); Maximum memory card size: 1 TB\n- **Memory**: Internal memory: 6 GB; Internal memory type: LPDDR4x-SDRAM\n- **Processor**: Processor manufacturer: MediaTek; Processor family: Mediatek; Processor model: Helio G99; Processor frequency: 2.2 GHz; Processor cores: 8\n- **Display**: Display diagonal: 29.2 cm (11.5\"); Panel type: IPS; Display resolution: 2000 x 1200 pixels; Pixel density: 204 ppi; HD type: 2K; Native aspect ratio: 15:9", "image_url": "https://images.icecat.biz/img/gallery_mediums/08ccb037fbb371573e555e2250d36d8d.jpg", "price": 647.61, "currency": "EUR", "categories": ["Tablets"], "attrs": {"Display diagonal": "29.2 cm (11.5\")", "Panel type": "IPS", "Display resolution": "2000 x 1200 pixels", "Pixel density": "204 ppi", "HD type": "2K", "Native aspect ratio": "15:9", "Processor manufacturer": "MediaTek", "Processor family": "Mediatek", "Processor model": "Helio G99", "Processor frequency": "2.2 GHz", "Processor cores": "8", "Internal memory": "6 GB", "Internal memory type": "LPDDR4x-SDRAM", "Internal storage capacity": "128 GB", "Storage media": "uMCP", "Compatible memory cards": "MicroSD (TransFlash)", "Maximum memory card size": "1 TB", "Graphics card family": "ARM", "Graphics card": "Mali-G57 MC2", "Audio system": "Dolby Atmos", "Speaker power": "1 W", "Rear camera type": "Single camera", "Rear camera resolution (numeric)": "13 MP", "Rear camera field of view (FOV) angle": "89°", "Video recording modes": "1080p", "Resolution at capture speed": "1920x1080@30fps", "Video capturing speed": "30 fps", "Front camera resolution (numeric)": "8 MP", "Front camera field of view (FOV) angle": "83°", "Top Wi-Fi standard": "Wi-Fi 6E (802.11ax)", "Bluetooth version": "5.2", "Wi-Fi standards": "802.11a, 802.11ad, 802.11b, 802.11g, Wi-Fi 4 (802.11n), Wi-Fi 5 (802.11ac), Wi-Fi 6 (802.11ax), Wi-Fi 6E (802.11ax)", "USB 20 Type-C ports quantity": "1", "Headphone connectivity": "3.5 mm", "Form factor": "Convertible (Detachable)", "Product colour": "Grey", "Device type": "Mobile tablet", "Colour name": "Storm Grey", "Platform": "Android", "Operating system installed": "Android 12", "Battery technology": "Lithium Polymer (LiPo)", "Battery capacity": "7500 mAh", "Battery voltage": "10 V", "AC adapter power": "20 W", "AC adapter input voltage": "240 V", "AC adapter frequency": "60 Hz", "AC adapter output voltage": "10 V", "AC adapter output current": "2 A", "Cables included": "USB Type-C"}, "attr_keys": ["AC adapter frequency", "AC adapter input voltage", "AC adapter output current", "AC adapter output voltage", "AC adapter power", "Audio system", "Battery capacity", "Battery technology", "Battery voltage", "Bluetooth version", "Cables included", "Colour name", "Compatible memory cards", "Device type", "Display diagonal", "Display resolution", "Form factor", "Front camera field of view (FOV) angle", "Front camera resolution (numeric)", "Graphics card", "Graphics card family", "HD type", "Headphone connectivity", "Internal memory", "Internal memory type", "Internal storage capacity", "Maximum memory card size", "Native aspect ratio", "Operating system installed", "Panel type", "Pixel density", "Platform", "Processor cores", "Processor family", "Processor frequency", "Processor manufacturer", "Processor model", "Product colour", "Rear camera field of view (FOV) angle", "Rear camera resolution (numeric)", "Rear camera type", "Resolution at capture speed", "Speaker power", "Storage media", "Top Wi-Fi standard", "USB 20 Type-C ports quantity", "Video capturing speed", "Video recording modes", "Wi-Fi standards"]}
{"id": "37406615", "title": "DELL Latitude 5285 Intel® Core™ i5 256 GB 31.2 cm (12.3\") 8 GB Wi-Fi 5 (802.11ac) Windows 10 Pro Black", "brand": "DELL", "description": "DELL Latitude 5285 Intel® Core™ i5 256 GB 31.2 cm (12.3\") 8 GB Wi-Fi 5 (802.11ac) Windows 10 Pro Black\n\n\nSecurity with style. Dell’s most secure 2-in-1 with the power of a laptop and flexibility of a tablet. Featuring a new design and optional keyboard (sold separately). Set up for success The auto-deploy kickstand is an industry-first feature designed for a smooth work experience. Place your Latitude 5285 2-in-1 on a flat surface and watch the kickstand automatically extend. It can rotate up to 150 degrees for multiple viewing angles. The ultimate defense system Best-in-class hardware security: Protect your hardware when accessing your company’s network thanks to the FIPS 140-2, TCG certified TPM2.0, FIPS 201 certified smartcard reader, touch fingerprint reader, self-encryption drive and NFC. Protect your identity: The Dell ControlVault™ provides the strongest authentication capabilities available. It stores and protects your passwords, biometric authentication, and security codes, so your credentials will be secured no matter where your work takes you. Control your data: Work worry free with powerful security solutions built into your Latitude 5285 2-in-1. Dell Data Protection includes Endpoint Security Suite Enterprise, Secure Lifecycle and Encryption for outstanding security that’s easily managed from one console. Innovative design On-the-go flexibility: At less than 2lbs, the Latitude 5285 2-in-1 is built for mobility. From meetings around the office to traveling across the country, its thin and light frame can fit anywhere. Enjoy the view, all day: Take in the 12.3\" Full HD screen without sacrificing your battery life. Up to 12 hours 29 mins2 of battery keeps up with your screen’s performance , while Corning® Gorilla® Glass 4 guards against drops and rough surfaces. Boost productivity: Streamline your workflow with an optional travel keyboard and active pen. The thin, lightweight keyboard attaches magnetically for easy transitions between laptop and tablet modes, while the active pen lets you take notes directly on the screen and magnetically attaches to your device when not in use. Powerful and easy to manage Reliable performance: Equipped with the latest generation of Intel® Core™ I processors, it’s powerful performance for your workday. All-day battery life: Make the most of your workday with up to 12 hours 29 mins2 of battery life. Automatic updates: Dell Client Command Suite comes with a set of automation tools that assists in device monitoring, deploying images, updating and more, to maximize your hardware and software investments and save time. Diagnostics, anywhere: Intel® vPro™ manages and protects your device from software attacks. Diagnose and repair your Latitude 5285 2-in-1 remotely, all while reducing power use. Extensive connectivity: Conveniently connect with a single cable or wirelessly with the optional Dell Dock and Dell Wireless Dock. Upgrade to 4G/LTE and stay connected anywhere. Featuring Windows 10 Store your ideas: Windows Ink allows you to incorporate your thoughts and ideas into the digital space. Use your optional active pen to take notes, draw and comment with this feature that’s directly integrated into your apps. Seamlessly switch tasks: Continuum optimizes content for the screen you’re currently viewing. By smoothly transitioning from laptop to tablet mode, you can stay productive with or without your keyboard. Log in with ease: Activate Windows Hello via optional infrared camera to facilitate facial recognition for easy and secure access.\n\n\nKey Specifications:\n- **Other features**: Processor socket: BGA 1356; Dell E-Value Code: N102L528512DEATBTP; Processor ARK ID: 97472\n- **Operational conditions**: Operating temperature (T-T): 0 - 35 °C; Storage temperature (T-T): -40 - 65 °C; Operating relative humidity (H-H): 10 - 90%; Storage relative humidity (H-H): 10 - 95%; Operating altitude: 0 - 3048 m; Non-operating altitude: 0 - 10668 m\n- **Weight & dimensions**: Width: 292 mm; Depth: 208.8 mm; Height: 9.76 mm; Weight: 860 g\n- **Sustainability**: Sustainability certificates: ENERGY STAR\n- **Power**: AC adapter power: 45 W; AC adapter input voltage: 100 - 240 V; AC adapter frequency: 47/63 Hz\n- **Battery**: Battery technology: Lithium Polymer (LiPo); Battery capacity: 42 Wh; Number of battery cells: 4\n- **Processor special features**: Intel® Turbo Boost Technology: 2.0; Intel Identity Protection Technology version: 1.00; Intel Secure Key Technology version: 1.00; Intel Smart Response Technology version: 1.00; Intel Stable Image Platform Program (SIPP) version: 1.00; Intel TSX-NI version: 1.00\n- **Software**: Platform: Windows; Operating system installed: Windows 10 Pro; Trial software: McAfee SecurityCenter, Microsoft Office\n- **Security**: Cable lock slot type: Noble\n- **Design**: Form factor: Slate; Product colour: Black; Device type: Tablet PC\n- **Ports & interfaces**: USB 3.2 Gen 1 (3.1 Gen 1) Type-A ports quantity: 1; USB 3.2 Gen 1 (3.1 Gen 1) Type-C ports quantity: 2; HDMI ports quantity: 0; Headphone connectivity: 3.5 mm\n- **Network**: Top Wi-Fi standard: Wi-Fi 5 (802.11ac); Bluetooth version: 4.1; Wi-Fi standards: 802.11a, Wi-Fi 5 (802.11ac), 802.11b, 802.11g, Wi-Fi 4 (802.11n)\n- **Camera**: Rear camera type: Single camera; Rear camera resolution (numeric): 8 MP; Rear camera resolution: 3264 x 2448 pixels; Video capturing speed: 30 fps; Front camera resolution (numeric): 5 MP\n- **Audio**: Number of built-in speakers: 2; Speaker power: 2 W\n- **Graphics**: Graphics card family: Intel; Graphics card: HD Graphics 620; Maximum graphics card memory: 32768 MB\n- **Storage**: Internal storage capacity: 256 GB; Storage media: SSD; Compatible memory cards: MicroSD (TransFlash)\n- **Memory**: Internal memory: 8 GB; Internal memory type: LPDDR3-SDRAM; Maximum internal memory: 8 GB; Memory clock speed: 1866 MHz\n- **Processor**: Processor manufacturer: Intel; Processor family: Intel® Core™ i5; Processor model: i5-7300U; Processor frequency: 2.6 GHz; Processor generation: 7th gen Intel® Core™ i5; Processor cores: 2; Processor threads: 4; Processor boost frequency: 3.5 GHz; Processor cache: 3 MB; Processor cache type: Smart Cache; Bus type: OPI; Processor code: SR340; Processor codename: Kaby Lake; Processor lithography: 14 nm; Processor operating modes: 64-bit; Processor package size: 42 X 24 mm; Processor series: Intel Core i5-7300 Mobile Series; Stepping: H0; Supported instruction sets: AVX 2.0, SSE4.1, SSE4.2; System bus rate: 4 GT/s; Tjunction: 100 °C; Thermal Design Power (TDP): 15 W; Configurable TDP-down frequency: 0.8 GHz; PCI Express configurations: 1x2+2x1, 1x4, 2x2, 4x1\n- **Display**: Display diagonal: 31.2 cm (12.3\"); Display resolution: 1920 x 1280 pixels; Display brightness: 340 cd/m²; Touch technology: Multi-touch; Touchscreen type: Capacitive; Native aspect ratio: 3:2", "image_url": "https://images.icecat.biz/img/gallery/37406615_8659586938.jpg", "price": 505.65, "currency": "EUR", "categories": ["Tablets"], "attrs": {"Display diagonal": "31.2 cm (12.3\")", "Display resolution": "1920 x 1280 pixels", "Display brightness": "340 cd/m²", "Touch technology": "Multi-touch", "Touchscreen type": "Capacitive", "Native aspect ratio": "3:2", "Processor manufacturer": "Intel", "Processor family": "Intel® Core™ i5", "Processor model": "i5-7300U", "Processor frequency": "2.6 GHz", "Processor generation": "7th gen Intel® Core™ i5", "Processor cores": "2", "Processor threads": "4", "Processor boost frequency": "3.5 GHz", "Processor cache": "3 MB", "Processor cache type": "Smart Cache", "Bus type": "OPI", "Processor code": "SR340", "Processor codename": "Kaby Lake", "Processor lithography": "14 nm", "Processor operating modes": "64-bit", "Processor package size": "42 X 24 mm", "Processor series": "Intel Core i5-7300 Mobile Series", "Stepping": "H0", "Supported instruction sets": "AVX 2.0, SSE4.1, SSE4.2", "System bus rate": "4 GT/s", "Tjunction": "100 °C", "Thermal Design Power (TDP)": "15 W", "Configurable TDP-down frequency": "0.8 GHz", "PCI Express configurations": "1x2+2x1, 1x4, 2x2, 4x1", "Internal memory": "8 GB", "Internal memory type": "LPDDR3-SDRAM", "Maximum internal memory": "8 GB", "Memory clock speed": "1866 MHz", "Internal storage capacity": "256 GB", "Storage media": "SSD", "Compatible memory cards": "MicroSD (TransFlash)", "Graphics card family": "Intel", "Graphics card": "HD Graphics 620", "Maximum graphics card memory": "32768 MB", "Number of built-in speakers": "2", "Speaker power": "2 W", "Rear camera type": "Single camera", "Rear camera resolution (numeric)": "8 MP", "Rear camera resolution": "3264 x 2448 pixels", "Video capturing speed": "30 fps", "Front camera resolution (numeric)": "5 MP", "Top Wi-Fi standard": "Wi-Fi 5 (802.11ac)", "Bluetooth version": "4.1", "Wi-Fi standards": "802.11a, Wi-Fi 5 (802.11ac), 802.11b, 802.11g, Wi-Fi 4 (802.11n)", "USB 32 Gen 1 (31 Gen 1) Type-A ports quantity": "1", "USB 32 Gen 1 (31 Gen 1) Type-C ports quantity": "2", "HDMI ports quantity": "0", "Headphone connectivity": "3.5 mm", "Form factor": "Slate", "Product colour": "Black", "Device type": "Tablet PC", "Cable lock slot type": "Noble", "Platform": "Windows", "Operating system installed": "Windows 10 Pro", "Trial software": "McAfee SecurityCenter, Microsoft Office", "Intel® Turbo Boost Technology": "2.0", "Intel Identity Protection Technology version": "1.00", "Intel Secure Key Technology version": "1.00", "Intel Smart Response Technology version": "1.00", "Intel Stable Image Platform Program (SIPP) version": "1.00", "Intel TSX-NI version": "1.00", "Battery technology": "Lithium Polymer (LiPo)", "Battery capacity": "42 Wh", "Number of battery cells": "4", "AC adapter power": "45 W", "AC adapter input voltage": "100 - 240 V", "AC adapter frequency": "47/63 Hz", "Sustainability certificates": "ENERGY STAR", "Width": "292 mm", "Depth": "208.8 mm", "Height": "9.76 mm", "Weight": "860 g", "Operating temperature (T-T)": "0 - 35 °C", "Storage temperature (T-T)": "-40 - 65 °C", "Operating relative humidity (H-H)": "10 - 90%", "Storage relative humidity (H-H)": "10 - 95%", "Operating altitude": "0 - 3048 m", "Non-operating altitude": "0 - 10668 m", "Processor socket": "BGA 1356", "Dell E-Value Code": "N102L528512DEATBTP", "Processor ARK ID": "97472"}, "attr_keys": ["AC adapter frequency", "AC adapter input voltage", "AC adapter power", "Battery capacity", "Battery technology", "Bluetooth version", "Bus type", "Cable lock slot type", "Compatible memory cards", "Configurable TDP-down frequency", "Dell E-Value Code", "Depth", "Device type", "Display brightness", "Display diagonal", "Display resolution", "Form factor", "Front camera resolution (numeric)", "Graphics card", "Graphics card family", "HDMI ports quantity", "Headphone connectivity", "Height", "Intel Identity Protection Technology version", "Intel Secure Key Technology version", "Intel Smart Response Technology version", "Intel Stable Image Platform Program (SIPP) version", "Intel TSX-NI version", "Intel® Turbo Boost Technology", "Internal memory", "Internal memory type", "Internal storage capacity", "Maximum graphics card memory", "Maximum internal memory", "Memory clock speed", "Native aspect ratio", "Non-operating altitude", "Number of battery cells", "Number of built-in speakers", "Operating altitude", "Operating relative humidity (H-H)", "Operating system installed", "Operating temperature (T-T)", "PCI Express configurations", "Platform", "Processor ARK ID", "Processor boost frequency", "Processor cache", "Processor cache type", "Processor code", "Processor codename", "Processor cores", "Processor family", "Processor frequency", "Processor generation", "Processor lithography", "Processor manufacturer", "Processor model", "Processor operating modes", "Processor package size", "Processor series", "Processor socket", "Processor threads", "Product colour", "Rear camera resolution", "Rear camera resolution (numeric)", "Rear camera type", "Speaker power", "Stepping", "Storage media", "Storage relative humidity (H-H)", "Storage temperature (T-T)", "Supported instruction sets", "Sustainability certificates", "System bus rate", "Thermal Design Power (TDP)", "Tjunction", "Top Wi-Fi standard", "Touch technology", "Touchscreen type", "Trial software", "USB 32 Gen 1 (31 Gen 1) Type-A ports quantity", "USB 32 Gen 1 (31 Gen 1) Type-C ports quantity", "Video capturing speed", "Weight", "Wi-Fi standards", "Width"]}
{"id": "21989104", "title": "DELL Venue 8 Intel Atom® 16 GB 20.3 cm (8\") 2 GB Wi-Fi 4 (802.11n) Android Black", "brand": "DELL", "description": "DELL Venue 8 Intel Atom® 16 GB 20.3 cm (8\") 2 GB Wi-Fi 4 (802.11n) Android Black\n\n\nFeature rich versatility High-def details: Enjoy every detail of your favorite apps, like Netflix, on a stunning HD screen. Thin and light: At less than 9.5mm thin, you can lay this lightweight tablet on your lap. Relax with your favorite Android-based games, or pop it in your bag and get going. Picture perfect: Snap amazing photos and video with a rear facing 3MP camera or video chat like a pro with the front facing VGA camera. Always up to date: Dell Venue 7 comes loaded with the latest Android Jellybean operating system. Expect enhanced performance and fun new features. Seamless connectivity All-access from anywhere: PocketCloud 2.0 gives you access to your content and applications from a PC, smartphone or tablet so you can update and share your files wherever you go. GPS and location-based services: Know where you’re going and where you’ve been with location services that are available even when you’re offline. Reliable productivity High-performance: Speed through your to-do list with a powerful Intel® Atom™ (up to 1.6GHz Dual-Core) processor Z2580. Power up: Spend more time away from the outlet with all-day battery life. Keep your schedule running smoothly with up to 10 hours6 of power and battery support. Store more: Take your multimedia and other files with you with up to 16GB7 of hard drive storage plus a micro SD slot for up to 32GB of additional storage.\n\n\nKey Specifications:\n- **Other features**: Processor socket: FC-MB4760; Processor ARK ID: 70100\n- **Packaging content**: Cables included: AC\n- **Weight & dimensions**: Width: 130 mm; Depth: 9.5 mm; Height: 212 mm; Weight: 350 g\n- **Power**: AC adapter power: 10 W\n- **Battery**: Battery capacity: 4100 mAh; Battery capacity: 15.5 Wh; Number of battery cells: 1; Battery life (max): 7.9 h\n- **Processor special features**: Intel Smart Idle Technology version: 1.00; Physical Address Extension (PAE): 32 bit\n- **Software**: Platform: Android; Operating system installed: Android; Operating system version: 4.2.2; Bundled software: --\n- **Design**: Form factor: Slate; Product colour: Black; Device type: Mobile tablet\n- **Ports & interfaces**: USB 2.0 ports quantity: 0; Micro-USB 2.0 ports quantity: 1; HDMI ports quantity: 0\n- **Network**: Top Wi-Fi standard: Wi-Fi 4 (802.11n); Bluetooth version: 4.0; Wi-Fi standards: 802.11b, 802.11g, Wi-Fi 4 (802.11n)\n- **Camera**: Rear camera type: Single camera; Rear camera resolution (numeric): 5 MP; Front camera resolution (numeric): 2 MP\n- **Graphics**: Graphics card family: Intel; Graphics card: HD Graphics\n- **Storage**: Internal storage capacity: 16 GB; Storage media: Flash; Compatible memory cards: MicroSD (TransFlash), MicroSDHC; Maximum memory card size: 32 GB\n- **Memory**: Internal memory: 2 GB; Internal memory type: DDR2-SDRAM\n- **Processor**: Processor manufacturer: Intel; Processor family: Intel Atom®; Processor model: Z2580; Processor cores: 2; Processor threads: 4; Processor boost frequency: 2 GHz; Processor cache: 1 MB; Processor cache type: Smart Cache; Graphics & IMC lithography: 32 nm; Processor code: SR146; Processor lithography: 32 nm; Processor operating modes: 32-bit; Processor package size: 14 x 14 mm; Stepping: B1; Supported instruction sets: SSE2, SSE3, SSSE3; Tjunction: 90 °C\n- **Display**: Display diagonal: 20.3 cm (8\"); Panel type: IPS; Display resolution: 1280 x 800 pixels; Touch technology: Multi-touch; Touchscreen type: Capacitive", "image_url": "https://images.icecat.biz/img/gallery_mediums/21609189_3583.jpg", "price": 675.38, "currency": "EUR", "categories": ["Tablets"], "attrs": {"Display diagonal": "20.3 cm (8\")", "Panel type": "IPS", "Display resolution": "1280 x 800 pixels", "Touch technology": "Multi-touch", "Touchscreen type": "Capacitive", "Processor manufacturer": "Intel", "Processor family": "Intel Atom®", "Processor model": "Z2580", "Processor cores": "2", "Processor threads": "4", "Processor boost frequency": "2 GHz", "Processor cache": "1 MB", "Processor cache type": "Smart Cache", "Graphics & IMC lithography": "32 nm", "Processor code": "SR146", "Processor lithography": "32 nm", "Processor operating modes": "32-bit", "Processor package size": "14 x 14 mm", "Stepping": "B1", "Supported instruction sets": "SSE2, SSE3, SSSE3", "Tjunction": "90 °C", "Internal memory": "2 GB", "Internal memory type": "DDR2-SDRAM", "Internal storage capacity": "16 GB", "Storage media": "Flash", "Compatible memory cards": "MicroSD (TransFlash), MicroSDHC", "Maximum memory card size": "32 GB", "Graphics card family": "Intel", "Graphics card": "HD Graphics", "Rear camera type": "Single camera", "Rear camera resolution (numeric)": "5 MP", "Front camera resolution (numeric)": "2 MP", "Top Wi-Fi standard": "Wi-Fi 4 (802.11n)", "Bluetooth version": "4.0", "Wi-Fi standards": "802.11b, 802.11g, Wi-Fi 4 (802.11n)", "USB 20 ports quantity": "0", "Micro-USB 20 ports quantity": "1", "HDMI ports quantity": "0", "Form factor": "Slate", "Product colour": "Black", "Device type": "Mobile tablet", "Platform": "Android", "Operating system installed": "Android", "Operating system version": "4.2.2", "Bundled software": "--", "Intel Smart Idle Technology version": "1.00", "Physical Address Extension (PAE)": "32 bit", "Battery capacity": "15.5 Wh", "Number of battery cells": "1", "Battery life (max)": "7.9 h", "AC adapter power": "10 W", "Width": "130 mm", "Depth": "9.5 mm", "Height": "212 mm", "Weight": "350 g", "Cables included": "AC", "Processor socket": "FC-MB4760", "Processor ARK ID": "70100"}, "attr_keys": ["AC adapter power", "Battery capacity", "Battery life (max)", "Bluetooth version", "Bundled software", "Cables included", "Compatible memory cards", "Depth", "Device type", "Display diagonal", "Display resolution", "Form factor", "Front camera resolution (numeric)", "Graphics & IMC lithography", "Graphics card", "Graphics card family", "HDMI ports quantity", "Height", "Intel Smart Idle Technology version", "Internal memory", "Internal memory type", "Internal storage capacity", "Maximum memory card size", "Micro-USB 20 ports quantity", "Number of battery cells", "Operating system installed", "Operating system version", "Panel type", "Physical Address Extension (PAE)", "Platform", "Processor ARK ID", "Processor boost frequency", "Processor cache", "Processor cache type", "Processor code", "Processor cores", "Processor family", "Processor lithography", "Processor manufacturer", "Processor model", "Processor operating modes", "Processor package size", "Processor socket", "Processor threads", "Product colour", "Rear camera resolution (numeric)", "Rear camera type", "Stepping", "Storage media", "Supported instruction sets", "Tjunction", "Top Wi-Fi standard", "Touch technology", "Touchscreen type", "USB 20 ports quantity", "Weight", "Wi-Fi standards", "Width"]}
{"id": "31823735", "title": "DELL Latitude 5179 4G Intel® Core™ m5 LTE 256 GB 27.4 cm (10.8\") 8 GB Wi-Fi 5 (802.11ac) Windows 10 Pro Black", "brand": "DELL", "description": "DELL Latitude 5179 4G Intel® Core™ m5 LTE 256 GB 27.4 cm (10.8\") 8 GB Wi-Fi 5 (802.11ac) Windows 10 Pro Black\n\n\nThe world’s most secure 2-in-1 for business. A one-two punch of flexibility and reliability, Intel® processors and optional keyboard (sold separately) make this 2-in-1 ideal for working on the go. The flexibility of two.The manageability of one. Easy fleet management: IT has the capability to manipulate BIOS settings and configure systems with ample flexibility that organizational IT infrastructures require. Tablet to laptop and back again: Effortlessly convert your tablet with the optional Latitude 11 Keyboard or Latitude 11 Slim Keyboard to instantly gain full laptop productivity and extended battery life. Packed with power: Expect high performance with the latest 6th Gen Intel® Core™ M processor (vPro) and up to 8GB memory. Government-grade security for your business. Select configurations of the Latitude 5000 Series 2-in-1 offer additional security features to enhance your protection (Coming soon). Integrated authentication: The integrated fingerprint and smartcard reader ensures the highest level of safety for your system and your business. Dell Data Protection: Count on Dell for the world’s most secure client devices, protected by comprehensive encryption, advanced authentication and malware prevention solutions. Self-encrypting drives: Dell SEDs provide hardware based encryption for stronger security—independent of the operating system and with zero impact on performance. As stunning as it is safe. Well-built beauty: Every Latitude 11 is constructed with premium materials, including magnesium alloy, and is finished off with soft-touch paint. It’s made with Corning® Concore Glass, providing 5x better surface damage resistance for thinner devices and greater durability than traditional displays. Interact with Clarity: Enjoy stunning resolution with the 10.8\" Ultrasharp™ FHD display, optimized for intuitive touch interaction. All in view: Take advantage of multi-angle viewing up to 150 degrees with optional Latitude 11 Slim Keyboard.\n\n\nKey Specifications:\n- **Other features**: Processor socket: BGA 1515; USB connector type: USB Type-A, USB Type-C; Intel segment tagging: Enterprise; Processor ARK ID: 88197\n- **Operational conditions**: Operating temperature (T-T): 0 - 35 °C; Storage temperature (T-T): -40 - 65 °C; Operating relative humidity (H-H): 10 - 90%; Storage relative humidity (H-H): 5 - 95%; Operating altitude: -15.2 - 3048 m; Non-operating altitude: -15.2 - 10668 m\n- **Weight & dimensions**: Width: 279.8 mm; Depth: 176.8 mm; Height: 14.3 mm; Weight: 760 g\n- **Power**: AC adapter power: 30 W; AC adapter input voltage: 100 - 240 V; AC adapter frequency: 50 - 60 Hz\n- **Battery**: Battery capacity: 35 Wh; Number of battery cells: 2; Battery life (max): 9.05 h\n- **Processor special features**: Intel® Turbo Boost Technology: 2.0; Intel Secure Key Technology version: 1.00; Intel Small Business Advantage (SBA) version: 1.00; Intel Smart Response Technology version: 1.00; Intel Stable Image Platform Program (SIPP) version: 1.00; Intel TSX-NI version: 1.00\n- **Software**: Platform: Windows; Operating system installed: Windows 10 Pro; Operating system architecture: 64-bit\n- **Security**: Cable lock slot type: Noble\n- **Design**: Form factor: Slate; Product colour: Black; Device type: Tablet PC\n- **Ports & interfaces**: USB 2.0 ports quantity: 0; Mini-USB 2.0 ports quantity: 0; Micro-USB 2.0 ports quantity: 0; USB 3.2 Gen 1 (3.1 Gen 1) Type-A ports quantity: 1; Mini-USB 3.2 Gen 1 (3.1 Gen 1) ports quantity: 0; HDMI ports quantity: 0; Mini HDMI ports quantity: 0; Micro HDMI ports quantity: 1; Headphone connectivity: 3.5 mm\n- **Network**: Top Wi-Fi standard: Wi-Fi 5 (802.11ac); Mobile network generation: 4G; 4G standard: LTE; Bluetooth version: 4.1; Wi-Fi standards: Wi-Fi 5 (802.11ac)\n- **Camera**: Rear camera type: Single camera; Rear camera resolution (numeric): 8 MP; Maximum video resolution: 1920 x 1080 pixels; Front camera resolution (numeric): 5 MP\n- **Storage**: Internal storage capacity: 256 GB; Storage media: SSD; Compatible memory cards: MicroSD (TransFlash), MicroSDHC, MicroSDXC\n- **Memory**: Internal memory: 8 GB; Internal memory type: LPDDR3-SDRAM; Maximum internal memory: 8 GB; Memory clock speed: 1600 MHz\n- **Processor**: Processor manufacturer: Intel; Processor family: Intel® Core™ m5; Processor model: m5-6Y57; Processor frequency: 1.1 GHz; Processor generation: 6th gen Intel® Core™ m5; Processor cores: 2; Processor threads: 4; Processor boost frequency: 2.8 GHz; Processor cache: 4 MB; Processor cache type: Smart Cache; Bus type: OPI; Graphics & IMC lithography: 14 nm; Processor code: SR2EG; Processor codename: Skylake; Processor lithography: 14 nm; Processor operating modes: 32-bit, 64-bit; Processor package size: 20 X 16.5 mm; Processor series: Intel Core m5-6Y Series; Stepping: D1; Supported instruction sets: SSE4.1, SSE4.2, AVX 2.0; Tjunction: 100 °C; Thermal Design Power (TDP): 4.5 W; PCI Express configurations: 1x2+2x1, 2x2, 1x4, 4x1\n- **Display**: Display diagonal: 27.4 cm (10.8\"); Display resolution: 1920 x 1080 pixels; Display brightness: 360 cd/m²; Touch technology: Multi-touch; Touchscreen type: Capacitive; Native aspect ratio: 16:9", "image_url": "https://images.icecat.biz/img/gallery_mediums/31823722_2544.jpg", "price": 634.5, "currency": "EUR", "categories": ["Tablets"], "attrs": {"Display diagonal": "27.4 cm (10.8\")", "Display resolution": "1920 x 1080 pixels", "Display brightness": "360 cd/m²", "Touch technology": "Multi-touch", "Touchscreen type": "Capacitive", "Native aspect ratio": "16:9", "Processor manufacturer": "Intel", "Processor family": "Intel® Core™ m5", "Processor model": "m5-6Y57", "Processor frequency": "1.1 GHz", "Processor generation": "6th gen Intel® Core™ m5", "Processor cores": "2", "Processor threads": "4", "Processor boost frequency": "2.8 GHz", "Processor cache": "4 MB", "Processor cache type": "Smart Cache", "Bus type": "OPI", "Graphics & IMC lithography": "14 nm", "Processor code": "SR2EG", "Processor codename": "Skylake", "Processor lithography": "14 nm", "Processor operating modes": "32-bit, 64-bit", "Processor package size": "20 X 16.5 mm", "Processor series": "Intel Core m5-6Y Series", "Stepping": "D1", "Supported instruction sets": "SSE4.1, SSE4.2, AVX 2.0", "Tjunction": "100 °C", "Thermal Design Power (TDP)": "4.5 W", "PCI Express configurations": "1x2+2x1, 2x2, 1x4, 4x1", "Internal memory": "8 GB", "Internal memory type": "LPDDR3-SDRAM", "Maximum internal memory": "8 GB", "Memory clock speed": "1600 MHz", "Internal storage capacity": "256 GB", "Storage media": "SSD", "Compatible memory cards": "MicroSD (TransFlash), MicroSDHC, MicroSDXC", "Rear camera type": "Single camera", "Rear camera resolution (numeric)": "8 MP", "Maximum video resolution": "1920 x 1080 pixels", "Front camera resolution (numeric)": "5 MP", "Top Wi-Fi standard": "Wi-Fi 5 (802.11ac)", "Mobile network generation": "4G", "4G standard": "LTE", "Bluetooth version": "4.1", "Wi-Fi standards": "Wi-Fi 5 (802.11ac)", "USB 20 ports quantity": "0", "Mini-USB 20 ports quantity": "0", "Micro-USB 20 ports quantity": "0", "USB 32 Gen 1 (31 Gen 1) Type-A ports quantity": "1", "Mini-USB 32 Gen 1 (31 Gen 1) ports quantity": "0", "HDMI ports quantity": "0", "Mini HDMI ports quantity": "0", "Micro HDMI ports quantity": "1", "Headphone connectivity": "3.5 mm", "Form factor": "Slate", "Product colour": "Black", "Device type": "Tablet PC", "Cable lock slot type": "Noble", "Platform": "Windows", "Operating system installed": "Windows 10 Pro", "Operating system architecture": "64-bit", "Intel® Turbo Boost Technology": "2.0", "Intel Secure Key Technology version": "1.00", "Intel Small Business Advantage (SBA) version": "1.00", "Intel Smart Response Technology version": "1.00", "Intel Stable Image Platform Program (SIPP) version": "1.00", "Intel TSX-NI version": "1.00", "Battery capacity": "35 Wh", "Number of battery cells": "2", "Battery life (max)": "9.05 h", "AC adapter power": "30 W", "AC adapter input voltage": "100 - 240 V", "AC adapter frequency": "50 - 60 Hz", "Width": "279.8 mm", "Depth": "176.8 mm", "Height": "14.3 mm", "Weight": "760 g", "Operating temperature (T-T)": "0 - 35 °C", "Storage temperature (T-T)": "-40 - 65 °C", "Operating relative humidity (H-H)": "10 - 90%", "Storage relative humidity (H-H)": "5 - 95%", "Operating altitude": "-15.2 - 3048 m", "Non-operating altitude": "-15.2 - 10668 m", "Processor socket": "BGA 1515", "USB connector type": "USB Type-A, USB Type-C", "Intel segment tagging": "Enterprise", "Processor ARK ID": "88197"}, "attr_keys": ["4G standard", "AC adapter frequency", "AC adapter input voltage", "AC adapter power", "Battery capacity", "Battery life (max)", "Bluetooth version", "Bus type", "Cable lock slot type", "Compatible memory cards", "Depth", "Device type", "Display brightness", "Display diagonal", "Display resolution", "Form factor", "Front camera resolution (numeric)", "Graphics & IMC lithography", "HDMI ports quantity", "Headphone connectivity", "Height", "Intel Secure Key Technology version", "Intel Small Business Advantage (SBA) version", "Intel Smart Response Technology version", "Intel Stable Image Platform Program (SIPP) version", "Intel TSX-NI version", "Intel segment tagging", "Intel® Turbo Boost Technology", "Internal memory", "Internal memory type", "Internal storage capacity", "Maximum internal memory", "Maximum video resolution", "Memory clock speed", "Micro HDMI ports quantity", "Micro-USB 20 ports quantity", "Mini HDMI ports quantity", "Mini-USB 20 ports quantity", "Mini-USB 32 Gen 1 (31 Gen 1) ports quantity", "Mobile network generation", "Native aspect ratio", "Non-operating altitude", "Number of battery cells", "Operating altitude", "Operating relative humidity (H-H)", "Operating system architecture", "Operating system installed", "Operating temperature (T-T)", "PCI Express configurations", "Platform", "Processor ARK ID", "Processor boost frequency", "Processor cache", "Processor cache type", "Processor code", "Processor codename", "Processor cores", "Processor family", "Processor frequency", "Processor generation", "Processor lithography", "Processor manufacturer", "Processor model", "Processor operating modes", "Processor package size", "Processor series", "Processor socket", "Processor threads", "Product colour", "Rear camera resolution (numeric)", "Rear camera type", "Stepping", "Storage media", "Storage relative humidity (H-H)", "Storage temperature (T-T)", "Supported instruction sets", "Thermal Design Power (TDP)", "Tjunction", "Top Wi-Fi standard", "Touch technology", "Touchscreen type", "USB 20 ports quantity", "USB 32 Gen 1 (31 Gen 1) Type-A ports quantity", "USB connector type", "Weight", "Wi-Fi standards", "Width"]}
{"id": "649180", "title": "Lenovo ThinkPad X60 Intel® Core™ Duo 80 GB 30.7 cm (12.1\") 1 GB Black", "brand": "Lenovo", "description": "Lenovo ThinkPad X60 Intel® Core™ Duo 80 GB 30.7 cm (12.1\") 1 GB Black\n\n\nThe Lenovo Design Advantage Designed to be the best engineered tablet notebook, the ThinkPad X60 Tablet has capabilities that allow you to use the notebook the way you need whether indoors or outdoors, with digitizer pen or touch input. - MultiTouch/MultiView display feature permits touch or pen interaction. - MultiView feature improves viewing outside and in sunlight as well as a 170° viewing angle. - X6 Tablet UltraBase provides light weight, fully-featured mobile docking solution. The ThinkPad X60 Tablet helps make easier the work that's important to you. Portability Without Compromise The Lenovo ThinkPad X60 Tablet is designed to provide the ultimate in portability without sacrificing features, performance, or battery life. Leading mobile connectivity The X60 Tablet is MIMO ready, compatible with the new and faster 802.11n Multiple-Input Multiple-Output wireless standard, as well as every other wireless options.\n\n\nKey Specifications:\n- **Other features**: Modem speed: 56 Kbit/s; Dimensions (WxDxH): 274 x 267 x 33 mm; Networking features: Ethernet, Fast Ethernet, Gigabit Ethernet; Firewire (IEEE 1394) ports: 1; Modem (RJ-11) ports: 1; CardBus PCMCIA slot type: Type II; CardBus PCMCIA slots quantity: 1; VGA (D-Sub) ports quantity: 1; HDD speed: 5400 RPM; Memory slots: 2x SO-DIMM; Modem type: V.92; Pre-installed software: Microsoft Windows XP Tablet PC Edition 2005; HDD interface: Serial ATA; Docking solution: X6 Tablet UltraBase\n- **Weight & dimensions**: Weight: 1.9 kg\n- **Battery**: Battery technology: Lithium-Ion (Li-Ion); Number of battery cells: 8; Battery life (max): 7.5 h\n- **Design**: Product colour: Black\n- **Ports & interfaces**: USB 2.0 ports quantity: 3; Ethernet LAN (RJ-45) ports: 1\n- **Audio**: Number of built-in speakers: 1\n- **Graphics**: Graphics card: GMA 950\n- **Storage**: Internal storage capacity: 80 GB\n- **Memory**: Internal memory: 1 GB; Maximum internal memory: 4 GB\n- **Processor**: Processor family: Intel® Core™ Duo; Processor front side bus: 667 MHz\n- **Display**: Display diagonal: 30.7 cm (12.1\"); Display resolution: 1024 x 768 pixels", "image_url": "https://images.icecat.biz/img/gallery_mediums/img_648701_medium_1480931768_9903_7799.jpg", "price": 670.07, "currency": "EUR", "categories": ["Tablets"], "attrs": {"Display diagonal": "30.7 cm (12.1\")", "Display resolution": "1024 x 768 pixels", "Processor family": "Intel® Core™ Duo", "Processor front side bus": "667 MHz", "Internal memory": "1 GB", "Maximum internal memory": "4 GB", "Internal storage capacity": "80 GB", "Graphics card": "GMA 950", "Number of built-in speakers": "1", "USB 20 ports quantity": "3", "Ethernet LAN (RJ-45) ports": "1", "Product colour": "Black", "Battery technology": "Lithium-Ion (Li-Ion)", "Number of battery cells": "8", "Battery life (max)": "7.5 h", "Weight": "1.9 kg", "Modem speed": "56 Kbit/s", "Dimensions (WxDxH)": "274 x 267 x 33 mm", "Networking features": "Ethernet, Fast Ethernet, Gigabit Ethernet", "Firewire (IEEE 1394) ports": "1", "Modem (RJ-11) ports": "1", "CardBus PCMCIA slot type": "Type II", "CardBus PCMCIA slots quantity": "1", "VGA (D-Sub) ports quantity": "1", "HDD speed": "5400 RPM", "Memory slots": "2x SO-DIMM", "Modem type": "V.92", "Pre-installed software": "Microsoft Windows XP Tablet PC Edition 2005", "HDD interface": "Serial ATA", "Docking solution": "X6 Tablet UltraBase"}, "attr_keys": ["Battery life (max)", "Battery technology", "CardBus PCMCIA slot type", "CardBus PCMCIA slots quantity", "Dimensions (WxDxH)", "Display diagonal", "Display resolution", "Docking solution", "Ethernet LAN (RJ-45) ports", "Firewire (IEEE 1394) ports", "Graphics card", "HDD interface", "HDD speed", "Internal memory", "Internal storage capacity", "Maximum internal memory", "Memory slots", "Modem (RJ-11) ports", "Modem speed", "Modem type", "Networking features", "Number of battery cells", "Number of built-in speakers", "Pre-installed software", "Processor family", "Processor front side bus", "Product colour", "USB 20 ports quantity", "VGA (D-Sub) ports quantity", "Weight"]}
{"id": "27199056", "title": "Samsung Galaxy Tab 4 SM-T530N 16 GB 25.6 cm (10.1\") 1.5 GB Wi-Fi 4 (802.11n) Android Black", "brand": "Samsung", "description": "Samsung Galaxy Tab 4 SM-T530N 16 GB 25.6 cm (10.1\") 1.5 GB Wi-Fi 4 (802.11n) Android Black\n\n\nInspiring Mobile Freedom in Your Life - Perfect for all ages, Samsung’s next-generation Galaxy Tab4 line offers an exceptional multimedia experience in a more premium and portable design, making it ideal for viewing or sharing content with friends and family. Rich Multimedia Experience - Available in 10.1-inch, 8.0-inch and 7.0-inch screen sizes, the Galaxy Tab4’s vivid WXGA display with a 16:10 screen ratio provides users with a brilliant viewing experience while watching videos, playing games, or reading digital contents. - With Multi Window functionality, users are able to seamlessly switch between apps and windows, as well as drag and drop contents with ease. Fun & Shareable Services* The new Galaxy Tab4 line is perfect for the whole family as it comes equipped with a number of fun and shareable services allowing users to access content and stay connected with friends wherever they are, including: - Group Play: Share and play music, documents and games with friends in realtime - Samsung Link: Share and play content across smart devices anytime, anywhere - WatchON: Watch TV shows and movies on any device, anywhere in your home or on the go. * Availability of features and functions listed above may be differed by device type or regions. Not all services will be provided. Please check product specification sheet for each product for details. Sleek & Portable Designs - The Galaxy Tab4 line all feature a textured, premium look and feel back cover. - With a slim design and weights, the Galaxy Tab4 10.1-inch, 8-inch and 7-inch models provide maximum portability while still allowing users to enjoy beautiful screens.\n\n\nKey Specifications:\n- **Weight & dimensions**: Width: 243.4 mm; Depth: 7.95 mm; Height: 176.4 mm; Weight: 487 g\n- **Media formats**: Audio formats supported: AAC, AAC+, AMR-NB, AMR-WB, eAAC+, FLAC, MP3, OGG, WMA; Video formats supported: H.263, H.264, MPEG4, VC-1, VP8, WMV7, WMV8\n- **Battery**: Battery capacity: 6800 mAh; Continuous video playback time: 10 h; Continuous audio playback time: 208 h; Browsing time (Wi-Fi): 10 h\n- **Software**: Platform: Android; Operating system installed: Android; Operating system version: 4.4\n- **Performance**: Google applications: Google Maps, Google Play, YouTube\n- **Design**: Form factor: Slate; Product colour: Black; Device type: Mobile tablet\n- **Ports & interfaces**: USB 2.0 ports quantity: 0; Micro-USB 2.0 ports quantity: 1; HDMI ports quantity: 0; Headphone connectivity: 3.5 mm\n- **Network**: Top Wi-Fi standard: Wi-Fi 4 (802.11n); Bluetooth version: 4.0; Wi-Fi standards: 802.11a, 802.11b, 802.11g\n- **Camera**: Rear camera type: Single camera; Rear camera resolution (numeric): 3 MP; Rear camera resolution: 2048 x 1536 pixels; Maximum video resolution: 1280 x 720 pixels; Video recording modes: 720p; Video capturing speed: 30 fps; Front camera resolution (numeric): 1.3 MP\n- **Storage**: Internal storage capacity: 16 GB; Storage media: Flash; Compatible memory cards: MicroSD (TransFlash); Maximum memory card size: 64 GB\n- **Memory**: Internal memory: 1.5 GB\n- **Processor**: Processor frequency: 1.2 GHz; Processor cores: 4\n- **Display**: Display diagonal: 25.6 cm (10.1\"); Panel type: TFT; Display resolution: 1280 x 800 pixels; Touch technology: Multi-touch; Touchscreen type: Capacitive; Display number of colours: 16.78 million colours", "image_url": "https://images.icecat.biz/img/norm/medium/27199056-6643.jpg", "price": 607.98, "currency": "EUR", "categories": ["Tablets"], "attrs": {"Display diagonal": "25.6 cm (10.1\")", "Panel type": "TFT", "Display resolution": "1280 x 800 pixels", "Touch technology": "Multi-touch", "Touchscreen type": "Capacitive", "Display number of colours": "16.78 million colours", "Processor frequency": "1.2 GHz", "Processor cores": "4", "Internal memory": "1.5 GB", "Internal storage capacity": "16 GB", "Storage media": "Flash", "Compatible memory cards": "MicroSD (TransFlash)", "Maximum memory card size": "64 GB", "Rear camera type": "Single camera", "Rear camera resolution (numeric)": "3 MP", "Rear camera resolution": "2048 x 1536 pixels", "Maximum video resolution": "1280 x 720 pixels", "Video recording modes": "720p", "Video capturing speed": "30 fps", "Front camera resolution (numeric)": "1.3 MP", "Top Wi-Fi standard": "Wi-Fi 4 (802.11n)", "Bluetooth version": "4.0", "Wi-Fi standards": "802.11a, 802.11b, 802.11g", "USB 20 ports quantity": "0", "Micro-USB 20 ports quantity": "1", "HDMI ports quantity": "0", "Headphone connectivity": "3.5 mm", "Form factor": "Slate", "Product colour": "Black", "Device type": "Mobile tablet", "Google applications": "Google Maps, Google Play, YouTube", "Platform": "Android", "Operating system installed": "Android", "Operating system version": "4.4", "Battery capacity": "6800 mAh", "Continuous video playback time": "10 h", "Continuous audio playback time": "208 h", "Browsing time (Wi-Fi)": "10 h", "Audio formats supported": "AAC, AAC+, AMR-NB, AMR-WB, eAAC+, FLAC, MP3, OGG, WMA", "Video formats supported": "H.263, H.264, MPEG4, VC-1, VP8, WMV7, WMV8", "Width": "243.4 mm", "Depth": "7.95 mm", "Height": "176.4 mm", "Weight": "487 g"}, "attr_keys": ["Audio formats supported", "Battery capacity", "Bluetooth version", "Browsing time (Wi-Fi)", "Compatible memory cards", "Continuous audio playback time", "Continuous video playback time", "Depth", "Device type", "Display diagonal", "Display number of colours", "Display resolution", "Form factor", "Front camera resolution (numeric)", "Google applications", "HDMI ports quantity", "Headphone connectivity", "Height", "Internal memory", "Internal storage capacity", "Maximum memory card size", "Maximum video resolution", "Micro-USB 20 ports quantity", "Operating system installed", "Operating system version", "Panel type", "Platform", "Processor cores", "Processor frequency", "Product colour", "Rear camera resolution", "Rear camera resolution (numeric)", "Rear camera type", "Storage media", "Top Wi-Fi standard", "Touch technology", "Touchscreen type", "USB 20 ports quantity", "Video capturing speed", "Video formats supported", "Video recording modes", "Weight", "Wi-Fi standards", "Width"]}
{"id": "96051379", "title": "Samsung Galaxy Tab S7 SM-T870 Qualcomm Snapdragon 256 GB 27.9 cm (11\") 8 GB Wi-Fi 6 (802.11ax) Silver", "brand": "Samsung", "description": "Samsung Galaxy Tab S7 SM-T870 Qualcomm Snapdragon 256 GB 27.9 cm (11\") 8 GB Wi-Fi 6 (802.11ax) Silver\n\n\nOur most advanced Galaxy Tab changes how you work and play Meet Galaxy Tab S7 and S7+. Work and play on the ultra smooth 120Hz display, powered by our most powerful chipset. Get a PC-like experience with the snap of a keyboard, or use the ultra low latency S Pen to write like never before. An immersive tablet experience changing the way you work and play. So smooth, you have to see it to believe it At 120Hz, the responsive display instantly reacts to what's on your screen. It intelligently adjusts the refresh rate based on your content and helps you save battery as you watch and scroll. Your favourite shows, with abrand new view Like the cinema, you get a massive screen made crystal clear with the largest Super AMOLED display on the Galaxy Tab S7+ and Quad speaker sound by AKG and Dolby Atmos. The fastest processor ever in Galaxy Tab The Qualcomm Snapdragon 865 Plus Mobile Platform is a breakthrough in processing power. The intuitive and intelligent chipset is extremely fast and powerful, with minimal lag, so it can run intense games and multitask with ease. Harness its power whenever the mood strikes. Intelligent battery to keep you going Binge-watch your favourite shows from sunrise to sunset. The biggest battery on a Galaxy Tab is built to keep you going.7 Even after all that, you don't have to power down. Power up and keep going with Fast Charging, the fastest tablet charger. The biggest leap in S Pen Completely made over for a comfortable, solid grip, S Pen also has ultra low latency so there's little lag between what you think and do. It's S Pen's biggest leap in responsiveness, giving you a true writing experience. Then when you're done, magnetically attach it to the back of your Tab. Effortless comes in 165° Take it all the way back to 165°. It's freedom you never thought you'd get from a tablet keyboard. The Book Cover Keyboard's free stop hinge lets you find your perfect angle for sending emails, blogging, studying — you name it. Incredibly thin and light, yet durable Coming in Mystic Black, Mystic Silver and Mystic Bronze hues, this design utilises an advanced dual colour anodising technique for enduring colour that's robust, yet stylish. Its exquisite aluminum textures are created by polycrystalline diamonds, with a micro-sand blasted finish soft to the touch. A powerful experience enhanced with Galaxy favourites RAM 6GB RAM to binge-watch and multitask with little lag. Storage 128GB. It's the storage of a laptop on your tablet to save all your photos and footage. External Memory Compatible with a microSD card up to 1TB if you need to store more.11 Daily Board Your smart home dashboard that lets you manage connected appliances, or use as a scheduler and memo board. Call and text on other devices A way to control your smartphone and answer calls and texts right from your tablet. Auto Hotspot One-touch tethering that turns your tablet into a Wi-Fi hub. Quick Share The ability to easily share files to nearby devices, simultaneously. Double tap to wake Your screen turns on when you double tap it.\n\n\nKey Specifications:\n- **Logistics data**: Harmonized System (HS) code: 84713000\n- **Weight & dimensions**: Width: 253.8 mm; Depth: 6.3 mm; Height: 165.3 mm; Weight: 498 g\n- **Battery**: Battery capacity: 8000 mAh; Continuous video playback time: 15 h; Continuous audio playback time: 129 h; Browsing time (Wi-Fi): 15 h\n- **Software**: Platform: Android\n- **Design**: Form factor: Slate; Product colour: Silver; Device type: Mobile tablet; Colour name: Mystic Silver\n- **Ports & interfaces**: USB 3.2 Gen 1 (3.1 Gen 1) Type-C ports quantity: 1; HDMI ports quantity: 0\n- **Network**: Top Wi-Fi standard: Wi-Fi 6 (802.11ax); Bluetooth version: 5.0; Wi-Fi standards: 802.11a, 802.11b, 802.11g, Wi-Fi 4 (802.11n), Wi-Fi 5 (802.11ac), Wi-Fi 6 (802.11ax)\n- **Camera**: Rear camera type: Dual camera; Rear camera resolution (numeric): 13 MP; Second rear camera resolution (numeric): 5 MP; Rear camera resolution: 3840 x 2160 pixels; Rear camera aperture number: 2; Second rear camera aperture number: 2.2; Digital zoom: 8x; Maximum video resolution: 3840 x 2160 pixels; Video recording modes: 720p, 1080p, 2160p; Resolution at capture speed: 1280x720@30fps, 1920x1080@30fps, 1920x1080@60fps, 3840x2160@30fps; Video capturing speed: 30 fps; Front camera resolution (numeric): 8 MP\n- **Audio**: Number of built-in speakers: 4; Number of microphones: 1; Audio system: Dolby Atmos\n- **Graphics**: Graphics card family: Adreno; Graphics card: Adreno 650\n- **Storage**: Internal storage capacity: 256 GB; Compatible memory cards: MicroSD (TransFlash); Maximum memory card size: 1 TB; User memory: 221.3 GB\n- **Memory**: Internal memory: 8 GB\n- **Processor**: Processor manufacturer: Qualcomm; Processor family: Qualcomm Snapdragon; Processor model: 865+; Processor frequency: 3.09 GHz; Processor cores: 8\n- **Display**: Display diagonal: 27.9 cm (11\"); Panel type: TFT; Display resolution: 2560 x 1600 pixels; Touchscreen type: Capacitive; Pixel density: 276 ppi; HD type: WQXGA; Native aspect ratio: 16:10; Display number of colours: 16 million colours", "image_url": "https://images.icecat.biz/img/gallery_mediums/88934245_6264222264.jpg", "price": 638.25, "currency": "EUR", "categories": ["Tablets"], "attrs": {"Display diagonal": "27.9 cm (11\")", "Panel type": "TFT", "Display resolution": "2560 x 1600 pixels", "Touchscreen type": "Capacitive", "Pixel density": "276 ppi", "HD type": "WQXGA", "Native aspect ratio": "16:10", "Display number of colours": "16 million colours", "Processor manufacturer": "Qualcomm", "Processor family": "Qualcomm Snapdragon", "Processor model": "865+", "Processor frequency": "3.09 GHz", "Processor cores": "8", "Internal memory": "8 GB", "Internal storage capacity": "256 GB", "Compatible memory cards": "MicroSD (TransFlash)", "Maximum memory card size": "1 TB", "User memory": "221.3 GB", "Graphics card family": "Adreno", "Graphics card": "Adreno 650", "Number of built-in speakers": "4", "Number of microphones": "1", "Audio system": "Dolby Atmos", "Rear camera type": "Dual camera", "Rear camera resolution (numeric)": "13 MP", "Second rear camera resolution (numeric)": "5 MP", "Rear camera resolution": "3840 x 2160 pixels", "Rear camera aperture number": "2", "Second rear camera aperture number": "2.2", "Digital zoom": "8x", "Maximum video resolution": "3840 x 2160 pixels", "Video recording modes": "720p, 1080p, 2160p", "Resolution at capture speed": "1280x720@30fps, 1920x1080@30fps, 1920x1080@60fps, 3840x2160@30fps", "Video capturing speed": "30 fps", "Front camera resolution (numeric)": "8 MP", "Top Wi-Fi standard": "Wi-Fi 6 (802.11ax)", "Bluetooth version": "5.0", "Wi-Fi standards": "802.11a, 802.11b, 802.11g, Wi-Fi 4 (802.11n), Wi-Fi 5 (802.11ac), Wi-Fi 6 (802.11ax)", "USB 32 Gen 1 (31 Gen 1) Type-C ports quantity": "1", "HDMI ports quantity": "0", "Form factor": "Slate", "Product colour": "Silver", "Device type": "Mobile tablet", "Colour name": "Mystic Silver", "Platform": "Android", "Battery capacity": "8000 mAh", "Continuous video playback time": "15 h", "Continuous audio playback time": "129 h", "Browsing time (Wi-Fi)": "15 h", "Width": "253.8 mm", "Depth": "6.3 mm", "Height": "165.3 mm", "Weight": "498 g", "Harmonized System (HS) code": "84713000"}, "attr_keys": ["Audio system", "Battery capacity", "Bluetooth version", "Browsing time (Wi-Fi)", "Colour name", "Compatible memory cards", "Continuous audio playback time", "Continuous video playback time", "Depth", "Device type", "Digital zoom", "Display diagonal", "Display number of colours", "Display resolution", "Form factor", "Front camera resolution (numeric)", "Graphics card", "Graphics card family", "HD type", "HDMI ports quantity", "Harmonized System (HS) code", "Height", "Internal memory", "Internal storage capacity", "Maximum memory card size", "Maximum video resolution", "Native aspect ratio", "Number of built-in speakers", "Number of microphones", "Panel type", "Pixel density", "Platform", "Processor cores", "Processor family", "Processor frequency", "Processor manufacturer", "Processor model", "Product colour", "Rear camera aperture number", "Rear camera resolution", "Rear camera resolution (numeric)", "Rear camera type", "Resolution at capture speed", "Second rear camera aperture number", "Second rear camera resolution (numeric)", "Top Wi-Fi standard", "Touchscreen type", "USB 32 Gen 1 (31 Gen 1) Type-C ports quantity", "User memory", "Video capturing speed", "Video recording modes", "Weight", "Wi-Fi standards", "Width"]}
{"id": "18485137", "title": "Fujitsu STYLISTIC Q702 Intel® Core™ i3 64 GB 29.5 cm (11.6\") 4 GB Wi-Fi 4 (802.11n) Windows 7 Black, Silver", "brand": "Fujitsu", "description": "Fujitsu STYLISTIC Q702 Intel® Core™ i3 64 GB 29.5 cm (11.6\") 4 GB Wi-Fi 4 (802.11n) Windows 7 Black, Silver\n\n\nThe Fujitsu STYLISTIC Q702 is the perfect choice for mobile professionals looking for high-performance without compromising on versatility. With its attachable keyboard option, this lightweight hybrid tablet PC enables easy content creation and consumption. Either use it as a tablet when traveling or attach the keyboard and convert the STYLISTIC Q702 into a traditional notebook for additional usability in the office. The 29.5 cm (11.6-inch) display with pen and finger input support offers you excellent flexibility while optional 4G/LTE completes the picture of a professional tablet. Notebook and Tablet PC in One. Benefit from ultimate versatility. With the attachable keyboard, you can turn your lightweight tablet into a traditional notebook for additional usability in business meetings or at your desk. Mobile Office on the Go A light weight, long battery runtime, ultimate connectivity as well as a robust magnesium cover for enhanced stability convert your STYLISTIC hybrid tablet into a real mobile office to support you on business trips. Ultimate Security Protect your most valuable asset - your data, with features like Fujitsu's Advanced Theft Protection, an integrated fingerprint sensor or an optional TPM module, granting you ultimate security. Content Creation Not only enjoy the STYLISTIC Q702 as a tablet to consume content, but attach the keyboard or use the touch-screen for direct pen and finger input to create valuable content. The hybrid tablet allows both, depending on the situation and your personal preferences.\n\n\nKey Specifications:\n- **Other features**: Processor socket: BGA 1023; Processor ARK ID: 65697\n- **Operational conditions**: Operating temperature (T-T): 5 - 35 °C; Operating relative humidity (H-H): 20 - 85%\n- **Weight & dimensions**: Width: 302 mm; Depth: 195 mm; Height: 12.7 mm; Weight: 850 g\n- **Power**: AC adapter power: 60 W; AC adapter input voltage: 100 - 240 V; AC adapter frequency: 50 - 60 Hz\n- **Battery**: Battery technology: Lithium-Ion (Li-Ion); Battery capacity: 3150 mAh; Battery capacity: 34 Wh; Number of battery cells: 3; Battery recharge time: 4.2 h; Battery life (max): 4.12 h\n- **Processor special features**: Intel Identity Protection Technology version: 1.00\n- **Software**: Platform: Windows; Operating system installed: Windows 7; Operating system architecture: 64-bit; Operating system version: Professional\n- **Design**: Form factor: Slate; Product colour: Black, Silver; Device type: Tablet PC\n- **Ports & interfaces**: USB 2.0 ports quantity: 1; USB 3.2 Gen 1 (3.1 Gen 1) Type-A ports quantity: 1; HDMI ports quantity: 1; Headphone connectivity: 3.5 mm\n- **Network**: Top Wi-Fi standard: Wi-Fi 4 (802.11n); Bluetooth version: 4.0; Wi-Fi standards: 802.11a, 802.11b, 802.11g\n- **Camera**: Rear camera type: Single camera; Rear camera resolution (numeric): 5 MP; Rear camera resolution: 1920 x 1080 pixels\n- **Audio**: Number of built-in speakers: 2; Audio system: Realtek ALC269\n- **Graphics**: Graphics card family: Intel; Graphics card: HD Graphics 4000\n- **Storage**: Internal storage capacity: 64 GB; Storage media: SSD; Compatible memory cards: SD, SDHC, SDXC; Maximum memory card size: 64 GB\n- **Memory**: Internal memory: 4 GB; Internal memory type: DDR3-SDRAM; Maximum internal memory: 4 GB; Memory clock speed: 1600 MHz\n- **Processor**: Processor manufacturer: Intel; Processor family: Intel® Core™ i3; Processor model: i3-3217U; Processor frequency: 1.8 GHz; Processor generation: 3rd gen Intel® Core™ i3; Processor cores: 2; Processor threads: 4; Processor cache: 3 MB; Processor cache type: Smart Cache; Motherboard chipset: Intel® QM77 Express; Bus type: DMI; CPU multiplier (bus/core ratio): 18; Graphics & IMC lithography: 22 nm; Processor code: SR0N9; Processor codename: Ivy Bridge; Processor lithography: 22 nm; Processor operating modes: 64-bit; Processor package size: 31 x 24 mm; Processor series: Intel Core i3-3200 Mobile Series; Stepping: L1; Supported instruction sets: AVX; System bus rate: 5 GT/s; Tjunction: 105 °C; Thermal Design Power (TDP): 17 W; PCI Express configurations: 1x16, 2x8, 1x8+2x4\n- **Display**: Display diagonal: 29.5 cm (11.6\"); Panel type: IPS; Display resolution: 1366 x 768 pixels; Display brightness: 400 cd/m²; Touch technology: Multi-touch; Touchscreen type: Capacitive; Native aspect ratio: 16:9", "image_url": "https://images.icecat.biz/img/norm/medium/18374898-8808.jpg", "price": 300.4, "currency": "EUR", "categories": ["Tablets"], "attrs": {"Display diagonal": "29.5 cm (11.6\")", "Panel type": "IPS", "Display resolution": "1366 x 768 pixels", "Display brightness": "400 cd/m²", "Touch technology": "Multi-touch", "Touchscreen type": "Capacitive", "Native aspect ratio": "16:9", "Processor manufacturer": "Intel", "Processor family": "Intel® Core™ i3", "Processor model": "i3-3217U", "Processor frequency": "1.8 GHz", "Processor generation": "3rd gen Intel® Core™ i3", "Processor cores": "2", "Processor threads": "4", "Processor cache": "3 MB", "Processor cache type": "Smart Cache", "Motherboard chipset": "Intel® QM77 Express", "Bus type": "DMI", "CPU multiplier (bus/core ratio)": "18", "Graphics & IMC lithography": "22 nm", "Processor code": "SR0N9", "Processor codename": "Ivy Bridge", "Processor lithography": "22 nm", "Processor operating modes": "64-bit", "Processor package size": "31 x 24 mm", "Processor series": "Intel Core i3-3200 Mobile Series", "Stepping": "L1", "Supported instruction sets": "AVX", "System bus rate": "5 GT/s", "Tjunction": "105 °C", "Thermal Design Power (TDP)": "17 W", "PCI Express configurations": "1x16, 2x8, 1x8+2x4", "Internal memory": "4 GB", "Internal memory type": "DDR3-SDRAM", "Maximum internal memory": "4 GB", "Memory clock speed": "1600 MHz", "Internal storage capacity": "64 GB", "Storage media": "SSD", "Compatible memory cards": "SD, SDHC, SDXC", "Maximum memory card size": "64 GB", "Graphics card family": "Intel", "Graphics card": "HD Graphics 4000", "Number of built-in speakers": "2", "Audio system": "Realtek ALC269", "Rear camera type": "Single camera", "Rear camera resolution (numeric)": "5 MP", "Rear camera resolution": "1920 x 1080 pixels", "Top Wi-Fi standard": "Wi-Fi 4 (802.11n)", "Bluetooth version": "4.0", "Wi-Fi standards": "802.11a, 802.11b, 802.11g", "USB 20 ports quantity": "1", "USB 32 Gen 1 (31 Gen 1) Type-A ports quantity": "1", "HDMI ports quantity": "1", "Headphone connectivity": "3.5 mm", "Form factor": "Slate", "Product colour": "Black, Silver", "Device type": "Tablet PC", "Platform": "Windows", "Operating system installed": "Windows 7", "Operating system architecture": "64-bit", "Operating system version": "Professional", "Intel Identity Protection Technology version": "1.00", "Battery technology": "Lithium-Ion (Li-Ion)", "Battery capacity": "34 Wh", "Number of battery cells": "3", "Battery recharge time": "4.2 h", "Battery life (max)": "4.12 h", "AC adapter power": "60 W", "AC adapter input voltage": "100 - 240 V", "AC adapter frequency": "50 - 60 Hz", "Width": "302 mm", "Depth": "195 mm", "Height": "12.7 mm", "Weight": "850 g", "Operating temperature (T-T)": "5 - 35 °C", "Operating relative humidity (H-H)": "20 - 85%", "Processor socket": "BGA 1023", "Processor ARK ID": "65697"}, "attr_keys": ["AC adapter frequency", "AC adapter input voltage", "AC adapter power", "Audio system", "Battery capacity", "Battery life (max)", "Battery recharge time", "Battery technology", "Bluetooth version", "Bus type", "CPU multiplier (bus/core ratio)", "Compatible memory cards", "Depth", "Device type", "Display brightness", "Display diagonal", "Display resolution", "Form factor", "Graphics & IMC lithography", "Graphics card", "Graphics card family", "HDMI ports quantity", "Headphone connectivity", "Height", "Intel Identity Protection Technology version", "Internal memory", "Internal memory type", "Internal storage capacity", "Maximum internal memory", "Maximum memory card size", "Memory clock speed", "Motherboard chipset", "Native aspect ratio", "Number of battery cells", "Number of built-in speakers", "Operating relative humidity (H-H)", "Operating system architecture", "Operating system installed", "Operating system version", "Operating temperature (T-T)", "PCI Express configurations", "Panel type", "Platform", "Processor ARK ID", "Processor cache", "Processor cache type", "Processor code", "Processor codename", "Processor cores", "Processor family", "Processor frequency", "Processor generation", "Processor lithography", "Processor manufacturer", "Processor model", "Processor operating modes", "Processor package size", "Processor series", "Processor socket", "Processor threads", "Product colour", "Rear camera resolution", "Rear camera resolution (numeric)", "Rear camera type", "Stepping", "Storage media", "Supported instruction sets", "System bus rate", "Thermal Design Power (TDP)", "Tjunction", "Top Wi-Fi standard", "Touch technology", "Touchscreen type", "USB 20 ports quantity", "USB 32 Gen 1 (31 Gen 1) Type-A ports quantity", "Weight", "Wi-Fi standards", "Width"]}
{"id": "33100527", "title": "HP ElitePad 1000 G2 Healthcare Intel Atom® 128 GB 25.6 cm (10.1\") 4 GB Wi-Fi 4 (802.11n) Windows 8.1 Pro Silver", "brand": "HP", "description": "HP ElitePad 1000 G2 Healthcare Intel Atom® 128 GB 25.6 cm (10.1\") 4 GB Wi-Fi 4 (802.11n) Windows 8.1 Pro Silver\n\n\nIntegrate workflows, access and update healthcare information systems, improve caregiver productivity, and enhance patient interaction with the HP ElitePad 1000 Healthcare Tablet, a Windows 10 solution designed in tandem with healthcare and hospital professionals. From mobile executives to field technicians, you’ll benefit from an assortment of industry-specific software and hardware options. Ready for healthcare - Use this durable, lightweight solution throughout your clinical environment. The shell has been treated with an antimicrobial preservative to protect the outer casing2 from degradation. Assist with regulatory requirements - Help keep patient data secure with a certified smart card reader; HP Client Security, HP BIOS Protection, and Trusted Platform Module (TPM) and full disk encryption. Gain 360-degree quality assurance - Help reduce the risk of medical errors by using the 2D barcode reader (select configurations) to validate personnel and patients and catalogue and administer medication. Dictate accurately with built-in noise cancelling software. Enable clinical workflow flexibility - Create the best solution for your environment with a suite of optional accessories. Use the tablet pen to enable data input on the move or a docking station to create a desktop-like environment when you’re at a desk or nurse’s station.\n\n\nKey Specifications:\n- **Other features**: Processor socket: BGA 1380; Processor ARK ID: 80267\n- **Weight & dimensions**: Width: 207.5 mm; Depth: 278 mm; Height: 20 mm; Weight: 1.1 kg\n- **Power**: AC adapter power: 10 W\n- **Battery**: Battery technology: Lithium Polymer (LiPo); Battery capacity: 4000 mAh; Battery capacity: 30 Wh; Number of battery cells: 2; Battery life (max): 12.5 h\n- **Software**: Platform: Windows; Operating system installed: Windows 8.1 Pro\n- **Performance**: Country of origin: China\n- **Design**: Form factor: Slate; Product colour: Silver; Device type: Tablet PC\n- **Ports & interfaces**: USB 2.0 ports quantity: 0; USB 3.2 Gen 1 (3.1 Gen 1) Type-A ports quantity: 1; HDMI ports quantity: 1; Headphone connectivity: 3.5 mm\n- **Network**: Top Wi-Fi standard: Wi-Fi 4 (802.11n); Bluetooth version: 4.0\n- **Camera**: Rear camera type: Single camera; Rear camera resolution (numeric): 8 MP; Flash type: LED; Front camera resolution (numeric): 2.1 MP\n- **Audio**: Number of built-in speakers: 2\n- **Graphics**: Graphics card family: Intel; Graphics card: HD Graphics\n- **Storage**: Internal storage capacity: 128 GB; Storage media: SSD; Compatible memory cards: Not supported\n- **Memory**: Internal memory: 4 GB; Internal memory type: LPDDR3-SDRAM; Memory clock speed: 1067 MHz\n- **Processor**: Processor manufacturer: Intel; Processor family: Intel Atom®; Processor model: Z3795; Processor frequency: 1.59 GHz; Processor cores: 4; Processor threads: 4; Processor boost frequency: 2.39 GHz; Processor cache: 2 MB; Processor cache type: L2; Graphics & IMC lithography: 22 nm; Processor code: SR1SK; Processor codename: Bay Trail; Processor lithography: 22 nm; Processor operating modes: 32-bit, 64-bit; Processor package size: 17 x 17 mm; Processor series: Intel Atom Z3700 Series; Scenario Design Power (SDP): 2 W; Stepping: C0; Thermal Design Power (TDP): 2 W\n- **Display**: Display diagonal: 25.6 cm (10.1\"); Display resolution: 1920 x 1200 pixels; Touch technology: Multi-touch; Touchscreen type: Capacitive", "image_url": "https://images.icecat.biz/img/gallery_mediums/8adf55e703ba1f21e9fcb33413dce97b.jpg", "price": 535.29, "currency": "EUR", "categories": ["Tablets"], "attrs": {"Display diagonal": "25.6 cm (10.1\")", "Display resolution": "1920 x 1200 pixels", "Touch technology": "Multi-touch", "Touchscreen type": "Capacitive", "Processor manufacturer": "Intel", "Processor family": "Intel Atom®", "Processor model": "Z3795", "Processor frequency": "1.59 GHz", "Processor cores": "4", "Processor threads": "4", "Processor boost frequency": "2.39 GHz", "Processor cache": "2 MB", "Processor cache type": "L2", "Graphics & IMC lithography": "22 nm", "Processor code": "SR1SK", "Processor codename": "Bay Trail", "Processor lithography": "22 nm", "Processor operating modes": "32-bit, 64-bit", "Processor package size": "17 x 17 mm", "Processor series": "Intel Atom Z3700 Series", "Scenario Design Power (SDP)": "2 W", "Stepping": "C0", "Thermal Design Power (TDP)": "2 W", "Internal memory": "4 GB", "Internal memory type": "LPDDR3-SDRAM", "Memory clock speed": "1067 MHz", "Internal storage capacity": "128 GB", "Storage media": "SSD", "Compatible memory cards": "Not supported", "Graphics card family": "Intel", "Graphics card": "HD Graphics", "Number of built-in speakers": "2", "Rear camera type": "Single camera", "Rear camera resolution (numeric)": "8 MP", "Flash type": "LED", "Front camera resolution (numeric)": "2.1 MP", "Top Wi-Fi standard": "Wi-Fi 4 (802.11n)", "Bluetooth version": "4.0", "USB 20 ports quantity": "0", "USB 32 Gen 1 (31 Gen 1) Type-A ports quantity": "1", "HDMI ports quantity": "1", "Headphone connectivity": "3.5 mm", "Form factor": "Slate", "Product colour": "Silver", "Device type": "Tablet PC", "Country of origin": "China", "Platform": "Windows", "Operating system installed": "Windows 8.1 Pro", "Battery technology": "Lithium Polymer (LiPo)", "Battery capacity": "30 Wh", "Number of battery cells": "2", "Battery life (max)": "12.5 h", "AC adapter power": "10 W", "Width": "207.5 mm", "Depth": "278 mm", "Height": "20 mm", "Weight": "1.1 kg", "Processor socket": "BGA 1380", "Processor ARK ID": "80267"}, "attr_keys": ["AC adapter power", "Battery capacity", "Battery life (max)", "Battery technology", "Bluetooth version", "Compatible memory cards", "Country of origin", "Depth", "Device type", "Display diagonal", "Display resolution", "Flash type", "Form factor", "Front camera resolution (numeric)", "Graphics & IMC lithography", "Graphics card", "Graphics card family", "HDMI ports quantity", "Headphone connectivity", "Height", "Internal memory", "Internal memory type", "Internal storage capacity", "Memory clock speed", "Number of battery cells", "Number of built-in speakers", "Operating system installed", "Platform", "Processor ARK ID", "Processor boost frequency", "Processor cache", "Processor cache type", "Processor code", "Processor codename", "Processor cores", "Processor family", "Processor frequency", "Processor lithography", "Processor manufacturer", "Processor model", "Processor operating modes", "Processor package size", "Processor series", "Processor socket", "Processor threads", "Product colour", "Rear camera resolution (numeric)", "Rear camera type", "Scenario Design Power (SDP)", "Stepping", "Storage media", "Thermal Design Power (TDP)", "Top Wi-Fi standard", "Touch technology", "Touchscreen type", "USB 20 ports quantity", "USB 32 Gen 1 (31 Gen 1) Type-A ports quantity", "Weight", "Width"]}
{"id": "55653224", "title": "ASUS ZenPad 8.0 Z581KL-1A039A tablet 4G Qualcomm Snapdragon LTE 16 GB 20.3 cm (8\") 2 GB Wi-Fi 5 (802.11ac) Android 6.0 Black", "brand": "ASUS", "description": "ASUS ZenPad 8.0 Z581KL-1A039A tablet 4G Qualcomm Snapdragon LTE 16 GB 20.3 cm (8\") 2 GB Wi-Fi 5 (802.11ac) Android 6.0 Black\n\n\nCinematic entertainment with 2K IPS display ASUS ZenPad 3 8.0 is a premium 8-inch tablet with vivid 2K (2048 x 1536 resolution) visuals and cinematic audio for truly immersive entertainment. Its fashion-inspired design with a brushed metallic finish and detailed concentric-circle button provides a sublime level of elegance and beauty, while a super-fast hexa-core processor and 4GB RAM delivers powerful performance in any usage scenario. Coupled with the all-new ZenUI 3.0 interface with added intelligence, ZenPad 3 8.0 delivers an incredible tablet experience like no other. Design Fashion-inspired design ASUS ZenPad 3 8.0 has a modern contemporary design that turns heads. Its forged aluminum body weighs just 320g, and has a premium leather-patterned rear cover that feels great to the touch. Craftsmanship Metallic finish with concentric-circle button ASUS ZenPad 3 8.0 has a brushed metallic finish and a finely-detailed concentric-circle button that reflects a balance of beauty and strength. Its exquisite surface is achieved thanks to a hyper-fine sanding process, before being polished to a smooth anodized finish. Multimedia It’s all in the details ASUS ZenPad 3 8.0 delivers mobile entertainment like you’ve never experienced. Its incredible 8-inch 2K (2048 x 1536 resolution) IPS display features wide 178-degree viewing angles and exclusive ASUS VisualMaster and ASUS Tru2Life+ technologies for a cinematic experience. TV-grade optimization ZenPad 3 8.0 has a dedicated display processor like those found in the latest high-end TVs. We call this ASUS Tru2Life+ technology, and with good reason. Every pixel is optimized to deliver incredible contrast and sharpness for beautiful, true-to-life images. Tru2Life+ also has motion-estimation and motion-compensation (MEMC) algorithms for smooth, blur-free video that doesn’t judder. Intelligent contrast Intelligent contrast enhancement analyzes and optimizes each pixel in an image before it is reproduced, rendering more detail in the highlights and shadows to reveal the true beauty in your pictures. Sharpness optimization Dramatically-enhanced detail for sharper, more lifelike images. SonicMaster DTS headphone X ASUS SonicMaster technology gives you higher volumes, improved audio delivery and additional audio effects. ASUS ZenPad 3 8.0 has dual front speakers for higher volume levels. And for full-immersion, DTS Headphone:X™ delivers an immersive, cinematic 7.1-channel surround sound experience straight to your headphones. Performance Supercharged gaming power Beneath the beautiful exterior of ASUS ZenPad 3 8.0 lies a performance beast. With a super-fast hexa-core processor, 4GB RAM and Adreno 510 GPU, ASUS ZenPad 3 8.0 handles the latest games with ease and lets you blast through productivity tasks. A power revolution A high-capacity 4650mAh battery gives you almost 11 hours* of battery life to keep the entertainment going. PixelMaster Capture the magic of the moment The 8MP PixelMaster camera captures stunning, high-resolution photos with zero shutter lag. Its industry-leading Low Light mode employs pixel-merging technology to capture up to 400% brighter photos at night or in low-light environments, without the need for a flash. ZenUI New interface with added intelligence Incredible hardware demands spectacular software — and that’s where ZenUI 3.0 comes in to brighten your mobile experience, improve productivity and make everyday life just that little bit more fun. Weather updates come with real-time animations, or check the time through the stylish clock widget. Feel the depth of parallax scrolling as you swipe through your apps, and appreciate how the subtle blurry effect keeps your focus on the foreground. ZenUI 3.0 isn’t just an interface — it’s the best friend who accompanies you everywhere. ASUS Zen Clutch A premium fashion accessory ASUS Zen Clutch is a tailor-made fashion accessory for your ASUS ZenPad 3 8.0. This stylish cover protects ZenPad without adding bulk to its compact, lightweight design. Inside, Zen Clutch incudes convenient slots for your ID and credit cards.\n\n\nKey Specifications:\n- **Weight & dimensions**: Width: 136.4 mm; Depth: 205.4 mm; Height: 7.57 mm; Weight: 320 g\n- **Battery**: Battery technology: Lithium Polymer (LiPo); Battery capacity: 4680 mAh; Battery capacity: 18 Wh; Battery life (max): 11 h\n- **Software**: Platform: Android; Operating system installed: Android 6.0\n- **Design**: Form factor: Slate; Product colour: Black; Device type: Mobile tablet\n- **Ports & interfaces**: USB 3.2 Gen 1 (3.1 Gen 1) Type-C ports quantity: 1; HDMI ports quantity: 0\n- **Network**: Top Wi-Fi standard: Wi-Fi 5 (802.11ac); Mobile network generation: 4G; 3G standards: UMTS; 4G standard: LTE; Bluetooth version: 4.1; Wi-Fi standards: 802.11a, 802.11b, 802.11g, Wi-Fi 4 (802.11n), Wi-Fi 5 (802.11ac); 3G bands supported: 850,900,2100 MHz\n- **Camera**: Rear camera type: Single camera; Rear camera resolution (numeric): 8 MP; Video recording modes: 1080p; Front camera resolution (numeric): 2 MP\n- **Audio**: Number of built-in speakers: 2\n- **Graphics**: Graphics card family: Adreno; Graphics card: Adreno 510\n- **Storage**: Internal storage capacity: 16 GB; Storage media: Flash; Compatible memory cards: MicroSD (TransFlash), SDXC; Maximum memory card size: 128 GB\n- **Memory**: Internal memory: 2 GB; Internal memory type: LPDDR3-SDRAM\n- **Processor**: Processor family: Qualcomm Snapdragon; Processor model: MSM8956; Processor frequency: 1.8 GHz; Processor cores: 2+4\n- **Display**: Display diagonal: 20.3 cm (8\"); Panel type: IPS; Display resolution: 2048 x 1536 pixels; Touch technology: Multi-touch", "image_url": "https://images.icecat.biz/img/gallery_mediums/36541620_8698022851.jpg", "price": 357.52, "currency": "EUR", "categories": ["Tablets"], "attrs": {"Display diagonal": "20.3 cm (8\")", "Panel type": "IPS", "Display resolution": "2048 x 1536 pixels", "Touch technology": "Multi-touch", "Processor family": "Qualcomm Snapdragon", "Processor model": "MSM8956", "Processor frequency": "1.8 GHz", "Processor cores": "2+4", "Internal memory": "2 GB", "Internal memory type": "LPDDR3-SDRAM", "Internal storage capacity": "16 GB", "Storage media": "Flash", "Compatible memory cards": "MicroSD (TransFlash), SDXC", "Maximum memory card size": "128 GB", "Graphics card family": "Adreno", "Graphics card": "Adreno 510", "Number of built-in speakers": "2", "Rear camera type": "Single camera", "Rear camera resolution (numeric)": "8 MP", "Video recording modes": "1080p", "Front camera resolution (numeric)": "2 MP", "Top Wi-Fi standard": "Wi-Fi 5 (802.11ac)", "Mobile network generation": "4G", "3G standards": "UMTS", "4G standard": "LTE", "Bluetooth version": "4.1", "Wi-Fi standards": "802.11a, 802.11b, 802.11g, Wi-Fi 4 (802.11n), Wi-Fi 5 (802.11ac)", "3G bands supported": "850,900,2100 MHz", "USB 32 Gen 1 (31 Gen 1) Type-C ports quantity": "1", "HDMI ports quantity": "0", "Form factor": "Slate", "Product colour": "Black", "Device type": "Mobile tablet", "Platform": "Android", "Operating system installed": "Android 6.0", "Battery technology": "Lithium Polymer (LiPo)", "Battery capacity": "18 Wh", "Battery life (max)": "11 h", "Width": "136.4 mm", "Depth": "205.4 mm", "Height": "7.57 mm", "Weight": "320 g"}, "attr_keys": ["3G bands supported", "3G standards", "4G standard", "Battery capacity", "Battery life (max)", "Battery technology", "Bluetooth version", "Compatible memory cards", "Depth", "Device type", "Display diagonal", "Display resolution", "Form factor", "Front camera resolution (numeric)", "Graphics card", "Graphics card family", "HDMI ports quantity", "Height", "Internal memory", "Internal memory type", "Internal storage capacity", "Maximum memory card size", "Mobile network generation", "Number of built-in speakers", "Operating system installed", "Panel type", "Platform", "Processor cores", "Processor family", "Processor frequency", "Processor model", "Product colour", "Rear camera resolution (numeric)", "Rear camera type", "Storage media", "Top Wi-Fi standard", "Touch technology", "USB 32 Gen 1 (31 Gen 1) Type-C ports quantity", "Video recording modes", "Weight", "Wi-Fi standards", "Width"]}
