{"id": "4718505", "title": "Vogel's PHW 100 M TV mount/stand Black", "brand": "Vogel's", "description": "Vogel's PHW 100 M TV mount/stand Black\n\n\nEnjoy your LCD/Plasma TV mounted (very) flat to the wall, and free up space. The FLAT MEDIUM wall mount from Physix is suitable for TV's from 26'' to 37'' weighing up to 30 kg. This universal support is suitable for almost all LCD/Plasma TV brands (use our MOUNT MATCHER to find exactly the right mount size for your TV). It comes with easy mounting instructions, as well as all the screws and wall plugs you might need. The Lock Release feature clicks your TV to the wall, and ensures a secure & safe connection between the TV and the wall mount.\n\n\nKey Specifications:\n- **Other features**: Screen size compatibility: 37\n- **Design**: Product colour: Black; Housing material: Aluminium, Plastic\n- **Mounting**: Mounting type: Wall; Maximum weight capacity: 30 kg", "image_url": "https://images.icecat.biz/img/gallery_mediums/img_4718505_medium_1481123657_2034_23752.jpg", "price": 53.48, "currency": "EUR", "categories": ["TV Mounts & Stands"], "attrs": {"Mounting type": "Wall", "Maximum weight capacity": "30 kg", "Product colour": "Black", "Housing material": "Aluminium, Plastic", "Screen size compatibility": "37"}, "attr_keys": ["Housing material", "Maximum weight capacity", "Mounting type", "Product colour", "Screen size compatibility"]}
{"id": "103154450", "title": "Hama 00118083 TV mount/stand 165.1 cm (65\") Black, White", "brand": "Hama", "description": "Hama 00118083 TV mount/stand 165.1 cm (65\") Black, White\n\n\nSofa, bed, kitchen or floor - thanks to this wall bracket you can move your flat screen TV in any position. It perfectly blends in with almost any home design so that you are guaranteed to enjoy watching TV. - Easy-Fix system for simple and fully adjustable orientation of your TV - The drilling template means easy marking of the drill holes without having to hold the bracket up against the wall - If the TV bracket has been mounted slightly at an angle on the wall, the position of the TV can be corrected by a few degrees horizontally - Make a safe choice with our tested safety and 10-year warranty: exacting stress, stability and functional tests guarantee high quality standards - Everything included: with the diverse mounting accessories, including high-quality Fischer plugs, you can get started straight away - Perfectly matched to the background: This TV wall bracket with wall plate and support arms in white and TV mounting plate in black matches the room design and TV colour\n\n\nKey Specifications:\n- **Weight & dimensions**: Width: 430 mm; Height: 418 mm\n- **Design**: Product colour: Black, White; Housing material: Steel\n- **Ergonomics**: Tilt angle range: -15 - 15°; Swivel angle: 180°; Angle of rotation: 6°; Distance to the wall (max): 42.5 cm; Distance to the wall (min): 9 cm\n- **Mounting**: Number of displays supported: 1; Maximum screen size: 165.1 cm (65\"); Mounting type: Wall; Maximum weight capacity: 35 kg; Minimum VESA mount: 100 x 100 mm; Maximum VESA mount: 400 x 400 mm; Minimum screen size: 81.3 cm (32\"); Panel mounting interface: 100 x 100,100 x 150,100 x 200,200 x 100,200 x 200,200 x 300,300 x 100,300 x 200,300 x 400,300 x 300,400 x 200,400 x 400,400 x 300", "image_url": "https://images.icecat.biz/img/gallery_mediums/103154450_0230971335.jpg", "price": 39.86, "currency": "EUR", "categories": ["TV Mounts & Stands"], "attrs": {"Number of displays supported": "1", "Maximum screen size": "165.1 cm (65\")", "Mounting type": "Wall", "Maximum weight capacity": "35 kg", "Minimum VESA mount": "100 x 100 mm", "Maximum VESA mount": "400 x 400 mm", "Minimum screen size": "81.3 cm (32\")", "Panel mounting interface": "100 x 100,100 x 150,100 x 200,200 x 100,200 x 200,200 x 300,300 x 100,300 x 200,300 x 400,300 x 300,400 x 200,400 x 400,400 x 300", "Tilt angle range": "-15 - 15°", "Swivel angle": "180°", "Angle of rotation": "6°", "Distance to the wall (max)": "42.5 cm", "Distance to the wall (min)": "9 cm", "Product colour": "Black, White", "Housing material": "Steel", "Width": "430 mm", "Height": "418 mm"}, "attr_keys": ["Angle of rotation", "Distance to the wall (max)", "Distance to the wall (min)", "Height", "Housing material", "Maximum VESA mount", "Maximum screen size", "Maximum weight capacity", "Minimum VESA mount", "Minimum screen size", "Mounting type", "Number of displays supported", "Panel mounting interface", "Product colour", "Swivel angle", "Tilt angle range", "Width"]}
{"id": "106733801", "title": "Chief PCS2398 TV mount/stand 180.3 cm (71\") Black", "brand": "Chief", "description": "Chief PCS2398 TV mount/stand 180.3 cm (71\") Black\n\n\nLarge Flat Panel Ceiling Mount with Angled Column (without interface) Series\n\n\nKey Specifications:\n- **Design**: Product colour: Black\n- **Ergonomics**: Tilt angle range: -20 - 5°\n- **Mounting**: Number of displays supported: 1; Maximum screen size: 180.3 cm (71\"); Mounting type: Ceiling; Maximum weight capacity: 90.7 kg; Minimum VESA mount: 200 x 200 mm; Maximum VESA mount: 800 x 400 mm; Minimum screen size: 106.7 cm (42\")", "image_url": "https://images.icecat.biz/img/gallery_mediums/img_5418997_medium_1481188403_6018_8183.jpg", "price": 61.55, "currency": "EUR", "categories": ["TV Mounts & Stands"], "attrs": {"Number of displays supported": "1", "Maximum screen size": "180.3 cm (71\")", "Mounting type": "Ceiling", "Maximum weight capacity": "90.7 kg", "Minimum VESA mount": "200 x 200 mm", "Maximum VESA mount": "800 x 400 mm", "Minimum screen size": "106.7 cm (42\")", "Tilt angle range": "-20 - 5°", "Product colour": "Black"}, "attr_keys": ["Maximum VESA mount", "Maximum screen size", "Maximum weight capacity", "Minimum VESA mount", "Minimum screen size", "Mounting type", "Number of displays supported", "Product colour", "Tilt angle range"]}
{"id": "77667327", "title": "ARCTIC TV Flex M Flat Full-Motion TV Wall Mount for medium sized TVs", "brand": "ARCTIC", "description": "ARCTIC TV Flex M Flat Full-Motion TV Wall Mount for medium sized TVs\n\n\nThe TV Flex M full-motion wall mount enhances the viewing capabilities of flatscreen TVs. Strong, safe, and fully articulated – maximum flexibility makes it easy to find the perfect screen position. High quality steel construction with a lock system stably and securely supports screens from 23”– 55”, up to 30 kg, and is suitable for nearly all VESA standard flat screen TVs. Whether flush against the wall or extended to almost 50 cm, the TV and bracket fit seamlessly into any interior design style.\n\n\nKey Specifications:\n- **Logistics data**: Harmonized System (HS) code: 85299097\n- **Weight & dimensions**: Weight: 3.9 kg\n- **Packaging content**: Number of washers included: 7; Number of screws: 19\n- **Design**: Product colour: Black; Housing material: Aluminium, Steel; Certification: CE\n- **Ergonomics**: Tilt angle range: -15 - 15°; Swivel angle: 180°; Angle of rotation: 360°; Distance to the wall (max): 49.8 cm; Distance to the wall (min): 4.1 cm\n- **Mounting**: Number of displays supported: 1; Maximum screen size: 139.7 cm (55\"); Mounting type: Wall; Maximum weight capacity: 30 kg; Minimum VESA mount: 50 x 50 mm; Maximum VESA mount: 400 x 400 mm; Minimum screen size: 58.4 cm (23\"); Panel mounting interface: 50 x 50,75 x 75,100 x 100,200 x 100,200 x 200,300 x 300,400 x 200,400 x 400", "image_url": "https://images.icecat.biz/img/gallery_mediums/77667327_1041967828.jpg", "price": 57.5, "currency": "EUR", "categories": ["TV Mounts & Stands"], "attrs": {"Number of displays supported": "1", "Maximum screen size": "139.7 cm (55\")", "Mounting type": "Wall", "Maximum weight capacity": "30 kg", "Minimum VESA mount": "50 x 50 mm", "Maximum VESA mount": "400 x 400 mm", "Minimum screen size": "58.4 cm (23\")", "Panel mounting interface": "50 x 50,75 x 75,100 x 100,200 x 100,200 x 200,300 x 300,400 x 200,400 x 400", "Tilt angle range": "-15 - 15°", "Swivel angle": "180°", "Angle of rotation": "360°", "Distance to the wall (max)": "49.8 cm", "Distance to the wall (min)": "4.1 cm", "Product colour": "Black", "Housing material": "Aluminium, Steel", "Certification": "CE", "Number of washers included": "7", "Number of screws": "19", "Weight": "3.9 kg", "Harmonized System (HS) code": "85299097"}, "attr_keys": ["Angle of rotation", "Certification", "Distance to the wall (max)", "Distance to the wall (min)", "Harmonized System (HS) code", "Housing material", "Maximum VESA mount", "Maximum screen size", "Maximum weight capacity", "Minimum VESA mount", "Minimum screen size", "Mounting type", "Number of displays supported", "Number of screws", "Number of washers included", "Panel mounting interface", "Product colour", "Swivel angle", "Tilt angle range", "Weight"]}
{"id": "2121227", "title": "Chief Flat Panel Custom Interface Bracket Black", "brand": "Chief", "description": "Chief Flat Panel Custom Interface Bracket Black\n\n\nCustom interface bracket compatible with all M-Series Q-Latch mounts, and the JWD210, JWS210 and JWP210.\n\n\nKey Specifications:\n- **Other features**: Screen size compatibility: 30\n- **Design**: Product colour: Black\n- **Mounting**: Mounting type: Wall", "image_url": "https://images.icecat.biz/img/gallery_mediums/img_2121227_medium_1481027631_3402_12184.jpg", "price": 44.99, "currency": "EUR", "categories": ["TV Mounts & Stands"], "attrs": {"Mounting type": "Wall", "Product colour": "Black", "Screen size compatibility": "30"}, "attr_keys": ["Mounting type", "Product colour", "Screen size compatibility"]}
{"id": "113229719", "title": "Hama 00220808 TV mount/stand 190.5 cm (75\") Black", "brand": "Hama", "description": "Hama 00220808 TV mount/stand 190.5 cm (75\") Black\n\n\n10-year warranty 10-year warranty: a warranty promise on longevity that goes far beyond the statutory guarantee Tested quality Make a safe choice with our tested safety: exacting stress, stability and functional tests guarantee high quality standards Easy-Fix system Easy-Fix system for simple and fully adjustable orientation of your TV Includes mounting material Everything included: with the diverse mounting accessories, including high-quality Fischer plugs, you can get started straight away FSC FSC-certified: the paper and cardboard used in our packaging comes from sustainable forest management - enabling us to take a resources-sparing approach to the raw material of wood Plastic-free Packaging with a clear conscience: our packaging is 100% plastic-free, enabling us to reduce plastic waste and increase its recyclability\n\n\nKey Specifications:\n- **Weight & dimensions**: Width: 445 mm; Depth (min): 10.5 cm\n- **Technical details**: Quantity per pack: 1 pc(s)\n- **Design**: Product colour: Black; Housing material: Metal\n- **Ergonomics**: Tilt angle range: -15 - 5°; Swivel angle: 0°; Angle of rotation: 0°; Distance to the wall (max): 5.2 cm; Distance to the wall (min): 5.2 cm\n- **Mounting**: Maximum screen size: 190.5 cm (75\"); Mounting type: Wall; Maximum weight capacity: 40 kg; Minimum VESA mount: 50 x 50 mm; Maximum VESA mount: 400 x 400 mm; Minimum screen size: 81.3 cm (32\"); Panel mounting interface: 50 x 50,75 x 75,100 x 100,200 x 100,200 x 200,200 x 300,300 x 400,300 x 300,300 x 100,300 x 200,400 x 200,400 x 400,400 x 300", "image_url": "https://images.icecat.biz/img/gallery_mediums/370c8af7cdb36615f8b71dc3a55c7dd5.jpg", "price": 46.17, "currency": "EUR", "categories": ["TV Mounts & Stands"], "attrs": {"Maximum screen size": "190.5 cm (75\")", "Mounting type": "Wall", "Maximum weight capacity": "40 kg", "Minimum VESA mount": "50 x 50 mm", "Maximum VESA mount": "400 x 400 mm", "Minimum screen size": "81.3 cm (32\")", "Panel mounting interface": "50 x 50,75 x 75,100 x 100,200 x 100,200 x 200,200 x 300,300 x 400,300 x 300,300 x 100,300 x 200,400 x 200,400 x 400,400 x 300", "Tilt angle range": "-15 - 5°", "Swivel angle": "0°", "Angle of rotation": "0°", "Distance to the wall (max)": "5.2 cm", "Distance to the wall (min)": "5.2 cm", "Product colour": "Black", "Housing material": "Metal", "Quantity per pack": "1 pc(s)", "Width": "445 mm", "Depth (min)": "10.5 cm"}, "attr_keys": ["Angle of rotation", "Depth (min)", "Distance to the wall (max)", "Distance to the wall (min)", "Housing material", "Maximum VESA mount", "Maximum screen size", "Maximum weight capacity", "Minimum VESA mount", "Minimum screen size", "Mounting type", "Panel mounting interface", "Product colour", "Quantity per pack", "Swivel angle", "Tilt angle range", "Width"]}
{"id": "5419105", "title": "Chief MWR6045B TV mount/stand Black", "brand": "Chief", "description": "Chief MWR6045B TV mount/stand Black\n\n\nProvides extended viewing angles for flat panel TVs and monitors. - Easily installs on 16\" center studs - Provides full extension while remaining low profile in the home position - Centris Technolgoy provides fingertip tilt adjustments - CableTrac System provides a fast and effective way to route cables - Swivel up to 90° left or right (depending upon screen size) - Integrated lateral shift 6\" left and right (ships shifted 2.5\" to the left) - Mounting guides provided for a hassle-free installation - Q-Latch Mounting System secures flat panel to mount with a latching flag - Screen can be installed in portrait or landscape orientation\n\n\nKey Specifications:\n- **Other features**: Screen size compatibility: 762 - 1397 mm (30 - 55\")\n- **Weight & dimensions**: Width: 600 mm; Depth: 86 mm; Height: 457 mm\n- **Design**: Product colour: Black; Housing material: Metal\n- **Ergonomics**: Tilt angle range: -15 - 5°; Swivel angle range: 0 - 90°\n- **Mounting**: Mounting type: Wall; Maximum weight capacity: 57 kg", "image_url": "https://images.icecat.biz/img/gallery_mediums/img_5419104_medium_1481188412_8013_8183.jpg", "price": 38.21, "currency": "EUR", "categories": ["TV Mounts & Stands"], "attrs": {"Mounting type": "Wall", "Maximum weight capacity": "57 kg", "Tilt angle range": "-15 - 5°", "Swivel angle range": "0 - 90°", "Product colour": "Black", "Housing material": "Metal", "Width": "600 mm", "Depth": "86 mm", "Height": "457 mm", "Screen size compatibility": "762 - 1397 mm (30 - 55\")"}, "attr_keys": ["Depth", "Height", "Housing material", "Maximum weight capacity", "Mounting type", "Product colour", "Screen size compatibility", "Swivel angle range", "Tilt angle range", "Width"]}
{"id": "106733774", "title": "Chief PCS2182 TV mount/stand 180.3 cm (71\") Black", "brand": "Chief", "description": "Chief PCS2182 TV mount/stand 180.3 cm (71\") Black\n\n\nLarge Flat Panel Ceiling Mount with Angled Column (without interface) Series\n\n\nKey Specifications:\n- **Design**: Product colour: Black\n- **Ergonomics**: Tilt angle range: -20 - 5°\n- **Mounting**: Number of displays supported: 1; Maximum screen size: 180.3 cm (71\"); Mounting type: Ceiling; Maximum weight capacity: 90.7 kg; Minimum VESA mount: 200 x 200 mm; Maximum VESA mount: 800 x 400 mm; Minimum screen size: 106.7 cm (42\")", "image_url": "https://images.icecat.biz/img/gallery_mediums/img_5418997_medium_1481188403_6018_8183.jpg", "price": 56.9, "currency": "EUR", "categories": ["TV Mounts & Stands"], "attrs": {"Number of displays supported": "1", "Maximum screen size": "180.3 cm (71\")", "Mounting type": "Ceiling", "Maximum weight capacity": "90.7 kg", "Minimum VESA mount": "200 x 200 mm", "Maximum VESA mount": "800 x 400 mm", "Minimum screen size": "106.7 cm (42\")", "Tilt angle range": "-20 - 5°", "Product colour": "Black"}, "attr_keys": ["Maximum VESA mount", "Maximum screen size", "Maximum weight capacity", "Minimum VESA mount", "Minimum screen size", "Mounting type", "Number of displays supported", "Product colour", "Tilt angle range"]}
{"id": "5418651", "title": "Chief PWR2540S TV mount/stand Black", "brand": "Chief", "description": "Chief PWR2540S TV mount/stand Black\n\n\nAllows for viewing flexibility when installing a flat panel TV or monitor. A great choice for corporate and home entertainment applications. - Extends 24.88\" from wall and remains low profile in the home position - Q-Latch Mounting System secures flat panel to mount with a latching flag - Integrated lateral shift 6\" left and right (ships shifted 2.5\" to the left) - Centris Technology provides fingertip tilt adjustments - Mounting guides provided for a hassle-free installation - Provides positive latch in home position to keep screen tight to wall - CableTrac System provides a fast and effective way to route cables - UL listed for proven strength - Swivel up to 90° left or right (depending upon screen size)\n\n\nKey Specifications:\n- **Other features**: Screen size compatibility: 939.8 - 1397 mm (37 - 55\")\n- **Weight & dimensions**: Width: 600 mm; Depth: 86 mm; Height: 457 mm\n- **Design**: Product colour: Black; Housing material: Metal\n- **Ergonomics**: Tilt angle range: -15 - 5°; Swivel angle range: 0 - 90°\n- **Mounting**: Mounting type: Wall; Maximum weight capacity: 56.7 kg", "image_url": "https://images.icecat.biz/img/gallery_mediums/img_1676954_medium_1480996728_1651_6217.jpg", "price": 54.86, "currency": "EUR", "categories": ["TV Mounts & Stands"], "attrs": {"Mounting type": "Wall", "Maximum weight capacity": "56.7 kg", "Tilt angle range": "-15 - 5°", "Swivel angle range": "0 - 90°", "Product colour": "Black", "Housing material": "Metal", "Width": "600 mm", "Depth": "86 mm", "Height": "457 mm", "Screen size compatibility": "939.8 - 1397 mm (37 - 55\")"}, "attr_keys": ["Depth", "Height", "Housing material", "Maximum weight capacity", "Mounting type", "Product colour", "Screen size compatibility", "Swivel angle range", "Tilt angle range", "Width"]}
{"id": "5418946", "title": "Chief PIWRF2000B TV mount/stand 180.3 cm (71\") Black", "brand": "Chief", "description": "Chief PIWRF2000B TV mount/stand 180.3 cm (71\") Black\n\n\n- Limitless centering on the wall between 16\" center studs without cutting studs - Low profile design ensures the mount remains concealed behind the flat panel - Centris Technology uses the center of gravity to achieve smooth, fingertip tilt - ClickConnect Technology provides an audible click to confirm the flat panel is locked in place - Easy connect/disconnect with no tools needed - Screen can be installed in portrait or landscape orientation ( PAC400 accessory can be used to rotate without removing the screen) - Integrated cable management\n\n\nKey Specifications:\n- **Other features**: Screen size compatibility: 1066.8 - 1803.4 mm (42 - 71\")\n- **Weight & dimensions**: Width: 518 mm; Depth: 141 mm; Height: 580 mm\n- **Design**: Product colour: Black; Housing material: Metal; Compatibility: LCD\n- **Ergonomics**: Tilt angle range: -15 - 2°; Distance to the wall (max): 38.1 cm; Distance to the wall (min): 4.32 cm\n- **Mounting**: Maximum screen size: 180.3 cm (71\"); Mounting type: Wall; Maximum weight capacity: 90.7 kg; Minimum VESA mount: 200 x 200 mm; Maximum VESA mount: 200 x 200 mm; Minimum screen size: 106.7 cm (42\")", "image_url": "https://images.icecat.biz/img/gallery_mediums/img_5418946_medium_1481188395_6093_8183.jpg", "price": 51.59, "currency": "EUR", "categories": ["TV Mounts & Stands"], "attrs": {"Maximum screen size": "180.3 cm (71\")", "Mounting type": "Wall", "Maximum weight capacity": "90.7 kg", "Minimum VESA mount": "200 x 200 mm", "Maximum VESA mount": "200 x 200 mm", "Minimum screen size": "106.7 cm (42\")", "Tilt angle range": "-15 - 2°", "Distance to the wall (max)": "38.1 cm", "Distance to the wall (min)": "4.32 cm", "Product colour": "Black", "Housing material": "Metal", "Compatibility": "LCD", "Width": "518 mm", "Depth": "141 mm", "Height": "580 mm", "Screen size compatibility": "1066.8 - 1803.4 mm (42 - 71\")"}, "attr_keys": ["Compatibility", "Depth", "Distance to the wall (max)", "Distance to the wall (min)", "Height", "Housing material", "Maximum VESA mount", "Maximum screen size", "Maximum weight capacity", "Minimum VESA mount", "Minimum screen size", "Mounting type", "Product colour", "Screen size compatibility", "Tilt angle range", "Width"]}
